Workbook

Sheet Dashboard
A1: x | F1: Financial Dashboard
F2: Income Statement | H2: 2024 | I2: 2025-F | J2: 2026-F | K2: 2027-F
F3: =Charts!H8 -> Revenue | H3: =Charts!J16 -> 7078783.1 | I3: =Charts!K16 -> 14671987 | J3: =Charts!L16 -> 66233629 | K3: =Charts!M16 -> 1.7811425e+08 | N3: =+J3-I3 -> 51561642
G4: =Charts!I9 -> VA Mental Health | H4: =Charts!J9 -> 6970768.1 | I4: =Charts!K9 -> 10955547 | J4: =Charts!L9 -> 17132940 | K4: =Charts!M9 -> 21077100
G5: =Charts!I10 -> VA Medical Exams | H5: =Charts!J10 -> 108015 | I5: =Charts!K10 -> 1040988 | J5: =Charts!L10 -> 4956620 | K5: =Charts!M10 -> 9468620
G6: =Charts!I11 -> Personal Injury | H6: =Charts!J11 -> 0 | I6: =Charts!K11 -> 2547952 | J6: =Charts!L11 -> 27817425 | K6: =Charts!M11 -> 50932946
G7: =Charts!I12 -> Workers Comp | H7: =Charts!J12 -> 0 | I7: =Charts!K12 -> 127500 | J7: =Charts!L12 -> 7650000 | K7: =Charts!M12 -> 19890000
G8: =Charts!I13 -> SaaS | H8: =Charts!J13 -> 0 | I8: =Charts!K13 -> 0 | J8: =Charts!L13 -> 1125419.1 | K8: =Charts!M13 -> 9514199.7
G9: =Charts!I14 -> Corrections | H9: =Charts!J14 -> 0 | I9: =Charts!K14 -> 0 | J9: =Charts!L14 -> 7514100 | K9: =Charts!M14 -> 65531400
G10: =Charts!I15 -> Healthcare Compliance | H10: =Charts!J15 -> 0 | I10: =Charts!K15 -> 0 | J10: =Charts!L15 -> 37125 | K10: =Charts!M15 -> 1699987.5
F11: =Charts!H17 -> COGS | H11: =Charts!J17 -> 4503867 | I11: =Charts!K17 -> 6758123.6 | J11: =Charts!L17 -> 22489378 | K11: =Charts!M17 -> 91956882 | Q11: 26 - $10mm rev growth (all PI)
F12: =Charts!H18 -> Gross Profit | H12: =Charts!J18 -> 2574916.1 | I12: =Charts!K18 -> 7913863.4 | J12: =Charts!L18 -> 43744250 | K12: =Charts!M18 -> 86157371 | Q12: 50% margin on PI - $5mm ($10mm receivable waiting to collect)
G13: =Charts!I19 -> Gross Margin | H13: =Charts!J19 -> 0.36375123 | I13: =Charts!K19 -> 0.53938593 | J13: =Charts!L19 -> 0.66045378 | K13: =Charts!M19 -> 0.48371969 | Q13: QV version - $7.5mm capital / rev growth to PI ($5mm-->$10mm work)
F15: =Charts!H20 -> Expenses | H15: =Charts!J25 -> 1630675 | I15: =Charts!K25 -> 2394328.7 | J15: =Charts!L25 -> 10536978 | K15: =Charts!M25 -> 11217840 | N15: =+J15-I15 -> 8142649.6 | Q15: Risk - make assumption 18 months on receivable vs. 9 months
G16: =Charts!I21 -> Technology | H16: =Charts!J21 -> 171650 | I16: =Charts!K21 -> 182487.04 | J16: =Charts!L21 -> 882042.71 | K16: =Charts!M21 -> 1066909.4
G17: =Charts!I22 -> Marketing & Development | H17: =Charts!J22 -> 534189 | I17: =Charts!K22 -> 346185.62 | J17: =Charts!L22 -> 3995196.5 | K17: =Charts!M22 -> 4223961.5
G18: =Charts!I23 -> Clinical Operations | H18: =Charts!J23 -> 229668 | I18: =Charts!K23 -> 349120.43 | J18: =Charts!L23 -> 2264444.5 | K18: =Charts!M23 -> 1886865.7
G19: =Charts!I24 -> General Administrative | H19: =Charts!J24 -> 695168 | I19: =Charts!K24 -> 1516535.7 | J19: =Charts!L24 -> 3395294.6 | K19: =Charts!M24 -> 4040103
F20: =Charts!H26 -> EBITDA | H20: =Charts!J26 -> 944241.07 | I20: =Charts!K26 -> 5519534.7 | J20: =Charts!L26 -> 33207272 | K20: =Charts!M26 -> 74939531
G21: =Charts!I27 -> EBITDA Margin | H21: =Charts!J27 -> 0.13339031 | I21: =Charts!K27 -> 0.37619544 | J21: =Charts!L27 -> 0.50136574 | K21: =Charts!M27 -> 0.42073854
F23: Balance Sheet | H23: 2024 | I23: 2025-F | J23: 2026-F | K23: 2027-F
F24: Assets | H24: =Charts!J32 -> 1258371 | I24: =Charts!K32 -> 7514289.2 | J24: =Charts!L32 -> 42780908 | K24: =Charts!M32 -> 1.237906e+08
G25: =Charts!I33 -> Cash | H25: =Charts!J33 -> 1257232 | I25: =Charts!K33 -> 2602593.6 | J25: =Charts!L33 -> 11389945 | K25: =Charts!M33 -> 64205898
G26: =Charts!I34 -> Accounts Receivable | H26: =Charts!J34 -> 0 | I26: =Charts!K34 -> 4907723.6 | J26: =Charts!L34 -> 31388191 | K26: =Charts!M34 -> 59583125
G27: =Charts!I35 -> Fixed Assets | H27: =Charts!J35 -> 1139 | I27: =Charts!K35 -> 3972 | J27: =Charts!L35 -> 2772 | K27: =Charts!M35 -> 1572
F28: Liabilities | H28: =Charts!J36 -> 198133 | I28: =Charts!K36 -> 2492984.6 | J28: =Charts!L36 -> 13345037 | K28: =Charts!M36 -> 33412669
G29: =Charts!I37 -> Current Liabilities | H29: =Charts!J37 -> 82446 | I29: =Charts!K37 -> 2446827.6 | J29: =Charts!L37 -> 13308156 | K29: =Charts!M37 -> 33385352
G30: =Charts!I38 -> Long-Term Liabilities | H30: =Charts!J38 -> 115687 | I30: =Charts!K38 -> 46157 | J30: =Charts!L38 -> 36881 | K30: =Charts!M38 -> 27317
F31: Equity | H31: =Charts!J39 -> 1060238 | I31: =Charts!K39 -> 5021304.5 | J31: =Charts!L39 -> 29435871 | K31: =Charts!M39 -> 90377926
F32: =Charts!H41 -> LIABILITIES AND EQUITY | H32: =Charts!J41 -> 1258371 | I32: =Charts!K41 -> 7514289.2 | J32: =Charts!L41 -> 42780908 | K32: =Charts!M41 -> 1.237906e+08

Sheet Monthly Financial Reports
B2: Profit & Loss Forecast
E3: 45292 | F3: 45323 | G3: 45352 | H3: 45383 | I3: 45413 | J3: 45444 | K3: 45474 | L3: 45505 | M3: 45536 | N3: 45566 | O3: 45597 | P3: 45627 | Q3: 45658 | R3: 45689 | S3: 45717 | T3: 45748 | U3: 45778 | V3: 45809 | W3: 45839 | X3: 45870 | Y3: 45901 | Z3: 45931 | AA3: 45962 | AB3: 45992 | AC3: 46023 | AD3: 46054 | AE3: 46082 | AF3: 46113 | AG3: 46143 | AH3: 46174 | AI3: 46204 | AJ3: 46235 | AK3: 46266 | AL3: 46296 | AM3: 46327 | AN3: 46357 | AO3: 46388 | AP3: 46419 | AQ3: 46447 | AR3: 46478 | AS3: 46508 | AT3: 46539 | AU3: 46569 | AV3: 46600 | AW3: 46631 | AX3: 46661 | AY3: 46692 | AZ3: 46722 | BB3: 2024 | BC3: 2025 | BD3: 2026 | BE3: 2027
C5: Revenue | E5: =SUM(E6:E7) -> 399264.35 | F5: =SUM(F6:F7) -> 416954.21 | G5: =SUM(G6:G7) -> 533761.66 | H5: =SUM(H6:H7) -> 540967.64 | I5: =SUM(I6:I7) -> 633262.09 | J5: =SUM(J6:J7) -> 604119.44 | K5: =SUM(K6:K7) -> 557899.1 | L5: =SUM(L6:L7) -> 693490.47 | ... P5: =SUM(P6:P7) -> 623942.57 | Q5: =SUM(Q6:Q13) -> 697873 | R5: =SUM(R6:R13) -> 605304 | S5: =SUM(S6:S13) -> 937772 | T5: =SUM(T6:T13) -> 850512 | U5: =SUM(U6:U13) -> 991397 | V5: =SUM(V6:V13) -> 951240 | W5: =SUM(W6:W13) -> 1034942.6 | X5: =SUM(X6:X13) -> 1263146.6 | ... AZ5: =SUM(AZ6:AZ13) -> 22051622 | BB5: =SUM(BB6:BB13) -> 7078783.1 | BC5: =SUM(BC6:BC13) -> 14671987 | BD5: =SUM(BD6:BD13) -> 66233629 | BE5: =SUM(BE6:BE13) -> 1.7811425e+08
D6: VA Mental Health | E6: 399264.35 | F6: 416954.21 | G6: 533761.66 | H6: 540967.64 | I6: 633262.09 | J6: 603034.44 | K6: 551879.1 | L6: 676335.47 | M6: 593998.91 | N6: 630918.38 | O6: 793259.25 | P6: 597132.57 | Q6: 666495 | R6: 567214 | S6: 880372 | T6: 775302 | U6: 863492 | V6: 721755 | W6: 735947 | X6: =Worksheet!N178 -> 1019370 | Y6: =Worksheet!O178 -> 1167210 | Z6: =Worksheet!P178 -> 1100220 | AA6: =Worksheet!Q178 -> 1208460 | AB6: =Worksheet!R178 -> 1249710 | AC6: =Worksheet!S178 -> 1277100 | AD6: =Worksheet!T178 -> 1304490 | AE6: =Worksheet!U178 -> 1331880 | ... AZ6: =Worksheet!AP178 -> 1907070 | BB6: =SUM(E6:P6) -> 6970768.1 | BC6: =SUM(Q6:AB6) -> 10955547 | BD6: =SUM(AC6:AN6) -> 17132940 | BE6: =SUM(AO6:AZ6) -> 21077100
D7: VA Medical Exams | J7: 1085 | K7: 6020 | L7: 17155 | M7: 18335 | N7: 14200 | O7: 24410 | P7: 26810 | Q7: 31378 | R7: 38090 | S7: 57400 | T7: 63200 | U7: 69600 | V7: 78800 | W7: 84000 | X7: =Worksheet!N179 -> 81780 | Y7: =Worksheet!O179 -> 84835 | Z7: =Worksheet!P179 -> 91885 | AA7: =Worksheet!Q179 -> 150635 | AB7: =Worksheet!R179 -> 209385 | AC7: =Worksheet!S179 -> 240718.33 | AD7: =Worksheet!T179 -> 272051.67 | AE7: =Worksheet!U179 -> 303385 | ... AZ7: =Worksheet!AP179 -> 961385 | BB7: =SUM(E7:P7) -> 108015 | BC7: =SUM(Q7:AB7) -> 1040988 | BD7: =SUM(AC7:AN7) -> 4956620 | BE7: =SUM(AO7:AZ7) -> 9468620
D8: Personal Injury | Q8: 0 | R8: 0 | S8: 0 | T8: 12010 | U8: 58305 | V8: =221000-U8-T8 -> 150685 | W8: =Worksheet!M181 -> 214995.6 | X8: =Worksheet!N181 -> 161996.6 | Y8: =Worksheet!O181 -> 284994.2 | Z8: =Worksheet!P181 -> 400991.8 | AA8: =Worksheet!Q181 -> 579988 | AB8: =Worksheet!R181 -> 683985.8 | AC8: =Worksheet!S181 -> 968980 | AD8: =Worksheet!T181 -> 1246974.2 | ... AZ8: =Worksheet!AP181 -> 4755901.6 | BC8: =SUM(Q8:AB8) -> 2547952 | BD8: =SUM(AC8:AN8) -> 27817425 | BE8: =SUM(AO8:AZ8) -> 50932946
D9: Workers Comp | Q9: 0 | R9: 0 | S9: 0 | T9: 0 | U9: 0 | V9: 0 | W9: =Worksheet!M182 -> 0 | X9: =Worksheet!N182 -> 0 | Y9: =Worksheet!O182 -> 0 | Z9: =Worksheet!P182 -> 0 | AA9: =Worksheet!Q182 -> 42500 | AB9: =Worksheet!R182 -> 85000 | AC9: =Worksheet!S182 -> 170000 | AD9: =Worksheet!T182 -> 255000 | ... AZ9: =Worksheet!AP182 -> 2125000 | BC9: =SUM(Q9:AB9) -> 127500 | BD9: =SUM(AC9:AN9) -> 7650000 | BE9: =SUM(AO9:AZ9) -> 19890000
D10: SaaS | Q10: 0 | R10: 0 | S10: 0 | T10: 0 | U10: 0 | V10: 0 | W10: =Worksheet!M188 -> 0 | X10: =Worksheet!N188 -> 0 | Y10: =Worksheet!O188 -> 0 | Z10: =Worksheet!P188 -> 0 | AA10: =Worksheet!Q188 -> 0 | AB10: =Worksheet!R188 -> 0 | AC10: =Worksheet!S188 -> 0 | AD10: =Worksheet!T188 -> 0 | ... AZ10: =Worksheet!AP188 -> 1327665.6 | BC10: =SUM(Q10:AB10) -> 0 | BD10: =SUM(AC10:AN10) -> 1125419.1 | BE10: =SUM(AO10:AZ10) -> 9514199.7
D11: Corrections | Q11: 0 | R11: 0 | S11: 0 | T11: 0 | U11: 0 | V11: 0 | W11: =Worksheet!M184 -> 0 | X11: =Worksheet!N184 -> 0 | Y11: =Worksheet!O184 -> 0 | Z11: =Worksheet!P184 -> 0 | AA11: =Worksheet!Q184 -> 0 | AB11: =Worksheet!R184 -> 0 | AC11: =Worksheet!S184 -> 0 | AD11: =Worksheet!T184 -> 0 | ... AZ11: =Worksheet!AP184 -> 10711800 | BC11: =SUM(Q11:AB11) -> 0 | BD11: =SUM(AC11:AN11) -> 7514100 | BE11: =SUM(AO11:AZ11) -> 65531400
D12: Healthcare Compliance | Q12: 0 | R12: 0 | S12: 0 | T12: 0 | U12: 0 | V12: 0 | W12: 0 | X12: 0 | Y12: 0 | Z12: 0 | AA12: 0 | AB12: 0 | AC12: 0 | AD12: 0 | AE12: 0 | AF12: 0 | AG12: 0 | AH12: 0 | AI12: =Worksheet!Y185 -> 0 | AJ12: =Worksheet!Z185 -> 0 | AK12: =Worksheet!AA185 -> 0 | AL12: =Worksheet!AB185 -> 6187.5 | AM12: =Worksheet!AC185 -> 12375 | AN12: =Worksheet!AD185 -> 18562.5 | AO12: =Worksheet!AE185 -> 41062.5 | AP12: =Worksheet!AF185 -> 57487.5 | ... AZ12: =Worksheet!AP185 -> 262800 | BC12: =SUM(Q12:AB12) -> 0 | BD12: =SUM(AC12:AN12) -> 37125 | BE12: =SUM(AO12:AZ12) -> 1699987.5
D13: Employee Wellness | Q13: 0 | R13: 0 | S13: 0 | T13: 0 | U13: 0 | V13: 0 | W13: =Worksheet!M186 -> 0 | X13: =Worksheet!N186 -> 0 | Y13: =Worksheet!O186 -> 0 | Z13: =Worksheet!P186 -> 0 | AA13: =Worksheet!Q186 -> 0 | AB13: =Worksheet!R186 -> 0 | AC13: =Worksheet!S186 -> 0 | AD13: =Worksheet!T186 -> 0 | ... AZ13: =Worksheet!AP186 -> 0 | BC13: =SUM(AM13:AX13) -> 0 | BD13: =SUM(AN13:AY13) -> 0 | BE13: =SUM(AO13:AZ13) -> 0
C15: COGS | Q15: 424809.87 | R15: 428219.25 | S15: 642221.25 | T15: 708475.86 | U15: 504172.01 | V15: 578488.93 | W15: 498680 | X15: 488960 | Y15: 513791 | Z15: 540930 | AA15: =Z15*AA5/Z5 -> 672839.02 | AB15: =AA15*AB5/AA5 -> 756536.42 | AC15: =AB15*AC5/AB5 -> 902105.84 | AD15: =AC15*AD5/AC5 -> 1045298.4 | AE15: =AD15*AE5/AD5 -> 1186793.4 | AF15: =AE15*AF5/AE5 -> 1324213.8 | AG15: =AF15*AG5/AF5 -> 1459257.4 | AH15: =AG15*AH5/AG5 -> 1602657.1 | ... AT15: =AS15*AT5/AS5 -> 4543005.3 | AU15: =Worksheet!AK85 -> 8204744 | AV15: =Worksheet!AL85 -> 10735816 | AW15: =Worksheet!AM85 -> 11617282 | AX15: =Worksheet!AN85 -> 11767926 | AY15: =Worksheet!AO85 -> 11922303 | AZ15: =AY15*AZ5/AY5 -> 13957141 | BB15: 4503867 | BC15: =SUM(Q15:AB15) -> 6758123.6 | BD15: =SUM(AC15:AN15) -> 22489378 | BE15: =SUM(AO15:AZ15) -> 91956882
C17: Gross Profit | Q17: =Q5-Q15 -> 273063.13 | R17: =R5-R15 -> 177084.75 | S17: =S5-S15 -> 295550.75 | T17: =T5-T15 -> 142036.14 | U17: =U5-U15 -> 487224.99 | V17: =V5-V15 -> 372751.07 | W17: =W5-W15 -> 536262.6 | X17: =X5-X15 -> 774186.6 | ... AZ17: =AZ5-AZ15 -> 8094480.8 | BB17: =BB5-BB15 -> 2574916.1 | BC17: =SUM(Q17:AB17) -> 7913863.4 | BD17: =BD5-BD15 -> 43744250 | BE17: =BE5-BE15 -> 86157371
D18: Gross Margin | Q18: =Q17/Q5 -> 0.39127912 | R18: =R17/R5 -> 0.29255506 | S18: =S17/S5 -> 0.3151627 | T18: =T17/T5 -> 0.16700075 | U18: =U17/U5 -> 0.49145296 | V18: =V17/V5 -> 0.39185807 | W18: =W17/W5 -> 0.51815685 | X18: =X17/X5 -> 0.61290321 | ... AZ18: =AZ17/AZ5 -> 0.36706963 | BB18: =BB17/BB5 -> 0.36375123 | BC18: =BC17/BC5 -> 0.53938593 | BD18: =BD17/BD5 -> 0.66045378 | BE18: =BE17/BE5 -> 0.48371969
C20: Expenses | Q20: =SUM(Q21:Q24) -> 174662.01 | R20: =SUM(R21:R24) -> 414778.49 | S20: =SUM(S21:S24) -> 199025.41 | T20: =SUM(T21:T24) -> 207571.94 | U20: =SUM(U21:U24) -> 32636.833 | V20: =SUM(V21:V24) -> 205117.9 | W20: =SUM(W21:W24) -> 175297.17 | X20: =SUM(X21:X24) -> 181987.5 | ... AZ20: =SUM(AZ21:AZ24) -> 998254.1 | BB20: =SUM(BB21:BB24) -> 1630675 | BC20: =SUM(Q20:AB20) -> 2394328.7 | BD20: =SUM(BD21:BD24) -> 10536978 | BE20: =SUM(BE21:BE24) -> 11217840
D21: Technology | Q21: 14719.81 | R21: 13757.56 | S21: 28920.28 | T21: 26873.24 | U21: 17173.83 | V21: 14673.57 | W21: =Worksheet!M26 -> 7728.125 | X21: =Worksheet!N26 -> 7728.125 | Y21: =Worksheet!O26 -> 7728.125 | Z21: =Worksheet!P26 -> 7728.125 | AA21: =Worksheet!Q26 -> 17728.125 | AB21: =Worksheet!R26 -> 17728.125 | AC21: =Worksheet!S26 -> 73184.375 | AD21: =Worksheet!T26 -> 48640.625 | ... AZ21: =Worksheet!AP26 -> 97796.458 | BB21: =96650+75000 -> 171650 | BC21: =SUM(Q21:AB21) -> 182487.04 | BD21: =SUM(AC21:AN21) -> 882042.71 | BE21: =SUM(AO21:AZ21) -> 1066909.4
D22: Marketing & Development | Q22: 31414.513 | R22: 32500.673 | S22: 48808.563 | T22: 31705.483 | U22: 21617.503 | V22: 22794.253 | W22: =Worksheet!M32 -> 26224.104 | X22: =Worksheet!N32 -> 26224.104 | Y22: =Worksheet!O32 -> 26224.104 | Z22: =Worksheet!P32 -> 26224.104 | AA22: =Worksheet!Q32 -> 26224.104 | AB22: =Worksheet!R32 -> 26224.104 | AC22: =Worksheet!S32 -> 147300.98 | AD22: =Worksheet!T32 -> 242300.98 | ... AZ22: =Worksheet!AP32 -> 318903.48 | BB22: =384189+150000 -> 534189 | BC22: =SUM(Q22:AB22) -> 346185.62 | BD22: =SUM(AC22:AN22) -> 3995196.5 | BE22: =SUM(AO22:AZ22) -> 4223961.5
D23: Clinical Operations | Q23: 26394.744 | R23: 26484.744 | S23: 26484.744 | T23: 26525.064 | U23: 26771.444 | V23: 26615.064 | W23: =Worksheet!M48 -> 26224.104 | X23: =Worksheet!N48 -> 26224.104 | Y23: =Worksheet!O48 -> 26224.104 | Z23: =Worksheet!P48 -> 26224.104 | AA23: =Worksheet!Q48 -> 26224.104 | AB23: =Worksheet!R48 -> 58724.104 | AC23: =Worksheet!S48 -> 125600.28 | AD23: =Worksheet!T48 -> 200600.28 | ... AZ23: =Worksheet!AP48 -> 234562.16 | BB23: =17668+212000 -> 229668 | BC23: =SUM(Q23:AB23) -> 349120.43 | BD23: =SUM(AC23:AN23) -> 2264444.5 | BE23: =SUM(AO23:AZ23) -> 1886865.7
D24: General Administrative | Q24: 102132.94 | R24: 342035.51 | S24: 94811.824 | T24: 122468.15 | U24: -32925.944 | V24: 141035.01 | W24: =Worksheet!M56 -> 115120.83 | X24: =Worksheet!N56 -> 121811.17 | Y24: =Worksheet!O56 -> 122731.17 | Z24: =Worksheet!P56 -> 128185 | AA24: =Worksheet!Q56 -> 129105 | AB24: =Worksheet!R56 -> 130025 | AC24: =Worksheet!S56 -> 261890.96 | AD24: =Worksheet!T56 -> 270519.08 | ... AZ24: =Worksheet!AP56 -> 346992 | BB24: =1651983-BB21-BB22-BB23-BB29-BB31-BB32 -> 695168 | BC24: =SUM(Q24:AB24) -> 1516535.7 | BD24: =SUM(AC24:AN24) -> 3395294.6 | BE24: =SUM(AO24:AZ24) -> 4040103
C26: EBITDA | Q26: =Q17-Q20 -> 98401.12 | R26: =R17-R20 -> -237693.74 | S26: =S17-S20 -> 96525.34 | T26: =T17-T20 -> -65535.8 | U26: =U17-U20 -> 454588.16 | V26: =V17-V20 -> 167633.18 | W26: =W17-W20 -> 360965.43 | X26: =X17-X20 -> 592199.1 | ... AZ26: =AZ17-AZ20 -> 7096226.7 | BB26: =BB17-BB20 -> 944241.07 | BC26: =BC17-BC20 -> 5519534.7 | BD26: =BD17-BD20 -> 33207272 | BE26: =BE17-BE20 -> 74939531
D27: EBIT Margin | Q27: =Q26/Q$5 -> 0.14100147 | R27: =R26/R$5 -> -0.3926849 | S27: =S26/S$5 -> 0.1029305 | T27: =T26/T$5 -> -0.077054527 | U27: =U26/U$5 -> 0.45853292 | V27: =V26/V$5 -> 0.17622596 | W27: =W26/W$5 -> 0.34877822 | X27: =X26/X5 -> 0.46882848 | Y27: =Y26/Y5 -> 0.54672691 | Z27: =Z26/Z5 -> 0.54221782 | AA27: =AA26/AA5 -> 0.55988704 | AB27: =AB26/AB5 -> 0.55601352 | AC27: =AC26/AC5 -> 0.43161571 | AD27: =AD26/AD5 -> 0.4129121 | AE27: =AE26/AE5 -> 0.38308214 | ... AZ27: =AZ26/AZ5 -> 0.32180067 | BB27: =BB26/BB5 -> 0.13339031 | BC27: =BC26/BC5 -> 0.37619544 | BD27: =BD26/BD5 -> 0.50136574 | BE27: =BE26/BE5 -> 0.42073854
D29: Interest Expense | Q29: 750 | R29: 750 | S29: 750 | T29: 750 | U29: 750 | V29: 750 | W29: 750 | X29: =W29-2 -> 748 | Y29: =X29-2 -> 746 | Z29: =Y29-2 -> 744 | AA29: =Z29-2 -> 742 | AB29: =AA29-2 -> 740 | AC29: =AB29-2 -> 738 | AD29: =AC29-2 -> 736 | AE29: =AD29-2 -> 734 | ... AZ29: =AY29-2 -> 692 | BB29: 11108 | BC29: =SUM(Q29:AB29) -> 8970 | BD29: =SUM(AC29:AN29) -> 8724 | BE29: =SUM(AO29:AZ29) -> 8436
A30: 0.259 | D30: Income Tax | W30: =$A30*W26 -> 93490.047 | X30: =$A30*X26 -> 153379.57 | Y30: =$A30*Y26 -> 217648.24 | Z30: =$A30*Z26 -> 223725.62 | AA30: =$A30*AA26 -> 287350.83 | AB30: =$A30*AB26 -> 320860.35 | AC30: =$A30*AC26 -> 296999.42 | AD30: =$A30*AD26 -> 329229.52 | ... AZ30: =$A30*AZ26 -> 1837922.7 | BC30: =SUM(Q30:AB30) -> 1296454.6 | BD30: =SUM(AC30:AN30) -> 8600683.4 | BE30: =SUM(AO30:AZ30) -> 19409339
D31: Depreciation | Q31: 100 | R31: 100 | S31: 100 | T31: 100 | U31: 100 | V31: 100 | W31: 100 | X31: =W31 -> 100 | Y31: =X31 -> 100 | Z31: =Y31 -> 100 | AA31: =Z31 -> 100 | AB31: =AA31 -> 100 | AC31: =AB31 -> 100 | AD31: =AC31 -> 100 | AE31: =AD31 -> 100 | ... AZ31: =AY31 -> 100 | BB31: 1200 | BC31: =SUM(Q31:AB31) -> 1200 | BD31: =SUM(AC31:AN31) -> 1200 | BE31: =SUM(AO31:AZ31) -> 1200
D32: Amortization | Q32: =1500-Q29 -> 750 | R32: =1500-R29 -> 750 | S32: =1500-S29 -> 750 | T32: =1500-T29 -> 750 | U32: =1500-U29 -> 750 | V32: =1500-V29 -> 750 | W32: =1500-W29 -> 750 | X32: =1500-X29 -> 752 | ... AZ32: =1500-AZ29 -> 808 | BB32: 9000 | BC32: =SUM(Q32:AB32) -> 9030 | BD32: =SUM(AC32:AN32) -> 9276 | BE32: =SUM(AO32:AZ32) -> 9564
C34: Net Income | Q34: =Q26-SUM(Q29:Q32) -> 96801.12 | R34: =R26-SUM(R29:R32) -> -239293.74 | S34: =S26-SUM(S29:S32) -> 94925.34 | T34: =T26-SUM(T29:T32) -> -67135.8 | U34: =U26-SUM(U29:U32) -> 452988.16 | V34: =V26-SUM(V29:V32) -> 166033.18 | W34: =W26-SUM(W29:W32) -> 265875.39 | X34: =X26-SUM(X29:X32) -> 437219.53 | ... AZ34: =AZ26-SUM(AZ29:AZ32) -> 5256704 | BB34: =BB26-SUM(BB29:BB32) -> 922933.07 | BC34: =BC26-SUM(BC29:BC32) -> 4203880 | BD34: =BD26-SUM(BD29:BD32) -> 24587389 | BE34: =BE26-SUM(BE29:BE32) -> 55510993
D35: Net Margin | Q35: =Q34/Q$5 -> 0.13870879 | R35: =R34/R$5 -> -0.3953282 | S35: =S34/S$5 -> 0.10122433 | T35: =T34/T$5 -> -0.078935747 | U35: =U34/U$5 -> 0.45691903 | V35: =V34/V$5 -> 0.17454394 | W35: =W34/W$5 -> 0.25689868 | X35: =X34/X$5 -> 0.34613523 | ... AZ35: =AZ34/AZ$5 -> 0.23838174 | BB35: =BB34/BB$5 -> 0.13038019 | BC35: =BC34/BC$5 -> 0.28652425 | BD35: =BD34/BD$5 -> 0.37122213 | BE35: =BE34/BE$5 -> 0.31165946
B38: Cashflow Forecast
Q39: 45658 | R39: 45689 | S39: 45717 | T39: 45748 | U39: 45778 | V39: 45809 | W39: 45839 | X39: 45870 | Y39: 45901 | Z39: 45931 | AA39: 45962 | AB39: 45992 | AC39: 46023 | AD39: 46054 | AE39: 46082 | AF39: 46113 | AG39: 46143 | AH39: 46174 | AI39: 46204 | AJ39: 46235 | AK39: 46266 | AL39: 46296 | AM39: 46327 | AN39: 46357 | AO39: 46388 | AP39: 46419 | AQ39: 46447 | AR39: 46478 | AS39: 46508 | AT39: 46539 | AU39: 46569 | AV39: 46600 | AW39: 46631 | AX39: 46661 | AY39: 46692 | AZ39: 46722 | BB39: 2024 | BC39: 2025 | BD39: 2026 | BE39: 2027
C41: Starting Cash | Q41: 1257232 | R41: =Q58 -> 1337303.1 | S41: =R58 -> 1111183.4 | T41: =S58 -> 1210604.1 | U41: =T58 -> 615697.93 | V41: =U58 -> 985758.14 | W41: =V58 -> 994792.37 | X41: =W58 -> 907889.66 | Y41: =X58 -> 1040575.4 | ... AZ41: =AY58 -> 57776987 | BB41: 299151 | BC41: =BB58 -> 1257232.1 | BD41: =AC41 -> 2602593.6 | BE41: =AO41 -> 11389945
D43: Net Income | Q43: =Q34 -> 96801.12 | R43: =R34 -> -239293.74 | S43: =S34 -> 94925.34 | T43: =T34 -> -67135.8 | U43: =U34 -> 452988.16 | V43: =V34 -> 166033.18 | W43: =W34 -> 265875.39 | X43: =X34 -> 437219.53 | ... AZ43: =AZ34 -> 5256704 | BB43: =BB34 -> 922933.07 | BC43: =SUM(Q43:AB43) -> 4203880 | BD43: =SUM(AC43:AN43) -> 24587389 | BE43: =SUM(AO43:AZ43) -> 55510993
D44: Recievables | T44: =-T8 -> -12010 | U44: =-U8 -> -58305 | V44: =-V8 -> -150685 | W44: =-Worksheet!M121 -> -1012535.3 | X44: =-Worksheet!N121 -> -1263146.6 | Y44: =-Worksheet!O121 -> -1537039.2 | Z44: =-Worksheet!P121 -> -1593096.8 | AA44: =-Worksheet!Q121 -> -1981583 | AB44: =-Worksheet!R121 -> -2228080.8 | AC44: =-Worksheet!S121 -> -2656798.3 | AD44: =-Worksheet!T121 -> -3078515.9 | ... AZ44: =-Worksheet!AP121 -> -20723957 | BC44: =SUM(Q44:AB44) -> -9836481.7 | BD44: =SUM(AC44:AN44) -> -65108210 | BE44: =SUM(AO44:AZ44) -> -1.6860005e+08
D45: Payables - COGS | W45: =Worksheet!M143 -> 512450.74 | X45: =Worksheet!N143 -> 642295 | Y45: =Worksheet!O143 -> 775265 | Z45: =Worksheet!P143 -> 792840 | AA45: =Worksheet!Q143 -> 974540 | AB45: =Worksheet!R143 -> 1088115 | AC45: =Worksheet!S143 -> 1286440 | AD45: =Worksheet!T143 -> 1481765 | ... AZ45: =Worksheet!AP143 -> 13913755 | BB45: 24948 | BC45: =SUM(Q45:AB45) -> 4785505.7 | BD45: =SUM(AC45:AN45) -> 33945930 | BE45: =SUM(AO45:AZ45) -> 105563495
D46: Net Contribution Cash | Q46: -22412 | R46: 2113 | S46: -39368 | T46: 3983 | U46: 345 | V46: -1269 | W46: =Worksheet!M117 -> 25449.146 | X46: =Worksheet!N117 -> 180381.63 | Y46: =Worksheet!O117 -> 265921.55 | Z46: =Worksheet!P117 -> 352096.71 | AA46: =Worksheet!Q117 -> 378001.71 | AB46: =Worksheet!R117 -> 223976.71 | AC46: =Worksheet!S117 -> 292739.42 | AD46: =Worksheet!T117 -> 270612.12 | ... AZ46: =Worksheet!AP117 -> 6148968.8 | BC46: =SUM(Q46:AB46) -> 1369219.4 | BD46: =SUM(AC46:AN46) -> 8083934 | BE46: =SUM(AO46:AZ46) -> 49657860
A47: 0.25 | D47: Net Expense Cash | Q47: =Worksheet!G23*'Monthly Financial Reports'!$A47 -> 0 | R47: =Worksheet!H23*'Monthly Financial Reports'!$A47 -> 0 | S47: =Worksheet!I23*'Monthly Financial Reports'!$A47 -> 12004.354 | T47: =Worksheet!J23*'Monthly Financial Reports'!$A47 -> 3477.6562 | U47: =Worksheet!K23*'Monthly Financial Reports'!$A47 -> 3220.0521 | V47: =Worksheet!L23*'Monthly Financial Reports'!$A47 -> 3220.0521 | W47: =Worksheet!M23*'Monthly Financial Reports'!$A47 -> 23937.25 | X47: =Worksheet!N23*'Monthly Financial Reports'!$A47 -> 1672.5833 | ... AZ47: =Worksheet!AP23*'Monthly Financial Reports'!$A47 -> 10301.042 | BC47: =SUM(Q47:AB47) -> 52085.406 | BD47: =SUM(AC47:AN47) -> 152328 | BE47: =SUM(AO47:AZ47) -> 52675.208
D48: Income Tax | W48: =W30 -> 93490.047 | X48: =X30 -> 153379.57 | Y48: =Y30 -> 217648.24 | Z48: =Z30 -> 223725.62 | AA48: =AA30 -> 287350.83 | AB48: =AB30 -> 320860.35 | AC48: =AC30 -> 296999.42 | AD48: =AD30 -> 329229.52 | ... AZ48: =AZ30 -> 1837922.7 | BC48: =SUM(Q48:AB48) -> 1296454.6 | BD48: =SUM(AC48:AN48) -> 8600683.4 | BE48: =SUM(AO48:AZ48) -> 19409339
D49: Taxes Paid | AF49: =-SUM(Q48:AB48) -> -1296454.6 | AR49: =-SUM(AC48:AN48) -> -8600683.4 | BC49: =SUM(Q49:AB49) -> 0 | BD49: =SUM(AC49:AN49) -> -1296454.6 | BE49: =SUM(AO49:AZ49) -> -8600683.4
D50: Interest Expense | Q50: =-Q29 -> -750 | R50: =-R29 -> -750 | S50: =-S29 -> -750 | T50: =-T29 -> -750 | U50: =-U29 -> -750 | V50: =-V29 -> -750 | W50: =-W29 -> -750 | X50: =-X29 -> -748 | ... AZ50: =-AZ29 -> -692 | BC50: =SUM(Q50:AB50) -> -8970 | BD50: =SUM(AC50:AN50) -> -8724 | BE50: =SUM(AO50:AZ50) -> -8436
D51: Depreciation | Q51: =Q31 -> 100 | R51: =R31 -> 100 | S51: =S31 -> 100 | T51: =T31 -> 100 | U51: =U31 -> 100 | V51: =V31 -> 100 | W51: =W31 -> 100 | X51: =X31 -> 100 | ... AZ51: =AZ31 -> 100 | BB51: =BB31 -> 1200 | BC51: =SUM(Q51:AB51) -> 1200 | BD51: =SUM(AC51:AN51) -> 1200 | BE51: =SUM(AO51:AZ51) -> 1200
D52: Amortization | Q52: =Q32 -> 750 | R52: =R32 -> 750 | S52: =S32 -> 750 | T52: =T32 -> 750 | U52: =U32 -> 750 | V52: =V32 -> 750 | W52: =W32 -> 750 | X52: =X32 -> 752 | ... AZ52: =AZ32 -> 808 | BB52: =BB32 -> 9000 | BC52: =SUM(Q52:AB52) -> 9030 | BD52: =SUM(AC52:AN52) -> 9276 | BE52: =SUM(AO52:AZ52) -> 9564
D53: Net Credit Card | Q53: =82466-74030 -> 8436 | R53: =R72-Q72 -> 12372 | S53: =S72-R72 -> 38526 | T53: =T72-S72 -> -39613 | U53: =U72-T72 -> -24952 | V53: =V72-U72 -> 4894 | W53: 15000 | X53: -18000 | Z53: 0 | BC53: =SUM(Q53:AB53) -> -3337 | BD53: =SUM(AC53:AN53) -> 0 | BE53: =SUM(AO53:AZ53) -> 0
D54: Owner's Draw | Q54: -2854 | R54: -1411 | S54: -6767 | T54: =-3708-450000 -> -453708 | U54: -3336 | V54: -13259 | W54: -10670 | X54: -1220 | Y54: =-Staffing!S4 -> 0 | Z54: =-Staffing!T4 -> 0 | AA54: =-Staffing!U4 -> 0 | AB54: =-Staffing!V4 -> 0 | AC54: =-Staffing!W4 -> -15000 | AD54: =-Staffing!X4 -> -15000 | AE54: =-Staffing!Y4 -> -15000 | AF54: =-Staffing!Z4 -> -15000 | ... AZ54: =-Staffing!AT4 -> -15000 | BC54: =SUM(Q54:AB54) -> -493225 | BD54: =SUM(AC54:AN54) -> -180000 | BE54: =SUM(AO54:AZ54) -> -180000
D55: Capital Raise | BC55: =SUM(Q55:AB55) -> 0 | BD55: =SUM(AC55:AN55) -> 0 | BE55: =SUM(AO55:AZ55) -> 0
D56: Loan Principal | T56: -30000 | BC56: =SUM(Q56:AB56) -> -30000 | BD56: =SUM(AC56:AN56) -> 0 | BE56: =SUM(AO56:AZ56) -> 0
C58: Ending Cash | Q58: =SUM(Q41:Q57) -> 1337303.1 | R58: =SUM(R41:R57) -> 1111183.4 | S58: =SUM(S41:S57) -> 1210604.1 | T58: =SUM(T41:T57) -> 615697.93 | U58: =SUM(U41:U57) -> 985758.14 | V58: =SUM(V41:V57) -> 994792.37 | W58: =SUM(W41:W57) -> 907889.66 | X58: =SUM(X41:X57) -> 1040575.4 | ... AZ58: =SUM(AZ41:AZ57) -> 64205898 | BB58: =SUM(BB41:BB57) -> 1257232.1 | BC58: =SUM(BC41:BC57) -> 2602593.6 | BD58: =SUM(BD41:BD57) -> 11389945 | BE58: =SUM(BE41:BE57) -> 64205898
B61: Balance Sheet Forecast
Q62: 45658 | R62: 45689 | S62: 45717 | T62: 45748 | U62: 45778 | V62: 45809 | W62: 45839 | X62: 45870 | Y62: 45901 | Z62: 45931 | AA62: 45962 | AB62: 45992 | AC62: 46023 | AD62: 46054 | AE62: 46082 | AF62: 46113 | AG62: 46143 | AH62: 46174 | AI62: 46204 | AJ62: 46235 | AK62: 46266 | AL62: 46296 | AM62: 46327 | AN62: 46357 | AO62: 46388 | AP62: 46419 | AQ62: 46447 | AR62: 46478 | AS62: 46508 | AT62: 46539 | AU62: 46569 | AV62: 46600 | AW62: 46631 | AX62: 46661 | AY62: 46692 | AZ62: 46722 | BB62: 2024 | BC62: 2025 | BD62: 2026 | BE62: 2027
C64: ASSETS | Q64: =Q65+Q68 -> 1341775.1 | R64: =R65+R68 -> 1115655.4 | S64: =S65+S68 -> 1215076.1 | T64: =T65+T68 -> 632179.93 | U64: =U65+U68 -> 1060545.1 | V64: =V65+V68 -> 1220264.4 | W64: =W65+W68 -> 2588244.4 | X64: =X65+X68 -> 3208641 | ... AZ64: =AZ65+AZ68 -> 1.237906e+08 | BB64: =BB65+BB68 -> 1258371 | BC64: =AB64 -> 7514289.2 | BD64: =AN64 -> 42780908 | BE64: =AZ64 -> 1.237906e+08
C65: Current Assets | Q65: =Q66+Q67 -> 1337303.1 | R65: =R66+R67 -> 1111183.4 | S65: =S66+S67 -> 1210604.1 | T65: =T66+T67 -> 627707.93 | U65: =U66+U67 -> 1056073.1 | V65: =V66+V67 -> 1215792.4 | W65: =W66+W67 -> 2583772.4 | X65: =X66+X67 -> 3204269 | ... AZ65: =AZ66+AZ67 -> 1.2378902e+08 | BB65: =BB66+BB67 -> 1257232 | BC65: =AB65 -> 7510317.2 | BD65: =AN65 -> 42778136 | BE65: =AZ65 -> 1.2378902e+08
D66: Cash | Q66: =Q58 -> 1337303.1 | R66: =R58 -> 1111183.4 | S66: =S58 -> 1210604.1 | T66: =T58 -> 615697.93 | U66: =U58 -> 985758.14 | V66: =V58 -> 994792.37 | W66: =W58 -> 907889.66 | X66: =X58 -> 1040575.4 | ... AZ66: =AZ58 -> 64205898 | BB66: 1257232 | BC66: =AB66 -> 2602593.6 | BD66: =AN66 -> 11389945 | BE66: =AZ66 -> 64205898
D67: Accounts Receivable | T67: =-T44 -> 12010 | U67: =T67-U44 -> 70315 | V67: =U67-V44 -> 221000 | W67: =Worksheet!M131 -> 1675882.7 | X67: =Worksheet!N131 -> 2163693.6 | Y67: =Worksheet!O131 -> 2744808 | Z67: =Worksheet!P131 -> 3162834.8 | AA67: =Worksheet!Q131 -> 3925867.8 | AB67: =Worksheet!R131 -> 4907723.6 | AC67: =Worksheet!S131 -> 6130291.9 | AD67: =Worksheet!T131 -> 7592712.8 | ... AZ67: =Worksheet!AP131 -> 59583125 | BB67: =Worksheet!AR131 -> 0 | BC67: =AB67 -> 4907723.6 | BD67: =AN67 -> 31388191 | BE67: =AZ67 -> 59583125
C68: Fixed Assets | Q68: =4572-Q51 -> 4472 | R68: =4572-R51 -> 4472 | S68: =4572-S51 -> 4472 | T68: =4572-T51 -> 4472 | U68: =4572-U51 -> 4472 | V68: =4572-V51 -> 4472 | W68: =4572-W51 -> 4472 | X68: =W68-X51 -> 4372 | Y68: =X68-Y51 -> 4272 | Z68: =Y68-Z51 -> 4172 | AA68: =Z68-AA51 -> 4072 | AB68: =AA68-AB51 -> 3972 | AC68: =AB68-AC51 -> 3872 | AD68: =AC68-AD51 -> 3772 | AE68: =AD68-AE51 -> 3672 | ... AZ68: =AY68-AZ51 -> 1572 | BB68: 1139 | BC68: =AB68 -> 3972 | BD68: =AN68 -> 2772 | BE68: =AZ68 -> 1572
BC69: =AB69 -> 0 | BD69: =AN69 -> 0 | BE69: =AZ69 -> 0
C70: LIABILITIES | Q70: =Q71+Q75 -> 188717 | R70: =R71+R75 -> 199089 | S70: =S71+S75 -> 206614 | T70: =T71+T75 -> 136002 | U70: =U71+U75 -> 111050 | V70: =V71+V75 -> 115944 | W70: =W71+W75 -> 736135.79 | X70: =X71+X75 -> 1000607.6 | ... AZ70: =AZ71+AZ75 -> 33412669 | BB70: =BB71+BB75 -> 198133 | BC70: =AB70 -> 2492984.6 | BD70: =AN70 -> 13345037 | BE70: =AZ70 -> 33412669
C71: Current Liabilities | Q71: =Q72+Q73+Q74 -> 74030 | R71: =R72+R73+R74 -> 86402 | S71: =S72+S73+S74 -> 124928 | T71: =T72+T73+T74 -> 85315 | U71: =U72+U73+U74 -> 60363 | V71: =V72+V73+V74 -> 65257 | W71: =W72+W73+W74 -> 686198.79 | X71: =X72+X73+X74 -> 951422.61 | ... AZ71: =AZ72+AZ73+AZ74 -> 33385352 | BB71: =BB72+BB73+BB74 -> 82446 | BC71: =AB71 -> 2446827.6 | BD71: =AN71 -> 13308156 | BE71: =AZ71 -> 33385352
D72: Total Credit Cards | Q72: 74030 | R72: 86402 | S72: 124928 | T72: 85315 | U72: 60363 | V72: 65257 | W72: =65258+W53 -> 80258 | X72: =W72+X53 -> 62258 | Y72: =X72+Y53 -> 62258 | Z72: =Y72+Z53 -> 62258 | AA72: =Z72+AA53 -> 62258 | AB72: =AA72+AB53 -> 62258 | AC72: =AB72+AC53 -> 62258 | AD72: =AC72+AD53 -> 62258 | AE72: =AD72+AE53 -> 62258 | ... AZ72: =AY72+AZ53 -> 62258 | BB72: 82446 | BC72: =AB72 -> 62258 | BD72: =AN72 -> 62258 | BE72: =AZ72 -> 62258
D73: Accounts Payable | T73: =T45+S73 -> 0 | U73: =U45+T73 -> 0 | V73: =V45+U73 -> 0 | W73: =Worksheet!M153 -> 512450.74 | X73: =Worksheet!N153 -> 642295 | Y73: =Worksheet!O153 -> 775265 | Z73: =Worksheet!P153 -> 792840 | AA73: =Worksheet!Q153 -> 974540 | AB73: =Worksheet!R153 -> 1088115 | AC73: =Worksheet!S153 -> 1286440 | AD73: =Worksheet!T153 -> 1481765 | ... AZ73: =Worksheet!AP153 -> 13913755 | BC73: =AB73 -> 1088115 | BD73: =AN73 -> 4645215 | BE73: =AZ73 -> 13913755
D74: Taxes Payable | W74: =V74+W48+W49 -> 93490.047 | X74: =W74+X48+X49 -> 246869.61 | Y74: =X74+Y48+Y49 -> 464517.86 | Z74: =Y74+Z48+Z49 -> 688243.47 | AA74: =Z74+AA48+AA49 -> 975594.3 | AB74: =AA74+AB48+AB49 -> 1296454.6 | AC74: =AB74+AC48+AC49 -> 1593454.1 | AD74: =AC74+AD48+AD49 -> 1922683.6 | ... AZ74: =AY74+AZ48+AZ49 -> 19409339 | BB74: =BA74+BB48+BB49 -> 0 | BC74: =AB74 -> 1296454.6 | BD74: =AN74 -> 8600683.4 | BE74: =AZ74 -> 19409339
C75: Long-Term Liabilities | Q75: 114687 | R75: 112687 | S75: 81686 | T75: =80687+T56 -> 50687 | U75: =80687-30000 -> 50687 | V75: =80687-30000 -> 50687 | W75: =V75-W52 -> 49937 | X75: =W75-X52 -> 49185 | Y75: =X75-Y52 -> 48431 | Z75: =Y75-Z52 -> 47675 | AA75: =Z75-AA52 -> 46917 | AB75: =AA75-AB52 -> 46157 | AC75: =AB75-AC52 -> 45395 | AD75: =AC75-AD52 -> 44631 | ... AZ75: =AY75-AZ52 -> 27317 | BB75: 115687 | BC75: =AB75 -> 46157 | BD75: =AN75 -> 36881 | BE75: =AZ75 -> 27317
BC76: =AB76 -> 0 | BD76: =AN76 -> 0 | BE76: =AZ76 -> 0
C77: EQUITY | Q77: =SUM(Q78:Q83) -> 1153058.1 | R77: =SUM(R78:R83) -> 916566.38 | S77: =SUM(S78:S83) -> 1008462.1 | T77: =SUM(T78:T83) -> 496177.93 | U77: =SUM(U78:U83) -> 949495.14 | V77: =SUM(V78:V83) -> 1104320.4 | W77: =SUM(W78:W83) -> 1852108.6 | X77: =SUM(X78:X83) -> 2208033.4 | ... AZ77: =SUM(AZ78:AZ83) -> 90377926 | BB77: =SUM(BB78:BB83) -> 1060238 | BC77: =AB77 -> 5021304.5 | BD77: =AN77 -> 29435871 | BE77: =AZ77 -> 90377926
D78: Opening Balance Equity | Q78: 82500 | R78: 82500 | S78: 82500 | T78: 82500 | U78: 82500 | V78: 82500 | W78: 82500 | X78: 82500 | Y78: 82500 | Z78: 82500 | AA78: 82500 | AB78: 82500 | AC78: 82500 | AD78: 82500 | AE78: 82500 | AF78: 82500 | AG78: 82500 | AH78: 82500 | AI78: 82500 | AJ78: 82500 | AK78: 82500 | AL78: 82500 | AM78: 82500 | AN78: 82500 | AO78: 82500 | AP78: 82500 | AQ78: 82500 | AR78: 82500 | AS78: 82500 | AT78: 82500 | AU78: 82500 | AV78: 82500 | AW78: 82500 | AX78: 82500 | AY78: 82500 | AZ78: 82500 | BB78: 82500 | BC78: =AB78 -> 82500 | BD78: =AN78 -> 82500 | BE78: =AZ78 -> 82500
D79: Investment By Others | X79: =W79+X55 -> 0 | Z79: =Y79+Z55 -> 0 | AA79: =Z79+AA55 -> 0 | AB79: =AA79+AB55 -> 0 | AC79: =AB79+AC55 -> 0 | AD79: =AC79+AD55 -> 0 | AE79: =AD79+AE55 -> 0 | AF79: =AE79+AF55 -> 0 | AG79: =AF79+AG55 -> 0 | ... AZ79: =AY79+AZ55 -> 0 | BB79: =BA79+BB55 -> 0 | BC79: =AB79 -> 0 | BD79: =AN79 -> 0 | BE79: =AZ79 -> 0
D80: Cumulative Owners Draw | Q80: =R80+Q54 -> 58326 | R80: =S80+R54 -> 61180 | S80: =T80+S54 -> 62591 | T80: =U80+T54 -> 69358 | U80: =V80+U54 -> 523066 | V80: =W80+V54 -> 526402 | W80: =539661 -> 539661 | X80: =W80-X54 -> 540881 | Y80: =X80-Y54 -> 540881 | Z80: =Y80-Z54 -> 540881 | AA80: =Z80-AA54 -> 540881 | AB80: =AA80-AB54 -> 540881 | AC80: =AB80-AC54 -> 555881 | AD80: =AC80-AD54 -> 570881 | AE80: =AD80-AE54 -> 585881 | ... AZ80: =AY80-AZ54 -> 900881 | BB80: =55098+164643 -> 219741 | BC80: =AB80 -> 540881 | BD80: =AN80 -> 720881 | BE80: =AZ80 -> 900881
D81: Balancing | Q81: =Q64-Q70-SUM(Q78:Q80,Q83,Q82) -> 118810.08 | R81: =R64-R70-SUM(R78:R80,R83,R82) -> 118758.08 | S81: =S64-S70-SUM(S78:S80,S83,S82) -> 114317.43 | T81: =T64-T70-SUM(T78:T80,T83,T82) -> -337597.91 | U81: =U64-U70-SUM(U78:U80,U83,U82) -> -790976.86 | V81: =V64-V70-SUM(V78:V80,V83,V82) -> -805520.81 | W81: =W64-W70-SUM(W78:W80,W83,W82) -> -336866.99 | X81: =X64-X70-SUM(X78:X80,X83,X82) -> -419381.7 | ... AZ81: =AZ64-AZ70-SUM(AZ78:AZ80,AZ83,AZ82) -> 4295663.2 | BB81: -336158 | BD81: =AN81 -> -955399.68 | BE81: =AZ81 -> 4295663.2
D82: Retained Earnings | Q82: =R82-Q83 -> 796620.92 | R82: =S82-R83 -> 893422.04 | S82: =T82-S83 -> 654128.3 | T82: =U82-T83 -> 749053.64 | U82: =V82-U83 -> 681917.84 | V82: =1134906 -> 1134906 | W82: =V82+V83 -> 1300939.2 | X82: =W82+W83 -> 1566814.6 | Y82: =X82+X83 -> 2004034.1 | Z82: =Y82+Y83 -> 2625126.6 | AA82: =Z82+Z83 -> 3263606.4 | AB82: =AA82+AA83 -> 4084118.2 | AC82: =AB82+AB83 -> 5000500.9 | AD82: =AC82+AC83 -> 5848617.4 | ... AZ82: =AY82+AY83 -> 79842178 | BB82: 171158 | BC82: =Q82 -> 796620.92 | BD82: =AN82 -> 25986075 | BE82: =AZ82 -> 79842178
D83: Net Income | Q83: =Q43 -> 96801.12 | R83: =R43 -> -239293.74 | S83: =S43 -> 94925.34 | T83: =T43 -> -67135.8 | U83: =U43 -> 452988.16 | V83: =V43 -> 166033.18 | W83: =W43 -> 265875.39 | X83: =X43 -> 437219.53 | ... AZ83: =AZ43 -> 5256704 | BB83: 922997 | BC83: =BC34 -> 4203880 | BD83: =AN83 -> 3601814.3 | BE83: =AZ83 -> 5256704
C85: LIABILITIES AND EQUITY | Q85: =Q77+Q70 -> 1341775.1 | R85: =R77+R70 -> 1115655.4 | S85: =S77+S70 -> 1215076.1 | T85: =T77+T70 -> 632179.93 | U85: =U77+U70 -> 1060545.1 | V85: =V77+V70 -> 1220264.4 | W85: =W77+W70 -> 2588244.4 | X85: =X77+X70 -> 3208641 | ... AZ85: =AZ77+AZ70 -> 1.237906e+08 | BB85: =BB77+BB70 -> 1258371 | BC85: =AB85 -> 7514289.2 | BD85: =AN85 -> 42780908 | BE85: =AZ85 -> 1.237906e+08

Sheet Assumptions
B1: ASSUMPTIONS:
B3: General:
B4: G1 | C4: The model spans 4 years: 2024 - 2027. It includes both actual and forecasted financials.
B5: G2 | C5: The Financial outputs can be found in the "Dashboard" page highlited in red or the "Monthly Financial Reports" highlited in blue
B6: G3 | C6: The model uses the GAAP-approved acrural accounting method and treats taxes as if the company were a C-corp. At present the company is an S-Corp that manages its books on a cash basis. In transistioning from method to the other, there may be small inconsistencies.
B7: G4 | C7: The model is interactive. All assumption inputs are in boxed yellow cells. Changes to an assumption will flow through the entire model.
B8: G5 | C8: Most of the assumptions and calculations are inputted and performed on the "Worksheet" page highlited in green.
B10: Fund Raise:
B11: FR1 | C11: Input for the capital raised is on line 55 of the "Monthly Financial Reports."
B13: Staffing:
B14: S1 | C14: Staffing details and inputs are on the "Staffing" sheet highlited in yellow
B15: S2 | C15: Employees focused on one specific product are counted as COGS for that product. The remainder are counted as an expense by function.
B16: S3 | C16: The starting dates of all staff counted as COGS are driven by the start date of that product.
B17: S4 | C17: Starting dates for funcitional staff and all salaries are inputted manually on the staffing sheet.
B19: Product Rollout:
B20: PR1 | C20: Starting dates of the product rollout are inputted in Worksheet rows 6-18 and drive the calculations for the rest of the model
B21: PR2 | C21: There is a graphical representation of the rollout as a seperate sheet highlited in pink
B23: Expenses:
B24: EX1 | C24: Functional Expenses and overhead are tracked in Worksheet rows 20-83
B25: EX2 | C25: Most inputs are growth factors to existing expenses
B27: Taxes and Benefits:
B28: TB1 | C28: Payroll tax: 7.65% of gross salary - Input on "Staffing" sheet
B29: TB2 | C29: Average Employee Benefits: 16% of gross salary - Input in "Staffing" sheet.
B30: TB3 | C30: Federal and State Income tax: 25.9% of EBITDA - Input in "Monthly Financial Reports"
B31: TB4 | C31: For simplicity, model shows income taxes paid once a year in April. This is not going to be the case in reality.
B33: Summaries of Revenue, COGS and Accrual Adjustments:
B34: RCC1 | C34: Financial assumptions and calculations are inputted and performed per project in the in "Worksheet"
B35: RCC2 | C35: The Summaries of the Revenue, COGS and Accrual Adjustments are the results of those assumprtions and calculations.
B36: RCC3 | C36: The Summary of COGS is shown in Worksheet rows 85-115
B37: RCC4 | C37: The Summary of Revenues is shown in Worksheet rows 175-192
B38: RCC5 | C38: Accrual adjustments are summarized in Worksheet lines 117-173
B39: RCC6 | C39: The Income Statement is affected by the MONTHLY Receivables and Payables of each Product
B40: RCC7 | C40: The Balance Sheet is affected by MONTHLY Net Cash as well as CUMULATIVE recievables and payables of each product
B42: Product Assumptions and Calculations:
C43: VA Mental Health: Worksheet lines 196-236
C44: - Current product line, broken out by contract, financial assumptions based on actual data
C45: VA Medical Exams: Worksheet lines 238-271
C46: - Current product line, broken out by contract, projected assumptions based on actual data
C47: - Sharp increase in sales driven by addition of Loyal Source contract in August 2025
C48: Personal Injury: Worksheet lines 273-309
C49: - Current product line, financial assumptions based on actual data
C50: - 9 month recievable is key driver in cash driver of available cash
C51: - Start dates of PI-only staff managed in this section and are tied to growth of PI sales
C52: Workers Comp: Worksheet lines 311-337
C53: - Program started in August 2025
C54: SaaS: Worksheet lines 521-579
... C60: - EmpowerHC views Healthcare Compliance as a high-potential growth sector for 2028 and beyond (outside the timeframe of this model)

Sheet Worksheet
G1: 2025 | S1: 2026 | AE1: 2027 | AQ1: 2028 | BD1: Annual
G2: -5 | H2: -4 | I2: -3 | J2: -2 | K2: -1 | L2: 0 | M2: 1 | N2: 2 | O2: 3 | P2: 4 | Q2: 5 | R2: 6 | S2: 7 | T2: 8 | U2: 9 | V2: 10 | W2: 11 | X2: 12 | Y2: 13 | Z2: 14 | AA2: 15 | AB2: 16 | AC2: 17 | AD2: 18 | AE2: 19 | AF2: 20 | AG2: 21 | AH2: 22 | AI2: 23 | AJ2: 24 | AK2: 25 | AL2: 26 | AM2: 27 | AN2: 28 | AO2: 29 | AP2: 30 | AQ2: 31 | AR2: 32 | AS2: 33 | AT2: 34 | AU2: 35 | AV2: 36 | AW2: 37 | AX2: 38 | AY2: 39 | AZ2: 40 | BA2: 41 | BB2: 42
G3: 45658 | H3: 45689 | I3: 45717 | J3: 45748 | K3: 45778 | L3: 45809 | M3: 45839 | N3: 45870 | O3: 45901 | P3: 45931 | Q3: 45962 | R3: 45992 | S3: 46023 | T3: 46054 | U3: 46082 | V3: 46113 | W3: 46143 | X3: 46174 | Y3: 46204 | Z3: 46235 | AA3: 46266 | AB3: 46296 | AC3: 46327 | AD3: 46357 | AE3: 46388 | AF3: 46419 | AG3: 46447 | AH3: 46478 | AI3: 46508 | AJ3: 46539 | AK3: 46569 | AL3: 46600 | AM3: 46631 | AN3: 46661 | AO3: 46692 | AP3: 46722 | AQ3: 46753 | AR3: 46784 | AS3: 46813 | AT3: 46844 | AU3: 46874 | AV3: 46905 | AW3: 46935 | AX3: 46966 | AY3: 46997 | AZ3: 47027 | BA3: 47058 | BB3: 47088 | BD3: 2024 | BE3: 2025 | BF3: 2026 | BG3: 2027
L4: =L2 -> 0 | M4: =M2 -> 1 | N4: =N2 -> 2 | O4: =O2 -> 3 | P4: =P2 -> 4 | Q4: =Q2 -> 5 | R4: =R2 -> 6 | S4: =S2 -> 7 | ... BB4: =BB2 -> 42
A6: Product Rollout
C8: Launch Date | D8: Months Prep | E8: Start Prep
B9: VA - Mental Health | C9: 45292 | G9: =IF($C9<=G$3,1," ") -> 1 | H9: =IF($C9<=H$3,1," ") -> 1 | I9: =IF($C9<=I$3,1," ") -> 1 | J9: =IF($C9<=J$3,1," ") -> 1 | K9: =IF($C9<=K$3,1," ") -> 1 | L9: =IF($C9<=L$3,1," ") -> 1 | M9: =IF($C9<=M$3,1," ") -> 1 | N9: =IF($C9<=N$3,1," ") -> 1 | ... BB9: =IF($C9<=BB$3,1," ") -> 1
B10: VA - Medical Evaluations | C10: 45658 | G10: =IF($C10<=G$3,1," ") -> 1 | H10: =IF($C10<=H$3,1," ") -> 1 | I10: =IF($C10<=I$3,1," ") -> 1 | J10: =IF($C10<=J$3,1," ") -> 1 | K10: =IF($C10<=K$3,1," ") -> 1 | L10: =IF($C10<=L$3,1," ") -> 1 | M10: =IF($C10<=M$3,1," ") -> 1 | N10: =IF($C10<=N$3,1," ") -> 1 | ... BB10: =IF($C10<=BB$3,1," ") -> 1
B11: Personal Injury | C11: 45778 | G11: =IF($C11<=G$3,1," ") | H11: =IF($C11<=H$3,1," ") | I11: =IF($C11<=I$3,1," ") | J11: =IF($C11<=J$3,1," ") | K11: =IF($C11<=K$3,1," ") -> 1 | L11: =IF($C11<=L$3,1," ") -> 1 | M11: =IF($C11<=M$3,1," ") -> 1 | N11: =IF($C11<=N$3,1," ") -> 1 | ... BB11: =IF($C11<=BB$3,1," ") -> 1
B12: Workers Comp | C12: 45931 | D12: 3 | F12: =HLOOKUP(C12,M$3:AP$4,2,FALSE) -> 4 | M12: =IF($C12<=M$3,1," ") | N12: =IF($C12<=N$3,1," ") | O12: =IF($C12<=O$3,1," ") | P12: =IF($C12<=P$3,1," ") -> 1 | Q12: =IF($C12<=Q$3,1," ") -> 1 | R12: =IF($C12<=R$3,1," ") -> 1 | S12: =IF($C12<=S$3,1," ") -> 1 | T12: =IF($C12<=T$3,1," ") -> 1 | ... BB12: =IF($C12<=BB$3,1," ") -> 1
B13: SaaS | C13: 46174 | D13: 3 | F13: =HLOOKUP(C13,M$3:AP$4,2,FALSE) -> 12 | M13: =IF($C13<=M$3,1," ") | N13: =IF($C13<=N$3,1," ") | O13: =IF($C13<=O$3,1," ") | P13: =IF($C13<=P$3,1," ") | Q13: Starting to have expenses | S13: =IF($C13<=S$3,1," ") | T13: =IF($C13<=T$3,1," ") | U13: =IF($C13<=U$3,1," ") | V13: =IF($C13<=V$3,1," ") | W13: =IF($C13<=W$3,1," ") | X13: =IF($C13<=X$3,1," ") -> 1 | Y13: =IF($C13<=Y$3,1," ") -> 1 | Z13: =IF($C13<=Z$3,1," ") -> 1 | ... BB13: =IF($C13<=BB$3,1," ") -> 1
B14: Corrections | C14: 46204 | D14: 3 | F14: =HLOOKUP(C14,M$3:AP$4,2,FALSE) -> 13 | M14: =IF($C14<=M$3,1," ") | N14: =IF($C14<=N$3,1," ") | O14: =IF($C14<=O$3,1," ") | P14: =IF($C14<=P$3,1," ") | Q14: =IF($C14<=Q$3,1," ") | R14: =IF($C14<=R$3,1," ") | S14: =IF($C14<=S$3,1," ") | T14: =IF($C14<=T$3,1," ") | ... BB14: =IF($C14<=BB$3,1," ") -> 1
B15: Healthcare Compliance | C15: 46296 | D15: 3 | F15: =HLOOKUP(C15,M$3:AP$4,2,FALSE) -> 16 | M15: =IF($C15<=M$3,1," ") | N15: =IF($C15<=N$3,1," ") | O15: =IF($C15<=O$3,1," ") | P15: =IF($C15<=P$3,1," ") | Q15: =IF($C15<=Q$3,1," ") | R15: =IF($C15<=R$3,1," ") | S15: =IF($C15<=S$3,1," ") | T15: =IF($C15<=T$3,1," ") | ... BB15: =IF($C15<=BB$3,1," ") -> 1
B16: Employee Wellness | C16: 46753 | D16: 3 | M16: =IF($C16<=M$3,1," ") | N16: =IF($C16<=N$3,1," ") | O16: =IF($C16<=O$3,1," ") | P16: =IF($C16<=P$3,1," ") | Q16: =IF($C16<=Q$3,1," ") | R16: =IF($C16<=R$3,1," ") | S16: =IF($C16<=S$3,1," ") | T16: =IF($C16<=T$3,1," ") | ... BB16: =IF($C16<=BB$3,1," ") -> 1
B17: Data Analytics | C17: 46753 | D17: 3 | M17: =IF($C17<=M$3,1," ") | N17: =IF($C17<=N$3,1," ") | O17: =IF($C17<=O$3,1," ") | P17: =IF($C17<=P$3,1," ") | R17: =IF($C17<=R$3,1," ") | S17: =IF($C17<=S$3,1," ") | T17: =IF($C17<=T$3,1," ") | U17: =IF($C17<=U$3,1," ") | V17: =IF($C17<=V$3,1," ") | W17: =IF($C17<=W$3,1," ") | X17: =IF($C17<=X$3,1," ") | Y17: =IF($C17<=Y$3,1," ") | ... BB17: =IF($C17<=BB$3,1," ") -> 1
A20: Expenses | G20: =G26+G32+G56+G74 -> 113758 | H20: =H26+H32+H56+H74 -> 113758 | I20: =I26+I32+I56+I74 -> 174140.42 | J20: =J26+J32+J56+J74 -> 201961.67 | K20: =K26+K32+K56+K74 -> 214841.88 | L20: =L26+L32+L56+L74 -> 227722.08 | M20: =M26+M32+M56+M74 -> 302862.75 | N20: =N26+N32+N56+N74 -> 315323.42 | ... AP20: =AP26+AP32+AP56+AP74 -> 1685760.3
B22: Expenses less Staff | G22: =G20-SUM(G75:G79) -> 33952.229 | H22: =H20-SUM(H75:H79) -> 33952.229 | I22: =I20-SUM(I75:I79) -> 81969.646 | J22: =J20-SUM(J75:J79) -> 95880.271 | K22: =K20-SUM(K75:K79) -> 108760.48 | L22: =L20-SUM(L75:L79) -> 121640.69 | M22: =M20-SUM(M75:M79) -> 217389.69 | N22: =N20-SUM(N75:N79) -> 224080.02 | ... AP22: =AP20-SUM(AP75:AP79) -> 1062306.7
B23: Difference month to month | H23: =H22-G22 -> 0 | I23: =I22-H22 -> 48017.417 | J23: =J22-I22 -> 13910.625 | K23: =K22-J22 -> 12880.208 | L23: =L22-K22 -> 12880.208 | M23: =M22-L22 -> 95749 | N23: =N22-M22 -> 6690.3333 | O23: =O22-N22 -> 920 | ... AP23: =AP22-AO22 -> 41204.167
G24: =G84-G85 -> 2837.92 | H24: =H84-H85 -> 6867.31 | I24: =I84-I85 -> 6704.5683 | J24: =J84-J85 -> 10835.97 | K24: =K84-K85 -> 7900.8555 | L24: =L84-L85 -> 57452.096 | M24: =M84-M85 -> -27900
B26: Technology | C26: =SUM(C27:C31) -> 325000 | G26: =SUM(G27:G31) -> 7728.125 | H26: =SUM(H27:H31) -> 7728.125 | I26: =SUM(I27:I31) -> 7728.125 | J26: =SUM(J27:J31) -> 7728.125 | K26: =SUM(K27:K31) -> 7728.125 | L26: =SUM(L27:L31) -> 7728.125 | M26: =SUM(M27:M31) -> 7728.125 | N26: =SUM(N27:N31) -> 7728.125 | ... BB26: =SUM(BB27:BB31) -> 0
B27: IT department - development costs and staff (How many staff?) | C27: 75000 | D27: 10000 | E27: 5000 | F27: Set up // Monthly | Q27: =$D27 -> 10000 | R27: =$D27 -> 10000 | S27: =$D27 -> 10000 | T27: =$E27 -> 5000 | U27: =$E27 -> 5000 | V27: =$E27 -> 5000 | W27: =$E27 -> 5000 | X27: =$E27 -> 5000 | Y27: =$E27 -> 5000 | Z27: =$E27 -> 5000 | AA27: =$E27 -> 5000 | ... AP27: =$E27 -> 5000
B28: SEO Tools and Audit | C28: 100000 | D28: 40000 | E28: 5000 | F28: Set up // Monthly | S28: =$D28 -> 40000 | T28: =$E28 -> 5000 | U28: =$E28 -> 5000 | V28: =$E28 -> 5000 | W28: =$E28 -> 5000 | X28: =$E28 -> 5000 | Y28: =$E28 -> 5000 | Z28: =$E28 -> 5000 | AA28: =$E28 -> 5000 | ... AP28: =$E28 -> 5000
B29: Data analysis: HC Compliance | C29: 150000 | D29: 10000 | F29: Monthly | Y29: =$D29 -> 10000 | Z29: =$D29 -> 10000 | AA29: =$D29 -> 10000 | AB29: =$D29 -> 10000 | AC29: =$D29 -> 10000 | AD29: =$D29 -> 10000 | AE29: =$D29 -> 10000 | AF29: =$D29 -> 10000 | ... AP29: =$D29 -> 10000
B30: Staff | G30: =G79 -> 7728.125 | H30: =H79 -> 7728.125 | I30: =I79 -> 7728.125 | J30: =J79 -> 7728.125 | K30: =K79 -> 7728.125 | L30: =L79 -> 7728.125 | M30: =M79 -> 7728.125 | N30: =N79 -> 7728.125 | ... BB30: =BB79 -> 0
B32: Marketing and Development | C32: =SUM(C33:C45) -> 2805000 | G32: =SUM(G33:G47) -> 26224.104 | H32: =SUM(H33:H47) -> 26224.104 | I32: =SUM(I33:I47) -> 26224.104 | J32: =SUM(J33:J47) -> 26224.104 | K32: =SUM(K33:K47) -> 26224.104 | L32: =SUM(L33:L47) -> 26224.104 | M32: =SUM(M33:M47) -> 26224.104 | N32: =SUM(N33:N47) -> 26224.104 | ... BB32: =SUM(BB33:BB47) -> 0
A33: BD | B33: Brand Development | C33: 300000 | D33: 25000 | E33: For 9 months | T33: =$D33 -> 25000 | U33: =$D33 -> 25000 | V33: =$D33 -> 25000 | W33: =$D33 -> 25000 | X33: =$D33 -> 25000 | Y33: =$D33 -> 25000 | Z33: =$D33 -> 25000 | AA33: =$D33 -> 25000 | AB33: =$E33 -> For 9 months | AC33: =$E33 -> For 9 months | AD33: =$E33 -> For 9 months | AE33: =$E33 -> For 9 months | AF33: =$E33 -> For 9 months | AG33: =$E33 -> For 9 months | AH33: =$E33 -> For 9 months | AI33: =$E33 -> For 9 months | ... AK33: =$E33 -> For 9 months
A34: BD | B34: Content Production | C34: 140000 | D34: 10000 | E34: Monthly | U34: =$D34 -> 10000 | V34: =$D34 -> 10000 | W34: =$D34 -> 10000 | X34: =$D34 -> 10000 | Y34: =$D34 -> 10000 | Z34: =$D34 -> 10000 | AA34: =$D34 -> 10000 | AB34: =$D34 -> 10000 | ... AP34: =$D34 -> 10000
A35: BD | B35: Thought Leadership Content | C35: 180000 | D35: 30000 | E35: Quarterly | U35: =$D35 -> 30000 | X35: =$D35 -> 30000 | AA35: =$D35 -> 30000 | AD35: =$D35 -> 30000 | AG35: =$D35 -> 30000 | AJ35: =$D35 -> 30000 | AM35: =$D35 -> 30000 | AP35: =$D35 -> 30000
A36: BD | B36: Brand Collateral | C36: 20000 | D36: 1500 | E36: Monthly | V36: =$D36 -> 1500 | W36: =$D36 -> 1500 | X36: =$D36 -> 1500 | Y36: =$D36 -> 1500 | Z36: =$D36 -> 1500 | AA36: =$D36 -> 1500 | AB36: =$D36 -> 1500 | AC36: =$D36 -> 1500 | ... AP36: =$D36 -> 1500
A37: BD | B37: Digital Demand Generator | C37: 320000 | D37: 15000 | E37: Monthly | U37: =$D37 -> 15000 | V37: =$D37 -> 15000 | W37: =$D37 -> 15000 | X37: =$D37 -> 15000 | Y37: =$D37 -> 15000 | Z37: =$D37 -> 15000 | AA37: =$D37 -> 15000 | AB37: =$D37 -> 15000 | ... AP37: =$D37 -> 15000
A38: BD | B38: ABM Tools | C38: 200000 | D38: 10000 | E38: Monthly | U38: =$D38 -> 10000 | V38: =$D38 -> 10000 | W38: =$D38 -> 10000 | X38: =$D38 -> 10000 | Y38: =$D38 -> 10000 | Z38: =$D38 -> 10000 | AA38: =$D38 -> 10000 | AB38: =$D38 -> 10000 | ... AP38: =$D38 -> 10000
A39: BD | B39: Sales Enablement Collateral | C39: 200000 | D39: 8000 | E39: Monthly | S39: =$D39 -> 8000 | T39: =$D39 -> 8000 | U39: =$D39 -> 8000 | V39: =$D39 -> 8000 | W39: =$D39 -> 8000 | X39: =$D39 -> 8000 | Y39: =$D39 -> 8000 | Z39: =$D39 -> 8000 | ... AP39: =$D39 -> 8000
A40: BD | B40: Flagship Conf Booths - 3 | C40: 400000 | D40: =C40/3 -> 133333.33 | U40: =$D40 -> 133333.33 | W40: =$D40 -> 133333.33 | Y40: =$D40 -> 133333.33
A41: BD | B41: Roadshows - 5 Cities | C41: 200000 | D41: =C41/5 -> 40000 | E41: Every other month except Dec | T41: =$D41 -> 40000 | V41: =$D41 -> 40000 | X41: =$D41 -> 40000 | Z41: =$D41 -> 40000 | AB41: =$D41 -> 40000 | AF41: =$D41 -> 40000 | AH41: =$D41 -> 40000 | AJ41: =$D41 -> 40000 | AL41: =$D41 -> 40000 | AN41: =$D41 -> 40000
A42: BD | B42: Onsite Staffing and Travel | C42: 150000 | D42: =C42/5 -> 30000 | E42: Every other month except Dec | T42: =$D42 -> 30000 | V42: =$D42 -> 30000 | X42: =$D42 -> 30000 | Z42: =$D42 -> 30000 | AB42: =$D42 -> 30000 | AF42: =$D42 -> 30000 | AH42: =$D42 -> 30000 | AJ42: =$D42 -> 30000 | AL42: =$D42 -> 30000 | AN42: =$D42 -> 30000
A43: BD | B43: Single Marquee Sponsorship | C43: 300000 | D43: =C43 -> 300000 | E43: Annually | V43: =$D43 -> 300000 | AH43: =$D43 -> 300000
A44: BD | B44: Paid Search and Social | C44: 320000 | D44: 28000 | E44: Monthly | S44: =$D44 -> 28000 | T44: =$D44 -> 28000 | U44: =$D44 -> 28000 | V44: =$D44 -> 28000 | W44: =$D44 -> 28000 | X44: =$D44 -> 28000 | Y44: =$D44 -> 28000 | Z44: =$D44 -> 28000 | ... AP44: =$D44 -> 28000
A45: BD | B45: Organic Social Management | C45: 75000 | D45: =C45/12 -> 6250 | E45: Monthly | S45: =$D45 -> 6250 | T45: =$D45 -> 6250 | U45: =$D45 -> 6250 | V45: =$D45 -> 6250 | W45: =$D45 -> 6250 | X45: =$D45 -> 6250 | Y45: =$D45 -> 6250 | Z45: =$D45 -> 6250 | ... AP45: =$D45 -> 6250
A46: BD | B46: Staff | G46: =G76+G77 -> 26224.104 | H46: =H76+H77 -> 26224.104 | I46: =I76+I77 -> 26224.104 | J46: =J76+J77 -> 26224.104 | K46: =K76+K77 -> 26224.104 | L46: =L76+L77 -> 26224.104 | M46: =M76+M77 -> 26224.104 | N46: =N76+N77 -> 26224.104 | ... BB46: =BB76+BB77 -> 0
B48: Clinical Operations | C48: =SUM(C49:C51) -> 1125000 | G48: =SUM(G49:G55) -> 26224.104 | H48: =SUM(H49:H55) -> 26224.104 | I48: =SUM(I49:I55) -> 26224.104 | J48: =SUM(J49:J55) -> 26224.104 | K48: =SUM(K49:K55) -> 26224.104 | L48: =SUM(L49:L55) -> 26224.104 | M48: =SUM(M49:M55) -> 26224.104 | N48: =SUM(N49:N55) -> 26224.104 | ... AP48: =SUM(AP49:AP55) -> 234562.16
A49: CO | B49: Sign on incent: 2.5K/250 providers | C49: 675000 | D49: 2500 | E49: 25 | F49: per month | R49: 32500 | S49: =$E49*$D49 -> 62500 | T49: =$E49*$D49 -> 62500 | U49: =$E49*$D49 -> 62500 | V49: =$E49*$D49 -> 62500 | W49: =$E49*$D49 -> 62500 | X49: =$E49*$D49 -> 62500 | Y49: =$E49*$D49 -> 62500 | Z49: =$E49*$D49 -> 62500 | ... AB49: =$E49*$D49 -> 62500
A50: CO | B50: Recruitment Ads (10 mkts) | C50: 275000 | D50: 75000 | E50: 50000 | F50: per 2 Markets | T50: =D50 -> 75000 | U50: =$E50 -> 50000 | W50: =$E50 -> 50000 | Y50: =$E50 -> 50000 | AA50: =$E50 -> 50000
A51: CO | B51: Outreach Platform | C51: 175000 | D51: =C51/E51 -> 9722.2222 | E51: 18 | F51: month program; expense/month | S51: =$D51 -> 9722.2222 | T51: =$D51 -> 9722.2222 | U51: =$D51 -> 9722.2222 | V51: =$D51 -> 9722.2222 | W51: =$D51 -> 9722.2222 | X51: =$D51 -> 9722.2222 | Y51: =$D51 -> 9722.2222 | Z51: =$D51 -> 9722.2222 | ... AP51: =$D51 -> 9722.2222
A52: CO | B52: Provider Workshops& events | C52: 325000 | D52: 75000 | E52: 100000 | F52: first 3 quarters // year end | U52: =$D52 -> 75000 | X52: =$D52 -> 75000 | AA52: =$D52 -> 75000 | AD52: =$E52 -> 100000 | AG52: =$D52 -> 75000 | AJ52: =$D52 -> 75000 | AM52: =$D52 -> 75000 | AP52: =$E52 -> 100000
A53: CO | B53: Swag and provider kits | C53: 80000 | D53: 5000 | E53: 5000 | F53: per month // Workshop extras | S53: =$D53 -> 5000 | T53: =$D53 -> 5000 | U53: =$D53+$E53 -> 10000 | V53: =$D53 -> 5000 | W53: =$D53 -> 5000 | X53: =$D53+$E53 -> 10000 | Y53: =$D53 -> 5000 | Z53: =$D53 -> 5000 | AA53: =$D53+$E53 -> 10000 | AB53: =$D53 -> 5000 | AC53: =$D53 -> 5000 | AD53: =$D53+$E53 -> 10000 | AE53: =$D53 -> 5000 | AF53: =$D53 -> 5000 | AG53: =$D53+$E53 -> 10000 | AH53: =$D53 -> 5000 | AI53: =$D53 -> 5000 | AJ53: =$D53+$E53 -> 10000 | AK53: =$D53 -> 5000 | AL53: =$D53 -> 5000 | AM53: =$D53+$E53 -> 10000 | AN53: =$D53 -> 5000 | AO53: =$D53 -> 5000 | AP53: =$D53+$E53 -> 10000
A54: CO | B54: Staff | G54: =G76 -> 26224.104 | H54: =H76 -> 26224.104 | I54: =I76 -> 26224.104 | J54: =J76 -> 26224.104 | K54: =K76 -> 26224.104 | L54: =L76 -> 26224.104 | M54: =M76 -> 26224.104 | N54: =N76 -> 26224.104 | ... BB54: =BB76 -> 0
B56: General Administrative | C56: =SUM(C57:C69) -> 588794.14 | D56: Base Expense | E56: Periodic Growth | G56: =SUM(G57:G69) -> 0 | H56: =SUM(H57:H69) -> 0 | I56: =SUM(I57:I73) -> 37610.208 | J56: =SUM(J57:J73) -> 51520.833 | K56: =SUM(K57:K73) -> 51520.833 | L56: =SUM(L57:L73) -> 51520.833 | M56: =SUM(M57:M73) -> 115120.83 | N56: =SUM(N57:N73) -> 121811.17 | O56: =SUM(O57:O73) -> 122731.17 | P56: =SUM(P57:P73) -> 128185 | ... AP56: =SUM(AP57:AP73) -> 346992
A57: GA | B57: Automobile Expense | C57: 26115.07 | D57: 2000 | F57: Base/mo. - Growth/mo. | M57: =$D57 -> 2000 | N57: =M57 -> 2000 | O57: =N57 -> 2000 | P57: =O57 -> 2000 | Q57: =P57 -> 2000 | R57: =Q57 -> 2000 | S57: =R57+$E57 -> 2000 | T57: =S57+$E57 -> 2000 | U57: =T57+$E57 -> 2000 | V57: =U57+$E57 -> 2000 | W57: =V57+$E57 -> 2000 | X57: =W57+$E57 -> 2000 | Y57: =X57+$E57 -> 2000 | Z57: =Y57+$E57 -> 2000 | ... AP57: =AO57+$E57 -> 2000
A58: GA | B58: Dues and Subscriptions | C58: 1294.15 | D58: 800 | F58: Base/mo. - Growth/mo. | M58: =$D58 -> 800 | N58: =M58+20 -> 820 | O58: =N58+20 -> 840 | P58: =O58+20 -> 860 | Q58: =P58+20 -> 880 | R58: =Q58+20 -> 900 | S58: =R58+$E58 -> 900 | T58: =S58+$E58 -> 900 | U58: =T58+$E58 -> 900 | V58: =U58+$E58 -> 900 | W58: =V58+$E58 -> 900 | X58: =W58+$E58 -> 900 | Y58: =X58+$E58 -> 900 | Z58: =Y58+$E58 -> 900 | ... AP58: =AO58+$E58 -> 900
A59: GA | B59: Freelancers | C59: 8786.54 | D59: 1800 | F59: Base/mo. - Growth/mo. | M59: =$D59 -> 1800 | N59: =$D59 -> 1800 | O59: =$D59 -> 1800 | P59: =$D59 -> 1800 | Q59: =$D59 -> 1800 | R59: =$D59 -> 1800 | S59: =R59+$E59 -> 1800 | T59: =S59+$E59 -> 1800 | U59: =T59+$E59 -> 1800 | V59: =U59+$E59 -> 1800 | W59: =V59+$E59 -> 1800 | X59: =W59+$E59 -> 1800 | Y59: =X59+$E59 -> 1800 | Z59: =Y59+$E59 -> 1800 | ... AP59: =AO59+$E59 -> 1800
A60: GA | B60: Insurance Expense | C60: 27466.39 | D60: 4200 | E60: 100 | F60: Base/mo. - Growth/mo. | M60: =D60 -> 4200 | N60: =M60+$E60 -> 4300 | O60: =N60+$E60 -> 4400 | P60: =O60+$E60 -> 4500 | Q60: =P60+$E60 -> 4600 | R60: =Q60+$E60 -> 4700 | S60: =R60+$E60 -> 4800 | T60: =S60+$E60 -> 4900 | U60: =T60+$E60 -> 5000 | ... AP60: =AO60+$E60 -> 7100
A61: GA | B61: Legal & Professional Fees | C61: =40819.99+3235 -> 44054.99 | D61: 7500 | E61: 250 | F61: Base/mo. - Growth/mo. | M61: =D61 -> 7500 | N61: =M61+$E61 -> 7750 | O61: =N61+$E61 -> 8000 | P61: =O61+$E61 -> 8250 | Q61: =P61+$E61 -> 8500 | R61: =Q61+$E61 -> 8750 | S61: =R61+$E61 -> 9000 | T61: =S61+$E61 -> 9250 | U61: =T61+$E61 -> 9500 | ... AP61: =AO61+$E61 -> 14750
A62: GA | B62: License | C62: 36851.29 | D62: 4500 | E62: 100 | F62: Base/mo. - Growth/mo. | M62: =$D62 -> 4500 | N62: =M62+$E62 -> 4600 | O62: =N62+$E62 -> 4700 | P62: =O62+$E62 -> 4800 | Q62: =P62+$E62 -> 4900 | R62: =Q62+$E62 -> 5000 | S62: =R62+$E62 -> 5100 | T62: =S62+$E62 -> 5200 | U62: =T62+$E62 -> 5300 | ... AP62: =AO62+$E62 -> 7400
A63: GA | B63: Meals and Entertainment | C63: 28976.73 | D63: 3600 | E63: 50 | F63: Base/mo. - Growth/mo. | M63: =D63 -> 3600 | N63: =M63+$E63 -> 3650 | O63: =N63+$E63 -> 3700 | P63: =O63+$E63 -> 3750 | Q63: =P63+$E63 -> 3800 | R63: =Q63+$E63 -> 3850 | S63: =R63+$E63 -> 3900 | T63: =S63+$E63 -> 3950 | U63: =T63+$E63 -> 4000 | ... AP63: =AO63+$E63 -> 5050
A64: GA | B64: Office Expenses | C64: =13071.42+3141+2897 -> 19109.42 | D64: 6200 | E64: 100 | F64: Base/mo. - Growth/mo. | M64: =D64 -> 6200 | N64: =M64+$E64 -> 6300 | O64: =N64+$E64 -> 6400 | P64: =O64+$E64 -> 6500 | Q64: =P64+$E64 -> 6600 | R64: =Q64+$E64 -> 6700 | S64: =R64+$E64 -> 6800 | T64: =S64+$E64 -> 6900 | U64: =T64+$E64 -> 7000 | ... AP64: =AO64+$E64 -> 9100
A65: GA | B65: Office Supplies | C65: 77828.27 | D65: 6000 | E65: 100 | F65: Base/mo. - Growth/mo. | M65: =D65 -> 6000 | N65: =M65+$E65 -> 6100 | O65: =N65+$E65 -> 6200 | P65: =O65+$E65 -> 6300 | Q65: =P65+$E65 -> 6400 | R65: =Q65+$E65 -> 6500 | S65: =R65+$E65 -> 6600 | T65: =S65+$E65 -> 6700 | U65: =T65+$E65 -> 6800 | ... AP65: =AO65+$E65 -> 8900
A66: GA | B66: Payroll Processing Fees | C66: 26641.64 | D66: 4000 | E66: 100 | F66: Base/mo. - Growth/mo. | M66: =D66 -> 4000 | N66: =M66+$E66 -> 4100 | O66: =N66+$E66 -> 4200 | P66: =O66+$E66 -> 4300 | Q66: =P66+$E66 -> 4400 | R66: =Q66+$E66 -> 4500 | S66: =R66+$E66 -> 4600 | T66: =S66+$E66 -> 4700 | U66: =T66+$E66 -> 4800 | ... AP66: =AO66+$E66 -> 6900
A67: GA | B67: Rent Expense | C67: 214658.98 | D67: 18000 | F67: Plus $2,000/6 months | M67: =D67 -> 18000 | N67: =M67 -> 18000 | O67: =N67 -> 18000 | P67: =O67 -> 18000 | Q67: =P67 -> 18000 | R67: =Q67 -> 18000 | S67: =R67+$E67 -> 18000 | T67: =S67 -> 18000 | U67: =T67 -> 18000 | V67: =U67 -> 18000 | W67: =V67 -> 18000 | X67: =W67 -> 18000 | Y67: =X67+$E67 -> 18000 | Z67: =Y67 -> 18000 | AA67: =Z67 -> 18000 | AB67: =AA67 -> 18000 | AC67: =AB67 -> 18000 | AD67: =AC67+$E67 -> 18000 | AE67: =AD67 -> 18000 | AF67: =AE67 -> 18000 | AG67: =AF67 -> 18000 | AH67: =AG67 -> 18000 | AI67: =AH67 -> 18000 | AJ67: =AI67 -> 18000 | AK67: =AJ67+$E67 -> 18000 | AL67: =AK67 -> 18000 | AM67: =AL67 -> 18000 | AN67: =AM67 -> 18000 | AO67: =AN67 -> 18000 | AP67: =AO67 -> 18000
A68: GA | B68: Total Bank Charges | C68: 6358.04 | D68: 500 | E68: 0 | M68: =D68 -> 500 | N68: =M68 -> 500 | O68: =N68 -> 500 | P68: =O68 -> 500 | Q68: =P68 -> 500 | R68: =Q68 -> 500 | S68: =R68 -> 500 | T68: =S68 -> 500 | U68: =T68 -> 500 | ... AP68: =AO68 -> 500
A69: GA | B69: Travel Expense | C69: 70652.63 | D69: 4500 | E69: 100 | F69: Plus $100/month | M69: =D69 -> 4500 | N69: =M69+$E69 -> 4600 | O69: =N69+$E69 -> 4700 | P69: =O69+$E69 -> 4800 | Q69: =P69+$E69 -> 4900 | R69: =Q69+$E69 -> 5000 | S69: =R69+$E69 -> 5100 | T69: =S69+$E69 -> 5200 | U69: =T69+$E69 -> 5300 | ... AP69: =AO69+$E69 -> 7400
A70: GA | B70: Staff | G70: =G75 -> 25245.208 | H70: =H75 -> 25245.208 | I70: =I75 -> 37610.208 | J70: =J75 -> 51520.833 | K70: =K75 -> 51520.833 | L70: =L75 -> 51520.833 | M70: =M75 -> 51520.833 | N70: =N75 -> 57291.167 | ... BB70: =BB75 -> 0
A74: ST | B74: Total Payroll (tax/Benefits) | E74: =D74/6 -> 0 | G74: =Staffing!K121 -> 79805.771 | H74: =Staffing!L121 -> 79805.771 | I74: =Staffing!M121 -> 102577.98 | J74: =Staffing!N121 -> 116488.6 | K74: =Staffing!O121 -> 129368.81 | L74: =Staffing!P121 -> 142249.02 | M74: =Staffing!Q121 -> 153789.69 | N74: =Staffing!R121 -> 159560.02 | ... AP74: =Staffing!AT121 -> 922068.35
B75: G&A | C75: Expenses | G75: =Staffing!K138 -> 25245.208 | H75: =Staffing!L138 -> 25245.208 | I75: =Staffing!M138 -> 37610.208 | J75: =Staffing!N138 -> 51520.833 | K75: =Staffing!O138 -> 51520.833 | L75: =Staffing!P138 -> 51520.833 | M75: =Staffing!Q138 -> 51520.833 | N75: =Staffing!R138 -> 57291.167 | ... AP75: =Staffing!AT138 -> 257192
B76: Clinical Ops | C76: Expenses | G76: =Staffing!K139 -> 26224.104 | H76: =Staffing!L139 -> 26224.104 | I76: =Staffing!M139 -> 26224.104 | J76: =Staffing!N139 -> 26224.104 | K76: =Staffing!O139 -> 26224.104 | L76: =Staffing!P139 -> 26224.104 | M76: =Staffing!Q139 -> 26224.104 | N76: =Staffing!R139 -> 26224.104 | ... AP76: =Staffing!AT139 -> 114839.94
B77: Marketing | C77: Expenses | G77: =Staffing!K140 -> 0 | H77: =Staffing!L140 -> 0 | I77: =Staffing!M140 -> 0 | J77: =Staffing!N140 -> 0 | K77: =Staffing!O140 -> 0 | L77: =Staffing!P140 -> 0 | M77: =Staffing!Q140 -> 0 | N77: =Staffing!R140 -> 0 | ... AP77: =Staffing!AT140 -> 95313.542
B78: Business Dev | C78: Expenses | G78: =Staffing!K141 -> 20608.333 | H78: =Staffing!L141 -> 20608.333 | I78: =Staffing!M141 -> 20608.333 | J78: =Staffing!N141 -> 20608.333 | K78: =Staffing!O141 -> 20608.333 | L78: =Staffing!P141 -> 20608.333 | M78: =Staffing!Q141 -> 0 | N78: =Staffing!R141 -> 0 | ... AP78: =Staffing!AT141 -> 78311.667
B79: Technology | C79: Expenses | G79: =Staffing!K142 -> 7728.125 | H79: =Staffing!L142 -> 7728.125 | I79: =Staffing!M142 -> 7728.125 | J79: =Staffing!N142 -> 7728.125 | K79: =Staffing!O142 -> 7728.125 | L79: =Staffing!P142 -> 7728.125 | M79: =Staffing!Q142 -> 7728.125 | N79: =Staffing!R142 -> 7728.125 | ... AP79: =Staffing!AT142 -> 77796.458
B80: PI | C80: COGS | G80: =Staffing!K144 -> 0 | H80: =Staffing!L144 -> 0 | I80: =Staffing!M144 -> 10407.208 | J80: =Staffing!N144 -> 10407.208 | K80: =Staffing!O144 -> 23287.417 | L80: =Staffing!P144 -> 36167.625 | M80: =Staffing!Q144 -> 47708.292 | N80: =Staffing!R144 -> 47708.292 | ... AP80: =Staffing!AT144 -> 100259.54
B81: SaaS | C81: COGS | G81: =Staffing!K145 -> 0 | H81: =Staffing!L145 -> 0 | I81: =Staffing!M145 -> 0 | J81: =Staffing!N145 -> 0 | K81: =Staffing!O145 -> 0 | L81: =Staffing!P145 -> 0 | M81: =Staffing!Q145 -> 0 | N81: =Staffing!R145 -> 0 | ... AP81: =Staffing!AT145 -> 59248.958
B82: HC Compliance | C82: COGS | G82: =Staffing!K146 -> 0 | H82: =Staffing!L146 -> 0 | I82: =Staffing!M146 -> 0 | J82: =Staffing!N146 -> 0 | K82: =Staffing!O146 -> 0 | L82: =Staffing!P146 -> 0 | M82: =Staffing!Q146 -> 0 | N82: =Staffing!R146 -> 0 | ... AP82: =Staffing!AT146 -> 139106.25
G84: 424809.87 | H84: 428219.25 | I84: 642221.25 | J84: 708475.86 | K84: 504172.01 | L84: 578488.93 | M84: 532259.03
A85: COGS | G85: =SUM(G87:G95) -> 421971.95 | H85: =SUM(H87:H95) -> 421351.94 | I85: =SUM(I87:I95) -> 635516.68 | J85: =SUM(J87:J95) -> 697639.89 | K85: =SUM(K87:K95) -> 496271.15 | L85: =SUM(L87:L95) -> 521036.83 | M85: =SUM(M87:M95) -> 560159.03 | N85: =SUM(N87:N95) -> 690003.29 | ... BB85: =SUM(BB87:BB95) -> 0 | BD85: =SUM(BD87:BD95) -> 0 | BE85: =SUM(BE87:BE95) -> 8273203.9 | BF85: =SUM(BF87:BF95) -> 35603979 | BG85: =SUM(BG87:BG95) -> 1.103021e+08
B87: =B178 -> VA Mental Health | G87: =G178*(1-G107) -> 406561.95 | H87: =H178*(1-H107) -> 402721.94 | I87: =I178*(1-I107) -> 607456.68 | J87: =J178*(1-J107) -> 651253.68 | K87: =K178*(1-K107) -> 414476.16 | L87: =L200 -> 366159.2 | M87: =M200 -> 372590.74 | N87: =N200 -> 540575 | O87: =O200 -> 618975 | P87: =P200 -> 583450 | Q87: =Q200 -> 640850 | R87: =R200 -> 662725 | S87: =S200 -> 677250 | ... AP87: =AP200 -> 1011325 | BE87: =SUM(G87:R87) -> 6267795.4 | BF87: =SUM(S87:AD87) -> 9085650 | BG87: =SUM(AE87:AP87) -> 11177250
B88: =B179 -> VA Medical Evaluations | G88: =G243+G244 -> 15410 | H88: =H243+H244 -> 18630 | I88: =I243+I244 -> 28060 | J88: =J243+J244 -> 30935 | K88: =K243+K244 -> 34059.574 | L88: =L243+L244 -> 45310 | M88: =M243+M244 -> 46460 | N88: =N243+N244 -> 31320 | ... AP88: =AP243+AP244 -> 388645 | BE88: =SUM(G88:R88) -> 463404.57 | BF88: =SUM(S88:AD88) -> 2003740 | BG88: =SUM(AE88:AP88) -> 3827740
B89: =B181 -> Personal Injury | G89: =G287 -> 0 | H89: =H287 -> 0 | I89: =I287 -> 0 | J89: =J287 -> 15451.208 | K89: =K287 -> 47735.417 | L89: =L287 -> 109567.62 | M89: =M287 -> 141108.29 | N89: =N287 -> 118108.29 | ... AP89: =AP287 -> 2166659.5 | BE89: =SUM(G89:R89) -> 1470004 | BF89: =SUM(S89:AD89) -> 12896926 | BG89: =SUM(AE89:AP89) -> 23253772
B90: =B182 -> Workers Comp | G90: =G320+G321 -> 0 | H90: =H320+H321 -> 0 | I90: =I320+I321 -> 0 | J90: =J320+J321 -> 0 | K90: =K320+K321 -> 0 | L90: =L320+L321 -> 0 | M90: =M320+M321 -> 0 | N90: =N320+N321 -> 0 | ... AP90: =AP320+AP321 -> 1200000 | BE90: =SUM(G90:R90) -> 72000 | BF90: =SUM(S90:AD90) -> 4320000 | BG90: =SUM(AE90:AP90) -> 11232000
B91: =B188 -> SaaS | G91: =G571 -> 0 | H91: =H571 -> 0 | I91: =I571 -> 0 | J91: =J571 -> 0 | K91: =K571 -> 0 | L91: =L571 -> 0 | M91: =M571 -> 0 | N91: =N571 -> 0 | ... AP91: =AP571 -> 363657.45 | BE91: =SUM(G91:R91) -> 0 | BF91: =SUM(S91:AD91) -> 640016.65 | BG91: =SUM(AE91:AP91) -> 2878013.3
B92: =B184 -> Corrections | G92: =G396 -> 0 | H92: =H396 -> 0 | I92: =I396 -> 0 | J92: =J396 -> 0 | K92: =K396 -> 0 | L92: =L396 -> 0 | M92: =M396 -> 0 | N92: =N396 -> 0 | ... W92: =W396 -> 0 | X92: =X392 -> 0 | Y92: =Y392 -> 726000 | Z92: =Z392 -> 726000 | AA92: =AA392 -> 726000 | AB92: =AB392 -> 1452000 | AC92: =AC392 -> 1452000 | AD92: =AD392 -> 1452000 | AE92: =AE392 -> 2178000 | ... AP92: =AP392 -> 9108000 | BE92: =SUM(G92:R92) -> 0 | BF92: =SUM(S92:AD92) -> 6534000 | BG92: =SUM(AE92:AP92) -> 56364000
B93: =B185 -> Healthcare Compliance | G93: =G484 -> 0 | H93: =H484 -> 0 | I93: =I484 -> 0 | J93: =J484 -> 0 | K93: =K484 -> 0 | L93: =L484 -> 0 | M93: =M484 -> 0 | N93: =N484 -> 0 | ... AP93: =AP484 -> 211140 | BE93: =SUM(G93:R93) -> 0 | BF93: =SUM(S93:AD93) -> 123646.67 | BG93: =SUM(AE93:AP93) -> 1569327.5
B94: =B186 -> Employee Wellness | G94: =G443 -> 0 | H94: =H443 -> 0 | I94: =I443 -> 0 | J94: =J443 -> 0 | K94: =K443 -> 0 | L94: =L443 -> 0 | M94: =M443 -> 0 | N94: =N443 -> 0 | ... AP94: =AP443 -> 0 | BE94: =SUM(G94:R94) -> 0 | BF94: =SUM(S94:AD94) -> 0 | BG94: =SUM(AE94:AP94) -> 0
A96: Gross Profit | G96: =SUM(G97:G105) -> 275901.05 | H96: =SUM(H97:H105) -> 183952.06 | I96: =SUM(I97:I105) -> 302255.32 | J96: =SUM(J97:J105) -> 152872.11 | K96: =SUM(K97:K105) -> 495125.85 | L96: =SUM(L97:L105) -> 448514.77 | M96: =SUM(M97:M105) -> 452376.25 | N96: =SUM(N97:N105) -> 573143.31 | ... BB96: =SUM(BB97:BB105) -> 0 | BD96: =SUM(BD97:BD105) -> 0 | BE96: =SUM(BE97:BE105) -> 6394687.4 | BF96: =SUM(BF97:BF105) -> 30629650 | BG96: =SUM(BG97:BG105) -> 67812150
B97: =B87 -> VA Mental Health | G97: =G178-G87 -> 259933.05 | H97: =H178-H87 -> 164492.06 | I97: =I178-I87 -> 272915.32 | J97: =J178-J87 -> 124048.32 | K97: =K178-K87 -> 449015.84 | L97: =L178-L87 -> 355595.8 | M97: =M178-M87 -> 330008.94 | N97: =N178-N87 -> 478795 | ... AP97: =AP178-AP87 -> 895745 | BE97: =BE178-BE87 -> 4654404.3 | BF97: =BF178-BF87 -> 8047290 | BG97: =BG178-BG87 -> 9899850
B98: =B88 -> VA Medical Evaluations | G98: =G179-G88 -> 15968 | H98: =H179-H88 -> 19460 | I98: =I179-I88 -> 29340 | J98: =J179-J88 -> 32265 | K98: =K179-K88 -> 35540.426 | L98: =L179-L88 -> 33490 | M98: =M179-M88 -> 48480 | N98: =N179-N88 -> 50460 | ... AP98: =AP179-AP88 -> 572740 | BE98: =BE179-BE88 -> 588523.43 | BF98: =BF179-BF88 -> 2952880 | BG98: =BG179-BG88 -> 5640880
B99: =B89 -> Personal Injury | G99: =G181-G89 -> 0 | H99: =H181-H89 -> 0 | I99: =I181-I89 -> 0 | J99: =J181-J89 -> -3441.2083 | K99: =K181-K89 -> 10569.583 | L99: =L181-L89 -> 59428.975 | M99: =M181-M89 -> 73887.308 | N99: =N181-N89 -> 43888.308 | ... AP99: =AP181-AP89 -> 2589242.1 | BE99: =BE181-BE89 -> 1096259.6 | BF99: =BF181-BF89 -> 14920499 | BG99: =BG181-BG89 -> 27679174
B100: =B90 -> Workers Comp | G100: =G182-G90 -> 0 | H100: =H182-H90 -> 0 | I100: =I182-I90 -> 0 | J100: =J182-J90 -> 0 | K100: =K182-K90 -> 0 | L100: =L182-L90 -> 0 | M100: =M182-M90 -> 0 | N100: =N182-N90 -> 0 | ... AP100: =AP182-AP90 -> 925000 | BE100: =BE182-BE90 -> 55500 | BF100: =BF182-BF90 -> 3330000 | BG100: =BG182-BG90 -> 8658000
B101: =B91 -> SaaS | G101: =G183-G91 -> 0 | H101: =H183-H91 -> 0 | I101: =I183-I91 -> 0 | J101: =J183-J91 -> 0 | K101: =K183-K91 -> 0 | L101: =L183-L91 -> 0 | M101: =M183-M91 -> 0 | N101: =N183-N91 -> 0 | ... AP101: =AP183-AP91 -> 964008.1 | BE101: =BE183-BE91 -> 0 | BF101: =BF183-BF91 -> 485402.48 | BG101: =BG183-BG91 -> 6636186.4
B102: =B92 -> Corrections | G102: =G184-G92 -> 0 | H102: =H184-H92 -> 0 | I102: =I184-I92 -> 0 | J102: =J184-J92 -> 0 | K102: =K184-K92 -> 0 | L102: =L184-L92 -> 0 | M102: =M184-M92 -> 0 | N102: =N184-N92 -> 0 | ... AP102: =AP184-AP92 -> 1603800 | BE102: =BE184-BE92 -> 0 | BF102: =BF184-BF92 -> 980100 | BG102: =BG184-BG92 -> 9167400
B103: =B93 -> Healthcare Compliance | G103: =G185-G93 -> 0 | H103: =H185-H93 -> 0 | I103: =I185-I93 -> 0 | J103: =J185-J93 -> 0 | K103: =K185-K93 -> 0 | L103: =L185-L93 -> 0 | M103: =M185-M93 -> 0 | N103: =N185-N93 -> 0 | ... AP103: =AP185-AP93 -> 51660 | BE103: =BE185-BE93 -> 0 | BF103: =BF185-BF93 -> -86521.667 | BG103: =BG185-BG93 -> 130660
B104: =B94 -> Employee Wellness | G104: =G186-G94 -> 0 | H104: =H186-H94 -> 0 | I104: =I186-I94 -> 0 | J104: =J186-J94 -> 0 | K104: =K186-K94 -> 0 | L104: =L186-L94 -> 0 | M104: =M186-M94 -> 0 | N104: =N186-N94 -> 0 | ... AP104: =AP186-AP94 -> 0 | BE104: =BE186-BE94 -> 0 | BF104: =BF186-BF94 -> 0 | BG104: =BG186-BG94 -> 0
A106: Gross Margin | G106: =G96/G175 -> 0.39534564 | H106: =H96/H175 -> 0.30390029 | I106: =I96/I175 -> 0.32231216 | J106: =J96/J175 -> 0.17974128 | K106: =K96/K175 -> 0.49942238 | L106: =L96/L175 -> 0.46260021 | M106: =M96/M175 -> 0.44677579 | N106: =N96/N175 -> 0.45374251 | ... AP106: =AP96/AP175 -> 0.34474539 | BE106: =BE96/BE175 -> 0.43596501 | BF106: =BF96/BF175 -> 0.46244861 | BG106: =BG96/BG175 -> 0.38072276
B107: =B87 -> VA Mental Health | G107: 0.39 | H107: 0.29 | I107: 0.31 | J107: 0.16 | K107: 0.52 | L107: 0.2 | M107: =M97/M178 -> 0.46969697 | N107: =N97/N178 -> 0.46969697 | O107: =O97/O178 -> 0.46969697 | P107: =P97/P178 -> 0.46969697 | Q107: =Q97/Q178 -> 0.46969697 | R107: =R97/R178 -> 0.46969697 | S107: =S97/S178 -> 0.46969697 | T107: =T97/T178 -> 0.46969697 | ... AP107: =AP97/AP178 -> 0.46969697 | BE107: =BE97/BE178 -> 0.42614166 | BF107: =BF97/BF178 -> 0.46969697 | BG107: =BG97/BG178 -> 0.46969697
B108: =B88 -> VA Medical Evaluations | G108: 0.55 | H108: =H98/H179 -> 0.51089525 | I108: =I98/I179 -> 0.51114983 | J108: =J98/J179 -> 0.51052215 | K108: =K98/K179 -> 0.5106383 | L108: =L98/L179 -> 0.425 | M108: =M98/M179 -> 0.5106383 | N108: =N98/N179 -> 0.61702128 | O108: =O98/O179 -> 0.61702128 | ... AP108: =AP98/AP179 -> 0.59574468 | BE108: =BE98/BE179 -> 0.5594712 | BF108: =BF98/BF179 -> 0.59574468 | BG108: =BG98/BG179 -> 0.59574468
B109: =B89 -> Personal Injury | J109: =J99/J181 -> -0.28652859 | K109: =K99/K181 -> 0.18128091 | L109: =L99/L181 -> 0.35165781 | M109: =M99/M181 -> 0.34366893 | N109: =N99/N181 -> 0.27092117 | O109: =O99/O181 -> 0.39820427 | P109: =P99/P181 -> 0.44660142 | Q109: =Q99/Q181 -> 0.48325087 | ... AP109: =AP99/AP181 -> 0.54442717 | BE109: =BE99/BE181 -> 0.42718121 | BF109: =BF99/BF181 -> 0.5363724 | BG109: =BG99/BG181 -> 0.5434434
B110: =B90 -> Workers Comp | N110: =N100/N182 -> #DIV/0! | O110: =O100/O182 -> #DIV/0! | P110: =P100/P182 -> #DIV/0! | Q110: =Q100/Q182 -> 0.43529412 | R110: =R100/R182 -> 0.43529412 | S110: =S100/S182 -> 0.43529412 | T110: =T100/T182 -> 0.43529412 | U110: =U100/U182 -> 0.43529412 | ... AP110: =AP100/AP182 -> 0.43529412 | BE110: =BE100/BE182 -> 0.43529412 | BF110: =BF100/BF182 -> 0.43529412 | BG110: =BG100/BG182 -> 0.43529412
B111: =B91 -> SaaS | X111: =X101/X183 -> -0.68846765 | Y111: =Y101/Y183 -> 0.073247421 | Z111: =Z101/Z183 -> 0.25719011 | AA111: =AA101/AA183 -> 0.40265366 | AB111: =AB101/AB183 -> 0.48956089 | AC111: =AC101/AC183 -> 0.54717844 | AD111: =AD101/AD183 -> 0.58805039 | AE111: =AE101/AE183 -> 0.59868945 | ... AP111: =AP101/AP183 -> 0.72609258 | BF111: =BF101/BF183 -> 0.43130818 | BG111: =BG101/BG183 -> 0.69750337
B112: =B92 -> Corrections | Y112: =Y102/Y184 -> 0.13043478 | Z112: =Z102/Z184 -> 0.13043478 | AA112: =AA102/AA184 -> 0.13043478 | AB112: =AB102/AB184 -> 0.13043478 | AC112: =AC102/AC184 -> 0.13043478 | AD112: =AD102/AD184 -> 0.13043478 | AE112: =AE102/AE184 -> 0.13043478 | AF112: =AF102/AF184 -> 0.13043478 | ... AP112: =AP102/AP184 -> 0.14972274 | BF112: =BF102/BF184 -> 0.13043478 | BG112: =BG102/BG184 -> 0.13989324
B113: =B93 -> Healthcare Compliance | AB113: =AB103/AB185 -> -4.0701684 | AC113: =AC103/AC185 -> -1.713266 | AD113: =AD103/AD185 -> -2.1621998 | AE113: =AE103/AE185 -> -0.64373415 | AF113: =AF103/AF185 -> -0.28133652 | AG113: =AG103/AG185 -> -0.08000451 | AH113: =AH103/AH185 -> -0.067192473 | AI113: =AI103/AI185 -> 0.03924599 | ... AP113: =AP103/AP185 -> 0.19657534 | BF113: =BF103/BF185 -> -2.3305499 | BG113: =BG103/BG185 -> 0.076859389
B114: =B94 -> Employee Wellness
A117: Accrual Adjustments: Receivables, Payables and Net Cash | G117: =SUM(G165:G173) -> 0 | H117: =SUM(H165:H173) -> 0 | I117: =SUM(I165:I173) -> 0 | J117: =SUM(J165:J173) -> 0 | K117: =SUM(K165:K173) -> 0 | L117: =SUM(L165:L173) -> 0 | M117: =SUM(M165:M173) -> 25449.146 | N117: =SUM(N165:N173) -> 180381.63 | ... AP117: =SUM(AP165:AP173) -> 6148968.8
A119: Accounts Recievable | M119: =M121 -> 1012535.3 | N119: =N121 -> 1263146.6 | O119: =O121 -> 1537039.2 | P119: =P121 -> 1593096.8 | Q119: =Q121 -> 1981583 | R119: =R121 -> 2228080.8 | S119: =S121 -> 2656798.3 | T119: =T121 -> 3078515.9 | ... AP119: =AP121 -> 20723957
...

Sheet Staffing
A2: EMPLOYEES: | K2: 45658 | L2: 45689 | M2: 45717 | N2: 45748 | O2: 45778 | P2: 45809 | Q2: 45839 | R2: 45870 | S2: 45901 | T2: 45931 | U2: 45962 | V2: 45992 | W2: 46023 | X2: 46054 | Y2: 46082 | Z2: 46113 | AA2: 46143 | AB2: 46174 | AC2: 46204 | AD2: 46235 | AE2: 46266 | AF2: 46296 | AG2: 46327 | AH2: 46357 | AI2: 46388 | AJ2: 46419 | AK2: 46447 | AL2: 46478 | AM2: 46508 | AN2: 46539 | AO2: 46569 | AP2: 46600 | AQ2: 46631 | AR2: 46661 | AS2: 46692 | AT2: 46722
B3: Last | C3: First | D3: Title | E3: Department | G3: Salary | H3: Monthly | I3: Start Date
A4: 1 | B4: Loeb | C4: Yisroel | D4: CEO | E4: Executive | F4: G&A | G4: DRAW | H4: 15000 | I4: 45658 | K4: 2854 | L4: 1411 | M4: 6767 | N4: =3708+450000 -> 453708 | O4: 3336 | P4: 13259 | Q4: 10670 | R4: 1220 | W4: =IF(W$2>=$I4,$H4,0) -> 15000 | X4: =IF(X$2>=$I4,$H4,0) -> 15000 | Y4: =IF(Y$2>=$I4,$H4,0) -> 15000 | Z4: =IF(Z$2>=$I4,$H4,0) -> 15000 | AA4: =IF(AA$2>=$I4,$H4,0) -> 15000 | AB4: =IF(AB$2>=$I4,$H4,0) -> 15000 | AC4: =IF(AC$2>=$I4,$H4,0) -> 15000 | AD4: =IF(AD$2>=$I4,$H4,0) -> 15000 | ... AT4: =IF(AT$2>=$I4,$H4,0) -> 15000
A5: 2 | B5: Reintein | C5: Sam | D5: CFO | E5: Executive | F5: G&A | G5: 250000 | H5: =G5/12 -> 20833.333 | I5: 45658 | K5: 0 | L5: 0 | M5: 0 | N5: 0 | O5: 0 | P5: 0 | Q5: 0 | R5: 0 | S5: 0 | T5: 0 | U5: 0 | V5: 0 | W5: =IF(W$2>=$I5,$H5,0) -> 20833.333 | X5: =IF(X$2>=$I5,$H5,0) -> 20833.333 | Y5: =IF(Y$2>=$I5,$H5,0) -> 20833.333 | Z5: =IF(Z$2>=$I5,$H5,0) -> 20833.333 | AA5: =IF(AA$2>=$I5,$H5,0) -> 20833.333 | AB5: =IF(AB$2>=$I5,$H5,0) -> 20833.333 | AC5: =IF(AC$2>=$I5,$H5,0) -> 20833.333 | AD5: =IF(AD$2>=$I5,$H5,0) -> 20833.333 | ... AT5: =IF(AT$2>=$I5,$H5,0) -> 20833.333
A6: 3 | B6: Blech | C6: Benzion | D6: CTO | E6: Executive | F6: G&A | G6: 300000 | H6: =G6/12 -> 25000 | I6: 45658 | K6: 0 | L6: 0 | M6: 10000 | N6: 10000 | O6: 10000 | P6: 10000 | Q6: 10000 | R6: 10000 | S6: 10000 | T6: 10000 | U6: 10000 | V6: 10000 | W6: =IF(W$2>=$I6,$H6,0) -> 25000 | X6: =IF(X$2>=$I6,$H6,0) -> 25000 | Y6: =IF(Y$2>=$I6,$H6,0) -> 25000 | Z6: =IF(Z$2>=$I6,$H6,0) -> 25000 | AA6: =IF(AA$2>=$I6,$H6,0) -> 25000 | AB6: =IF(AB$2>=$I6,$H6,0) -> 25000 | AC6: =IF(AC$2>=$I6,$H6,0) -> 25000 | AD6: =IF(AD$2>=$I6,$H6,0) -> 25000 | ... AT6: =IF(AT$2>=$I6,$H6,0) -> 25000
A7: 4 | B7: Craft | C7: Sherry | D7: CCO | E7: Executive | F7: G&A | G7: 250000 | H7: =G7/12 -> 20833.333 | I7: 45658 | K7: 12500 | L7: 12500 | M7: 12500 | N7: 12500 | O7: 12500 | P7: 12500 | Q7: 12500 | R7: 12500 | S7: 12500 | T7: 12500 | U7: 12500 | V7: 12500 | W7: =IF(W$2>=$I7,$H7,0) -> 20833.333 | X7: =IF(X$2>=$I7,$H7,0) -> 20833.333 | Y7: =IF(Y$2>=$I7,$H7,0) -> 20833.333 | Z7: =IF(Z$2>=$I7,$H7,0) -> 20833.333 | AA7: =IF(AA$2>=$I7,$H7,0) -> 20833.333 | AB7: =IF(AB$2>=$I7,$H7,0) -> 20833.333 | AC7: =IF(AC$2>=$I7,$H7,0) -> 20833.333 | AD7: =IF(AD$2>=$I7,$H7,0) -> 20833.333 | ... AT7: =IF(AT$2>=$I7,$H7,0) -> 20833.333
B8: NEW | D8: CMO | E8: Executive | F8: G&A | G8: 300000 | H8: =G8/12 -> 25000 | I8: 45962 | Q8: =IF(Q$2>=$I8,$H8,0) -> 0 | R8: =IF(R$2>=$I8,$H8,0) -> 0 | S8: =IF(S$2>=$I8,$H8,0) -> 0 | T8: =IF(T$2>=$I8,$H8,0) -> 0 | W8: =IF(W$2>=$I8,$H8,0) -> 25000 | X8: =IF(X$2>=$I8,$H8,0) -> 25000 | Y8: =IF(Y$2>=$I8,$H8,0) -> 25000 | Z8: =IF(Z$2>=$I8,$H8,0) -> 25000 | AA8: =IF(AA$2>=$I8,$H8,0) -> 25000 | AB8: =IF(AB$2>=$I8,$H8,0) -> 25000 | AC8: =IF(AC$2>=$I8,$H8,0) -> 25000 | AD8: =IF(AD$2>=$I8,$H8,0) -> 25000 | ... AT8: =IF(AT$2>=$I8,$H8,0) -> 25000
B9: NEW | D9: COO | E9: Executive | F9: G&A | G9: 300000 | H9: =G9/12 -> 25000 | I9: 45962 | Q9: =IF(Q$2>=$I9,$H9,0) -> 0 | R9: =IF(R$2>=$I9,$H9,0) -> 0 | S9: =IF(S$2>=$I9,$H9,0) -> 0 | T9: =IF(T$2>=$I9,$H9,0) -> 0 | W9: =IF(W$2>=$I9,$H9,0) -> 25000 | X9: =IF(X$2>=$I9,$H9,0) -> 25000 | Y9: =IF(Y$2>=$I9,$H9,0) -> 25000 | Z9: =IF(Z$2>=$I9,$H9,0) -> 25000 | AA9: =IF(AA$2>=$I9,$H9,0) -> 25000 | AB9: =IF(AB$2>=$I9,$H9,0) -> 25000 | AC9: =IF(AC$2>=$I9,$H9,0) -> 25000 | AD9: =IF(AD$2>=$I9,$H9,0) -> 25000 | ... AT9: =IF(AT$2>=$I9,$H9,0) -> 25000
A10: 5 | B10: Cohen | C10: Nate | D10: Directors, Business Dev | E10: Business Dev | F10: Business Dev | G10: 200000 | H10: =G10/12 -> 16666.667 | I10: 45139 | K10: 16666.667 | L10: 16666.667 | M10: 16666.667 | N10: 16666.667 | O10: 16666.667 | P10: 16666.667 | Q10: 16666.667 | R10: 16666.667 | S10: 16666.667 | T10: 16666.667 | U10: 16666.667 | V10: 16666.667 | W10: =IF(W$2>=$I10,$H10,0) -> 16666.667 | X10: =IF(X$2>=$I10,$H10,0) -> 16666.667 | Y10: =IF(Y$2>=$I10,$H10,0) -> 16666.667 | Z10: =IF(Z$2>=$I10,$H10,0) -> 16666.667 | AA10: =IF(AA$2>=$I10,$H10,0) -> 16666.667 | AB10: =IF(AB$2>=$I10,$H10,0) -> 16666.667 | AC10: =IF(AC$2>=$I10,$H10,0) -> 16666.667 | AD10: =IF(AD$2>=$I10,$H10,0) -> 16666.667 | ... AT10: =IF(AT$2>=$I10,$H10,0) -> 16666.667
A11: 6 | B11: Dodson | C11: Danielle | D11: HR Director | E11: HR | F11: G&A | G11: 125000 | H11: =G11/12 -> 10416.667 | I11: 45627 | K11: 7916.6667 | L11: 7916.6667 | M11: 7916.6667 | N11: 7916.6667 | O11: 7916.6667 | P11: 7916.6667 | Q11: 7916.6667 | R11: 7916.6667 | S11: 7916.6667 | T11: 7916.6667 | U11: 7916.6667 | V11: 7916.6667 | W11: =IF(W$2>=$I11,$H11,0) -> 10416.667 | X11: =IF(X$2>=$I11,$H11,0) -> 10416.667 | Y11: =IF(Y$2>=$I11,$H11,0) -> 10416.667 | Z11: =IF(Z$2>=$I11,$H11,0) -> 10416.667 | AA11: =IF(AA$2>=$I11,$H11,0) -> 10416.667 | AB11: =IF(AB$2>=$I11,$H11,0) -> 10416.667 | AC11: =IF(AC$2>=$I11,$H11,0) -> 10416.667 | AD11: =IF(AD$2>=$I11,$H11,0) -> 10416.667 | ... AT11: =IF(AT$2>=$I11,$H11,0) -> 10416.667
A12: 7 | B12: Kulfan | C12: Jaclyn | D12: Ops Director | E12: Operations | F12: G&A | G12: 135000 | H12: =G12/12 -> 11250 | I12: 45741 | K12: 0 | L12: 0 | M12: 0 | N12: 11250 | O12: 11250 | P12: 11250 | Q12: 11250 | R12: 11250 | S12: 11250 | T12: 11250 | U12: 11250 | V12: 11250 | W12: =IF(W$2>=$I12,$H12,0) -> 11250 | X12: =IF(X$2>=$I12,$H12,0) -> 11250 | Y12: =IF(Y$2>=$I12,$H12,0) -> 11250 | Z12: =IF(Z$2>=$I12,$H12,0) -> 11250 | AA12: =IF(AA$2>=$I12,$H12,0) -> 11250 | AB12: =IF(AB$2>=$I12,$H12,0) -> 11250 | AC12: =IF(AC$2>=$I12,$H12,0) -> 11250 | AD12: =IF(AD$2>=$I12,$H12,0) -> 11250 | ... AT12: =IF(AT$2>=$I12,$H12,0) -> 11250
A13: 8 | B13: Kawaski | C13: Bailey | D13: Office Manager | E13: Finance Admin | F13: G&A | G13: 44000 | H13: =G13/12 -> 3666.6667 | I13: 45931 | K13: 0 | L13: 0 | M13: 0 | N13: 0 | O13: 0 | P13: 0 | Q13: 0 | R13: 0 | S13: 0 | T13: 3666.6667 | U13: 3666.6667 | V13: 3666.6667 | W13: =IF(W$2>=$I13,$H13,0) -> 3666.6667 | X13: =IF(X$2>=$I13,$H13,0) -> 3666.6667 | Y13: =IF(Y$2>=$I13,$H13,0) -> 3666.6667 | Z13: =IF(Z$2>=$I13,$H13,0) -> 3666.6667 | AA13: =IF(AA$2>=$I13,$H13,0) -> 3666.6667 | AB13: =IF(AB$2>=$I13,$H13,0) -> 3666.6667 | AC13: =IF(AC$2>=$I13,$H13,0) -> 3666.6667 | AD13: =IF(AD$2>=$I13,$H13,0) -> 3666.6667 | ... AT13: =IF(AT$2>=$I13,$H13,0) -> 3666.6667
A14: 9 | B14: Kluger | C14: Kasiah | D14: Mgr, Provider Recruiting | E14: Clinical Ops | F14: Clinical Ops | G14: 70000 | H14: =G14/12 -> 5833.3333 | I14: 45444 | K14: 5833.3333 | L14: 5833.3333 | M14: 5833.3333 | N14: 5833.3333 | O14: 5833.3333 | P14: 5833.3333 | Q14: 5833.3333 | R14: 5833.3333 | S14: 5833.3333 | T14: 5833.3333 | U14: 5833.3333 | V14: 5833.3333 | W14: =IF(W$2>=$I14,$H14,0) -> 5833.3333 | X14: =IF(X$2>=$I14,$H14,0) -> 5833.3333 | Y14: =IF(Y$2>=$I14,$H14,0) -> 5833.3333 | Z14: =IF(Z$2>=$I14,$H14,0) -> 5833.3333 | AA14: =IF(AA$2>=$I14,$H14,0) -> 5833.3333 | AB14: =IF(AB$2>=$I14,$H14,0) -> 5833.3333 | AC14: =IF(AC$2>=$I14,$H14,0) -> 5833.3333 | AD14: =IF(AD$2>=$I14,$H14,0) -> 5833.3333 | ... AT14: =IF(AT$2>=$I14,$H14,0) -> 5833.3333
A15: 10 | B15: Aviva | C15: David | D15: Mgr, Provider Recruiting | E15: Clinical Ops | F15: Clinical Ops | G15: 82500 | H15: =G15/12 -> 6875 | I15: 45335 | K15: 6875 | L15: 6875 | M15: 6875 | N15: 6875 | O15: 6875 | P15: 6875 | Q15: 6875 | R15: 6875 | S15: 6875 | T15: 6875 | U15: 6875 | V15: 6875 | W15: =IF(W$2>=$I15,$H15,0) -> 6875 | X15: =IF(X$2>=$I15,$H15,0) -> 6875 | Y15: =IF(Y$2>=$I15,$H15,0) -> 6875 | Z15: =IF(Z$2>=$I15,$H15,0) -> 6875 | AA15: =IF(AA$2>=$I15,$H15,0) -> 6875 | AB15: =IF(AB$2>=$I15,$H15,0) -> 6875 | AC15: =IF(AC$2>=$I15,$H15,0) -> 6875 | AD15: =IF(AD$2>=$I15,$H15,0) -> 6875 | ... AT15: =IF(AT$2>=$I15,$H15,0) -> 6875
A16: 11 | B16: Gallegos | C16: Martha | D16: Case Mgr, PI | E16: Clinical Ops | F16: PI | G16: 57000 | H16: =G16/12 -> 4750 | I16: 45839 | K16: 0 | L16: 0 | M16: 0 | N16: 0 | O16: 0 | P16: 0 | Q16: 4750 | R16: 4750 | S16: 4750 | T16: 4750 | U16: 4750 | V16: 4750 | W16: =IF(W$2>=$I16,$H16,0) -> 4750 | X16: =IF(X$2>=$I16,$H16,0) -> 4750 | Y16: =IF(Y$2>=$I16,$H16,0) -> 4750 | Z16: =IF(Z$2>=$I16,$H16,0) -> 4750 | AA16: =IF(AA$2>=$I16,$H16,0) -> 4750 | AB16: =IF(AB$2>=$I16,$H16,0) -> 4750 | AC16: =IF(AC$2>=$I16,$H16,0) -> 4750 | AD16: =IF(AD$2>=$I16,$H16,0) -> 4750 | ... AT16: =IF(AT$2>=$I16,$H16,0) -> 4750
A17: 12 | B17: Zuckerberg | C17: Beth | D17: Biz Dev, PI | E17: Business Dev | F17: PI | G17: 125000 | H17: =G17/12 -> 10416.667 | I17: 45754 | K17: 0 | L17: 0 | M17: 0 | N17: 0 | O17: 10416.667 | P17: 10416.667 | Q17: 10416.667 | R17: 10416.667 | S17: 10416.667 | T17: 10416.667 | U17: 10416.667 | V17: 10416.667 | W17: =IF(W$2>=$I17,$H17,0) -> 10416.667 | X17: =IF(X$2>=$I17,$H17,0) -> 10416.667 | Y17: =IF(Y$2>=$I17,$H17,0) -> 10416.667 | Z17: =IF(Z$2>=$I17,$H17,0) -> 10416.667 | AA17: =IF(AA$2>=$I17,$H17,0) -> 10416.667 | AB17: =IF(AB$2>=$I17,$H17,0) -> 10416.667 | AC17: =IF(AC$2>=$I17,$H17,0) -> 10416.667 | AD17: =IF(AD$2>=$I17,$H17,0) -> 10416.667 | ... AT17: =IF(AT$2>=$I17,$H17,0) -> 10416.667
A18: 13 | B18: Rafael | C18: Ayden | D18: Biz Dev, Jr Assoc | E18: Business Dev | F18: PI | G18: 55000 | H18: =G18/12 -> 4583.3333 | I18: 45817 | K18: 0 | L18: 0 | M18: 0 | N18: 0 | O18: 0 | P18: 0 | Q18: 4583.3333 | R18: 4583.3333 | S18: 4583.3333 | T18: 4583.3333 | U18: 4583.3333 | V18: 4583.3333 | W18: =IF(W$2>=$I18,$H18,0) -> 4583.3333 | X18: =IF(X$2>=$I18,$H18,0) -> 4583.3333 | Y18: =IF(Y$2>=$I18,$H18,0) -> 4583.3333 | Z18: =IF(Z$2>=$I18,$H18,0) -> 4583.3333 | AA18: =IF(AA$2>=$I18,$H18,0) -> 4583.3333 | AB18: =IF(AB$2>=$I18,$H18,0) -> 4583.3333 | AC18: =IF(AC$2>=$I18,$H18,0) -> 4583.3333 | AD18: =IF(AD$2>=$I18,$H18,0) -> 4583.3333 | ... AT18: =IF(AT$2>=$I18,$H18,0) -> 4583.3333
A19: 14 | B19: Rincon | C19: Ashlee | D19: Director, Clinical Ops | E19: Clinical Ops | F19: PI | G19: 125000 | H19: =G19/12 -> 10416.667 | I19: 45784 | K19: 0 | L19: 0 | M19: 0 | N19: 0 | O19: 0 | P19: 10416.667 | Q19: 10416.667 | R19: 10416.667 | S19: 10416.667 | T19: 10416.667 | U19: 10416.667 | V19: 10416.667 | W19: =IF(W$2>=$I19,$H19,0) -> 10416.667 | X19: =IF(X$2>=$I19,$H19,0) -> 10416.667 | Y19: =IF(Y$2>=$I19,$H19,0) -> 10416.667 | Z19: =IF(Z$2>=$I19,$H19,0) -> 10416.667 | AA19: =IF(AA$2>=$I19,$H19,0) -> 10416.667 | AB19: =IF(AB$2>=$I19,$H19,0) -> 10416.667 | AC19: =IF(AC$2>=$I19,$H19,0) -> 10416.667 | AD19: =IF(AD$2>=$I19,$H19,0) -> 10416.667 | ... AT19: =IF(AT$2>=$I19,$H19,0) -> 10416.667
A20: 15 | B20: Locke | C20: Ashley | D20: Clinical Ops Mgr | E20: Clinical Ops | F20: PI | G20: 48000 | H20: =G20/12 -> 4000 | I20: 45717 | K20: 0 | L20: 0 | M20: 4000 | N20: 4000 | O20: 4000 | P20: 4000 | Q20: 4000 | R20: 4000 | S20: 4000 | T20: 4000 | U20: 4000 | V20: 4000 | W20: =IF(W$2>=$I20,$H20,0) -> 4000 | X20: =IF(X$2>=$I20,$H20,0) -> 4000 | Y20: =IF(Y$2>=$I20,$H20,0) -> 4000 | Z20: =IF(Z$2>=$I20,$H20,0) -> 4000 | AA20: =IF(AA$2>=$I20,$H20,0) -> 4000 | AB20: =IF(AB$2>=$I20,$H20,0) -> 4000 | AC20: =IF(AC$2>=$I20,$H20,0) -> 4000 | AD20: =IF(AD$2>=$I20,$H20,0) -> 4000 | ... AT20: =IF(AT$2>=$I20,$H20,0) -> 4000
A21: 16 | B21: Chapman | C21: Chelsea | D21: Clinical Care Coordinator | E21: Clinical Ops | F21: PI | G21: 53000 | H21: =G21/12 -> 4416.6667 | I21: 45708 | K21: 0 | L21: 0 | M21: 4416.6667 | N21: 4416.6667 | O21: 4416.6667 | P21: 4416.6667 | Q21: 4416.6667 | R21: 4416.6667 | S21: 4416.6667 | T21: 4416.6667 | U21: 4416.6667 | V21: 4416.6667 | W21: =IF(W$2>=$I21,$H21,0) -> 4416.6667 | X21: =IF(X$2>=$I21,$H21,0) -> 4416.6667 | Y21: =IF(Y$2>=$I21,$H21,0) -> 4416.6667 | Z21: =IF(Z$2>=$I21,$H21,0) -> 4416.6667 | AA21: =IF(AA$2>=$I21,$H21,0) -> 4416.6667 | AB21: =IF(AB$2>=$I21,$H21,0) -> 4416.6667 | AC21: =IF(AC$2>=$I21,$H21,0) -> 4416.6667 | AD21: =IF(AD$2>=$I21,$H21,0) -> 4416.6667 | ... AT21: =IF(AT$2>=$I21,$H21,0) -> 4416.6667
... A24: 21 | B24: Kanter | C24: Yishai | D24: IT Solutions Engineer | E24: Technolgy | F24: Technology | G24: 75000 | H24: =G24/12 -> 6250 | I24: 45233 | K24: 6250 | L24: 6250 | M24: 6250 | N24: 6250 | O24: 6250 | P24: 6250 | Q24: 6250 | R24: 6250 | S24: 6250 | T24: 6250 | U24: 6250 | V24: 6250 | W24: =IF(W$2>=$I24,$H24,0) -> 6250 | X24: =IF(X$2>=$I24,$H24,0) -> 6250 | Y24: =IF(Y$2>=$I24,$H24,0) -> 6250 | Z24: =IF(Z$2>=$I24,$H24,0) -> 6250 | AA24: =IF(AA$2>=$I24,$H24,0) -> 6250 | AB24: =IF(AB$2>=$I24,$H24,0) -> 6250 | AC24: =IF(AC$2>=$I24,$H24,0) -> 6250 | AD24: =IF(AD$2>=$I24,$H24,0) -> 6250 | ... AT24: =IF(AT$2>=$I24,$H24,0) -> 6250
A25: 1 | D25: QA | E25: Clinical Ops | F25: SaaS | G25: 75000 | H25: =G25/12 -> 6250 | I25: 46143 | Q25: =IF(Q$2>=$I25,$H25,0) -> 0 | R25: =IF(R$2>=$I25,$H25,0) -> 0 | S25: =IF(S$2>=$I25,$H25,0) -> 0 | T25: =IF(T$2>=$I25,$H25,0) -> 0 | U25: =IF(U$2>=$I25,$H25,0) -> 0 | V25: =IF(V$2>=$I25,$H25,0) -> 0 | W25: =IF(W$2>=$I25,$H25,0) -> 0 | X25: =IF(X$2>=$I25,$H25,0) -> 0 | ... AT25: =IF(AT$2>=$I25,$H25,0) -> 6250
A26: 2 | D26: QA | E26: Clinical Ops | F26: SaaS | G26: 75000 | H26: =G26/12 -> 6250 | I26: 46692 | Q26: =IF(Q$2>=$I26,$H26,0) -> 0 | R26: =IF(R$2>=$I26,$H26,0) -> 0 | S26: =IF(S$2>=$I26,$H26,0) -> 0 | T26: =IF(T$2>=$I26,$H26,0) -> 0 | W26: =IF(W$2>=$I26,$H26,0) -> 0 | X26: =IF(X$2>=$I26,$H26,0) -> 0 | Y26: =IF(Y$2>=$I26,$H26,0) -> 0 | Z26: =IF(Z$2>=$I26,$H26,0) -> 0 | AA26: =IF(AA$2>=$I26,$H26,0) -> 0 | AB26: =IF(AB$2>=$I26,$H26,0) -> 0 | AC26: =IF(AC$2>=$I26,$H26,0) -> 0 | AD26: =IF(AD$2>=$I26,$H26,0) -> 0 | ... AT26: =IF(AT$2>=$I26,$H26,0) -> 6250
A27: 3 | D27: Provider Liaison/Training | E27: Clinical Ops | F27: Clinical Ops | G27: 125000 | H27: =G27/12 -> 10416.667 | I27: 45992 | Q27: =IF(Q$2>=$I27,$H27,0) -> 0 | R27: =IF(R$2>=$I27,$H27,0) -> 0 | S27: =IF(S$2>=$I27,$H27,0) -> 0 | T27: =IF(T$2>=$I27,$H27,0) -> 0 | W27: =IF(W$2>=$I27,$H27,0) -> 10416.667 | X27: =IF(X$2>=$I27,$H27,0) -> 10416.667 | Y27: =IF(Y$2>=$I27,$H27,0) -> 10416.667 | Z27: =IF(Z$2>=$I27,$H27,0) -> 10416.667 | AA27: =IF(AA$2>=$I27,$H27,0) -> 10416.667 | AB27: =IF(AB$2>=$I27,$H27,0) -> 10416.667 | AC27: =IF(AC$2>=$I27,$H27,0) -> 10416.667 | AD27: =IF(AD$2>=$I27,$H27,0) -> 10416.667 | ... AT27: =IF(AT$2>=$I27,$H27,0) -> 10416.667
A28: 4 | D28: Provider Liaison/Training | E28: Clinical Ops | F28: Clinical Ops | G28: 125000 | H28: =G28/12 -> 10416.667 | I28: 46174 | Q28: =IF(Q$2>=$I28,$H28,0) -> 0 | R28: =IF(R$2>=$I28,$H28,0) -> 0 | S28: =IF(S$2>=$I28,$H28,0) -> 0 | T28: =IF(T$2>=$I28,$H28,0) -> 0 | W28: =IF(W$2>=$I28,$H28,0) -> 0 | X28: =IF(X$2>=$I28,$H28,0) -> 0 | Y28: =IF(Y$2>=$I28,$H28,0) -> 0 | Z28: =IF(Z$2>=$I28,$H28,0) -> 0 | AA28: =IF(AA$2>=$I28,$H28,0) -> 0 | AB28: =IF(AB$2>=$I28,$H28,0) -> 10416.667 | AC28: =IF(AC$2>=$I28,$H28,0) -> 10416.667 | AD28: =IF(AD$2>=$I28,$H28,0) -> 10416.667 | ... AT28: =IF(AT$2>=$I28,$H28,0) -> 10416.667
A29: 5 | D29: Provider Liaison/Training | E29: Clinical Ops | F29: Clinical Ops | G29: 125000 | H29: =G29/12 -> 10416.667 | I29: 46266 | Q29: =IF(Q$2>=$I29,$H29,0) -> 0 | R29: =IF(R$2>=$I29,$H29,0) -> 0 | S29: =IF(S$2>=$I29,$H29,0) -> 0 | T29: =IF(T$2>=$I29,$H29,0) -> 0 | W29: =IF(W$2>=$I29,$H29,0) -> 0 | X29: =IF(X$2>=$I29,$H29,0) -> 0 | Y29: =IF(Y$2>=$I29,$H29,0) -> 0 | Z29: =IF(Z$2>=$I29,$H29,0) -> 0 | AA29: =IF(AA$2>=$I29,$H29,0) -> 0 | AB29: =IF(AB$2>=$I29,$H29,0) -> 0 | AC29: =IF(AC$2>=$I29,$H29,0) -> 0 | AD29: =IF(AD$2>=$I29,$H29,0) -> 0 | ... AT29: =IF(AT$2>=$I29,$H29,0) -> 10416.667
A30: 6 | D30: Provider Liaison/Training | E30: Clinical Ops | F30: Clinical Ops | G30: 125000 | H30: =G30/12 -> 10416.667 | I30: 46419 | Q30: =IF(Q$2>=$I30,$H30,0) -> 0 | R30: =IF(R$2>=$I30,$H30,0) -> 0 | S30: =IF(S$2>=$I30,$H30,0) -> 0 | T30: =IF(T$2>=$I30,$H30,0) -> 0 | W30: =IF(W$2>=$I30,$H30,0) -> 0 | X30: =IF(X$2>=$I30,$H30,0) -> 0 | Y30: =IF(Y$2>=$I30,$H30,0) -> 0 | Z30: =IF(Z$2>=$I30,$H30,0) -> 0 | AA30: =IF(AA$2>=$I30,$H30,0) -> 0 | AB30: =IF(AB$2>=$I30,$H30,0) -> 0 | AC30: =IF(AC$2>=$I30,$H30,0) -> 0 | AD30: =IF(AD$2>=$I30,$H30,0) -> 0 | ... AT30: =IF(AT$2>=$I30,$H30,0) -> 10416.667
A31: 7 | D31: Provider Recruiting | E31: Clinical Ops | F31: Clinical Ops | G31: 90000 | H31: =G31/12 -> 7500 | I31: 45962 | Q31: =IF(Q$2>=$I31,$H31,0) -> 0 | R31: =IF(R$2>=$I31,$H31,0) -> 0 | S31: =IF(S$2>=$I31,$H31,0) -> 0 | T31: =IF(T$2>=$I31,$H31,0) -> 0 | W31: =IF(W$2>=$I31,$H31,0) -> 7500 | X31: =IF(X$2>=$I31,$H31,0) -> 7500 | Y31: =IF(Y$2>=$I31,$H31,0) -> 7500 | Z31: =IF(Z$2>=$I31,$H31,0) -> 7500 | AA31: =IF(AA$2>=$I31,$H31,0) -> 7500 | AB31: =IF(AB$2>=$I31,$H31,0) -> 7500 | AC31: =IF(AC$2>=$I31,$H31,0) -> 7500 | AD31: =IF(AD$2>=$I31,$H31,0) -> 7500 | ... AT31: =IF(AT$2>=$I31,$H31,0) -> 7500
A32: 8 | D32: Provider Recruiting | E32: Clinical Ops | F32: Clinical Ops | G32: 90000 | H32: =G32/12 -> 7500 | I32: 46143 | Q32: =IF(Q$2>=$I32,$H32,0) -> 0 | R32: =IF(R$2>=$I32,$H32,0) -> 0 | S32: =IF(S$2>=$I32,$H32,0) -> 0 | T32: =IF(T$2>=$I32,$H32,0) -> 0 | W32: =IF(W$2>=$I32,$H32,0) -> 0 | X32: =IF(X$2>=$I32,$H32,0) -> 0 | Y32: =IF(Y$2>=$I32,$H32,0) -> 0 | Z32: =IF(Z$2>=$I32,$H32,0) -> 0 | AA32: =IF(AA$2>=$I32,$H32,0) -> 7500 | AB32: =IF(AB$2>=$I32,$H32,0) -> 7500 | AC32: =IF(AC$2>=$I32,$H32,0) -> 7500 | AD32: =IF(AD$2>=$I32,$H32,0) -> 7500 | ... AT32: =IF(AT$2>=$I32,$H32,0) -> 7500
A33: 9 | D33: Provider Recruiting | E33: Clinical Ops | F33: Clinical Ops | G33: 90000 | H33: =G33/12 -> 7500 | I33: 46235 | Q33: =IF(Q$2>=$I33,$H33,0) -> 0 | R33: =IF(R$2>=$I33,$H33,0) -> 0 | S33: =IF(S$2>=$I33,$H33,0) -> 0 | T33: =IF(T$2>=$I33,$H33,0) -> 0 | U33: =IF(U$2>=$I33,$H33,0) -> 0 | V33: =IF(V$2>=$I33,$H33,0) -> 0 | W33: =IF(W$2>=$I33,$H33,0) -> 0 | X33: =IF(X$2>=$I33,$H33,0) -> 0 | ... AT33: =IF(AT$2>=$I33,$H33,0) -> 7500
A34: 10 | D34: Provider Recruiting | E34: Clinical Ops | F34: Clinical Ops | G34: 90000 | H34: =G34/12 -> 7500 | I34: 46388 | Q34: =IF(Q$2>=$I34,$H34,0) -> 0 | R34: =IF(R$2>=$I34,$H34,0) -> 0 | S34: =IF(S$2>=$I34,$H34,0) -> 0 | T34: =IF(T$2>=$I34,$H34,0) -> 0 | U34: =IF(U$2>=$I34,$H34,0) -> 0 | V34: =IF(V$2>=$I34,$H34,0) -> 0 | W34: =IF(W$2>=$I34,$H34,0) -> 0 | X34: =IF(X$2>=$I34,$H34,0) -> 0 | ... AT34: =IF(AT$2>=$I34,$H34,0) -> 7500
A35: 11 | D35: Subscrptions | E35: Clinical Ops | F35: Clinical Ops | G35: 75000 | H35: =G35/12 -> 6250 | I35: 46813 | Q35: =IF(Q$2>=$I35,$H35,0) -> 0 | R35: =IF(R$2>=$I35,$H35,0) -> 0 | S35: =IF(S$2>=$I35,$H35,0) -> 0 | T35: =IF(T$2>=$I35,$H35,0) -> 0 | U35: =IF(U$2>=$I35,$H35,0) -> 0 | V35: =IF(V$2>=$I35,$H35,0) -> 0 | W35: =IF(W$2>=$I35,$H35,0) -> 0 | X35: =IF(X$2>=$I35,$H35,0) -> 0 | ... AT35: =IF(AT$2>=$I35,$H35,0) -> 0
A36: 12 | D36: Subscrptions | E36: Clinical Ops | F36: Clinical Ops | G36: 75000 | H36: =G36/12 -> 6250 | I36: 46813 | Q36: =IF(Q$2>=$I36,$H36,0) -> 0 | R36: =IF(R$2>=$I36,$H36,0) -> 0 | S36: =IF(S$2>=$I36,$H36,0) -> 0 | T36: =IF(T$2>=$I36,$H36,0) -> 0 | U36: =IF(U$2>=$I36,$H36,0) -> 0 | V36: =IF(V$2>=$I36,$H36,0) -> 0 | W36: =IF(W$2>=$I36,$H36,0) -> 0 | X36: =IF(X$2>=$I36,$H36,0) -> 0 | ... AT36: =IF(AT$2>=$I36,$H36,0) -> 0
A37: 13 | D37: Subscrptions | E37: Clinical Ops | F37: Clinical Ops | G37: 75000 | H37: =G37/12 -> 6250 | I37: 46813 | Q37: =IF(Q$2>=$I37,$H37,0) -> 0 | R37: =IF(R$2>=$I37,$H37,0) -> 0 | S37: =IF(S$2>=$I37,$H37,0) -> 0 | T37: =IF(T$2>=$I37,$H37,0) -> 0 | U37: =IF(U$2>=$I37,$H37,0) -> 0 | V37: =IF(V$2>=$I37,$H37,0) -> 0 | W37: =IF(W$2>=$I37,$H37,0) -> 0 | X37: =IF(X$2>=$I37,$H37,0) -> 0 | ... AT37: =IF(AT$2>=$I37,$H37,0) -> 0
A38: 14 | D38: Med-legal Clinical Manager | E38: Clinical Ops | F38: PI | G38: 70000 | H38: =G38/12 -> 5833.3333 | J38: 2 | Q38: =IF(Worksheet!M$306>=$J38,Staffing!$H38,0) -> 0 | R38: =IF(Worksheet!N$306>=$J38,Staffing!$H38,0) -> 0 | S38: =IF(Worksheet!O$306>=$J38,Staffing!$H38,0) -> 0 | T38: =IF(Worksheet!P$306>=$J38,Staffing!$H38,0) -> 0 | U38: =IF(Worksheet!Q$306>=$J38,Staffing!$H38,0) -> 0 | V38: =IF(Worksheet!R$306>=$J38,Staffing!$H38,0) -> 0 | W38: =IF(Worksheet!S$306>=$J38,Staffing!$H38,0) -> 0 | X38: =IF(Worksheet!T$306>=$J38,Staffing!$H38,0) -> 0 | ... AT38: =IF(Worksheet!AP$306>=$J38,Staffing!$H38,0) -> 5833.3333
A39: 15 | D39: Med-legal Clinical Manager | E39: Clinical Ops | F39: PI | G39: 70000 | H39: =G39/12 -> 5833.3333 | J39: 3 | Q39: =IF(Worksheet!M$306>=$J39,Staffing!$H39,0) -> 0 | R39: =IF(Worksheet!N$306>=$J39,Staffing!$H39,0) -> 0 | S39: =IF(Worksheet!O$306>=$J39,Staffing!$H39,0) -> 0 | T39: =IF(Worksheet!P$306>=$J39,Staffing!$H39,0) -> 0 | U39: =IF(Worksheet!Q$306>=$J39,Staffing!$H39,0) -> 0 | V39: =IF(Worksheet!R$306>=$J39,Staffing!$H39,0) -> 0 | W39: =IF(Worksheet!S$306>=$J39,Staffing!$H39,0) -> 0 | X39: =IF(Worksheet!T$306>=$J39,Staffing!$H39,0) -> 0 | ... AT39: =IF(Worksheet!AP$306>=$J39,Staffing!$H39,0) -> 0
A40: 16 | D40: Med-legal Clinical Manager | E40: Clinical Ops | F40: PI | G40: 70000 | H40: =G40/12 -> 5833.3333 | J40: 4 | Q40: =IF(Worksheet!M$306>=$J40,Staffing!$H40,0) -> 0 | R40: =IF(Worksheet!N$306>=$J40,Staffing!$H40,0) -> 0 | S40: =IF(Worksheet!O$306>=$J40,Staffing!$H40,0) -> 0 | T40: =IF(Worksheet!P$306>=$J40,Staffing!$H40,0) -> 0 | U40: =IF(Worksheet!Q$306>=$J40,Staffing!$H40,0) -> 0 | V40: =IF(Worksheet!R$306>=$J40,Staffing!$H40,0) -> 0 | W40: =IF(Worksheet!S$306>=$J40,Staffing!$H40,0) -> 0 | X40: =IF(Worksheet!T$306>=$J40,Staffing!$H40,0) -> 0 | ... AT40: =IF(Worksheet!AP$306>=$J40,Staffing!$H40,0) -> 0
A41: 17 | D41: Med-legal Clinical Coord | E41: Clinical Ops | F41: PI | G41: 55000 | H41: =G41/12 -> 4583.3333 | J41: 2 | Q41: =IF(Worksheet!M$305>=$J41,Staffing!$H41,0) -> 0 | R41: =IF(Worksheet!N$305>=$J41,Staffing!$H41,0) -> 0 | S41: =IF(Worksheet!O$305>=$J41,Staffing!$H41,0) -> 0 | T41: =IF(Worksheet!P$305>=$J41,Staffing!$H41,0) -> 0 | U41: =IF(Worksheet!Q$305>=$J41,Staffing!$H41,0) -> 0 | W41: =IF(Worksheet!S$305>=$J41,Staffing!$H41,0) -> 4583.3333 | X41: =IF(Worksheet!T$305>=$J41,Staffing!$H41,0) -> 4583.3333 | Y41: =IF(Worksheet!U$305>=$J41,Staffing!$H41,0) -> 4583.3333 | Z41: =IF(Worksheet!V$305>=$J41,Staffing!$H41,0) -> 4583.3333 | AA41: =IF(Worksheet!W$305>=$J41,Staffing!$H41,0) -> 4583.3333 | AB41: =IF(Worksheet!X$305>=$J41,Staffing!$H41,0) -> 4583.3333 | AC41: =IF(Worksheet!Y$305>=$J41,Staffing!$H41,0) -> 4583.3333 | AD41: =IF(Worksheet!Z$305>=$J41,Staffing!$H41,0) -> 4583.3333 | ... AT41: =IF(Worksheet!AP$305>=$J41,Staffing!$H41,0) -> 4583.3333
A42: 18 | D42: Med-legal Clinical Coord | E42: Clinical Ops | F42: PI | G42: 55000 | H42: =G42/12 -> 4583.3333 | J42: 3 | Q42: =IF(Worksheet!M$306>=$J42,Staffing!$H42,0) -> 0 | R42: =IF(Worksheet!N$306>=$J42,Staffing!$H42,0) -> 0 | S42: =IF(Worksheet!O$306>=$J42,Staffing!$H42,0) -> 0 | T42: =IF(Worksheet!P$306>=$J42,Staffing!$H42,0) -> 0 | U42: =IF(Worksheet!Q$305>=$J42,Staffing!$H42,0) -> 0 | V42: =IF(Worksheet!R$305>=$J42,Staffing!$H42,0) -> 0 | W42: =IF(Worksheet!S$305>=$J42,Staffing!$H42,0) -> 0 | X42: =IF(Worksheet!T$305>=$J42,Staffing!$H42,0) -> 4583.3333 | Y42: =IF(Worksheet!U$305>=$J42,Staffing!$H42,0) -> 4583.3333 | Z42: =IF(Worksheet!V$305>=$J42,Staffing!$H42,0) -> 4583.3333 | AA42: =IF(Worksheet!W$305>=$J42,Staffing!$H42,0) -> 4583.3333 | AB42: =IF(Worksheet!X$305>=$J42,Staffing!$H42,0) -> 4583.3333 | ... AT42: =IF(Worksheet!AP$305>=$J42,Staffing!$H42,0) -> 4583.3333
A43: 19 | D43: Med-legal Clinical Coord | E43: Clinical Ops | F43: PI | G43: 55000 | H43: =G43/12 -> 4583.3333 | J43: 4 | Q43: =IF(Worksheet!M$305=4,Staffing!H$38,0) -> 0 | R43: =IF(Worksheet!N$305=4,Staffing!I$38,0) -> 0 | S43: =IF(Worksheet!O$305=4,Staffing!J$38,0) -> 0 | T43: =IF(Worksheet!P$305=4,Staffing!K$38,0) -> 0 | U43: =IF(Worksheet!Q$305>=$J43,Staffing!$H43,0) -> 0 | V43: =IF(Worksheet!R$305>=$J43,Staffing!$H43,0) -> 0 | W43: =IF(Worksheet!S$305>=$J43,Staffing!$H43,0) -> 0 | X43: =IF(Worksheet!T$305>=$J43,Staffing!$H43,0) -> 0 | Y43: =IF(Worksheet!U$305>=$J43,Staffing!$H43,0) -> 0 | Z43: =IF(Worksheet!V$305>=$J43,Staffing!$H43,0) -> 4583.3333 | AA43: =IF(Worksheet!W$305>=$J43,Staffing!$H43,0) -> 4583.3333 | AB43: =IF(Worksheet!X$305>=$J43,Staffing!$H43,0) -> 4583.3333 | ... AT43: =IF(Worksheet!AP$305>=$J43,Staffing!$H43,0) -> 4583.3333
A44: 20 | D44: Med-legal Clinical Coord | E44: Clinical Ops | F44: PI | G44: 55000 | H44: =G44/12 -> 4583.3333 | J44: 5 | Q44: =IF(Worksheet!M$305=5,Staffing!H$38,0) -> 0 | R44: =IF(Worksheet!N$305=5,Staffing!I$38,0) -> 0 | S44: =IF(Worksheet!O$305=5,Staffing!J$38,0) -> 0 | T44: =IF(Worksheet!P$305=5,Staffing!K$38,0) -> 0 | U44: =IF(Worksheet!Q$305>=$J44,Staffing!$H44,0) -> 0 | V44: =IF(Worksheet!R$305>=$J44,Staffing!$H44,0) -> 0 | W44: =IF(Worksheet!S$305>=$J44,Staffing!$H44,0) -> 0 | X44: =IF(Worksheet!T$305>=$J44,Staffing!$H44,0) -> 0 | Y44: =IF(Worksheet!U$305>=$J44,Staffing!$H44,0) -> 0 | Z44: =IF(Worksheet!V$305>=$J44,Staffing!$H44,0) -> 0 | AA44: =IF(Worksheet!W$305>=$J44,Staffing!$H44,0) -> 0 | AB44: =IF(Worksheet!X$305>=$J44,Staffing!$H44,0) -> 0 | ... AT44: =IF(Worksheet!AP$305>=$J44,Staffing!$H44,0) -> 4583.3333
A45: 21 | D45: Med-legal Clinical Coord | E45: Clinical Ops | F45: PI | G45: 55000 | H45: =G45/12 -> 4583.3333 | J45: 6 | Q45: =IF(Worksheet!M$305=6,Staffing!H$38,0) -> 0 | R45: =IF(Worksheet!N$305=6,Staffing!I$38,0) -> 0 | S45: =IF(Worksheet!O$305=6,Staffing!J$38,0) -> 0 | T45: =IF(Worksheet!P$305=6,Staffing!K$38,0) -> 0 | U45: =IF(Worksheet!Q$305>=$J45,Staffing!$H45,0) -> 0 | V45: =IF(Worksheet!R$305>=$J45,Staffing!$H45,0) -> 0 | W45: =IF(Worksheet!S$305>=$J45,Staffing!$H45,0) -> 0 | X45: =IF(Worksheet!T$305>=$J45,Staffing!$H45,0) -> 0 | Y45: =IF(Worksheet!U$305>=$J45,Staffing!$H45,0) -> 0 | Z45: =IF(Worksheet!V$305>=$J45,Staffing!$H45,0) -> 0 | AA45: =IF(Worksheet!W$305>=$J45,Staffing!$H45,0) -> 0 | AB45: =IF(Worksheet!X$305>=$J45,Staffing!$H45,0) -> 0 | ... AT45: =IF(Worksheet!AP$305>=$J45,Staffing!$H45,0) -> 4583.3333
A46: 22 | D46: Med-legal Clinical Coord | E46: Clinical Ops | F46: PI | G46: 55000 | H46: =G46/12 -> 4583.3333 | J46: 7 | Q46: =IF(Worksheet!M$305=7,Staffing!H$38,0) -> 0 | R46: =IF(Worksheet!N$305=7,Staffing!I$38,0) -> 0 | S46: =IF(Worksheet!O$305=7,Staffing!J$38,0) -> 0 | T46: =IF(Worksheet!P$305=7,Staffing!K$38,0) -> 0 | U46: =IF(Worksheet!Q$305>=$J46,Staffing!$H46,0) -> 0 | V46: =IF(Worksheet!R$305>=$J46,Staffing!$H46,0) -> 0 | W46: =IF(Worksheet!S$305>=$J46,Staffing!$H46,0) -> 0 | X46: =IF(Worksheet!T$305>=$J46,Staffing!$H46,0) -> 0 | Y46: =IF(Worksheet!U$305>=$J46,Staffing!$H46,0) -> 0 | Z46: =IF(Worksheet!V$305>=$J46,Staffing!$H46,0) -> 0 | AA46: =IF(Worksheet!W$305>=$J46,Staffing!$H46,0) -> 0 | AB46: =IF(Worksheet!X$305>=$J46,Staffing!$H46,0) -> 0 | ... AT46: =IF(Worksheet!AP$305>=$J46,Staffing!$H46,0) -> 4583.3333
A47: 23 | D47: Med-legal Clinical Coord | E47: Clinical Ops | F47: PI | G47: 55000 | H47: =G47/12 -> 4583.3333 | J47: 8 | Q47: =IF(Worksheet!M$305=8,Staffing!H$38,0) -> 0 | R47: =IF(Worksheet!N$305=8,Staffing!I$38,0) -> 0 | S47: =IF(Worksheet!O$305=8,Staffing!J$38,0) -> 0 | T47: =IF(Worksheet!P$305=8,Staffing!K$38,0) -> 0 | U47: =IF(Worksheet!Q$305>=$J47,Staffing!$H47,0) -> 0 | V47: =IF(Worksheet!R$305>=$J47,Staffing!$H47,0) -> 0 | W47: =IF(Worksheet!S$305>=$J47,Staffing!$H47,0) -> 0 | X47: =IF(Worksheet!T$305>=$J47,Staffing!$H47,0) -> 0 | Y47: =IF(Worksheet!U$305>=$J47,Staffing!$H47,0) -> 0 | Z47: =IF(Worksheet!V$305>=$J47,Staffing!$H47,0) -> 0 | AA47: =IF(Worksheet!W$305>=$J47,Staffing!$H47,0) -> 0 | AB47: =IF(Worksheet!X$305>=$J47,Staffing!$H47,0) -> 0 | ... AT47: =IF(Worksheet!AP$305>=$J47,Staffing!$H47,0) -> 4583.3333
A48: 24 | D48: Med-legal Clinical Coord | E48: Clinical Ops | F48: PI | G48: 55000 | H48: =G48/12 -> 4583.3333 | J48: 9 | Q48: =IF(Worksheet!M$305=9,Staffing!H$38,0) -> 0 | R48: =IF(Worksheet!N$305=9,Staffing!I$38,0) -> 0 | S48: =IF(Worksheet!O$305=9,Staffing!J$38,0) -> 0 | T48: =IF(Worksheet!P$305=9,Staffing!K$38,0) -> 0 | U48: =IF(Worksheet!Q$305>=$J48,Staffing!$H48,0) -> 0 | V48: =IF(Worksheet!R$305>=$J48,Staffing!$H48,0) -> 0 | W48: =IF(Worksheet!S$305>=$J48,Staffing!$H48,0) -> 0 | X48: =IF(Worksheet!T$305>=$J48,Staffing!$H48,0) -> 0 | Y48: =IF(Worksheet!U$305>=$J48,Staffing!$H48,0) -> 0 | Z48: =IF(Worksheet!V$305>=$J48,Staffing!$H48,0) -> 0 | AA48: =IF(Worksheet!W$305>=$J48,Staffing!$H48,0) -> 0 | AB48: =IF(Worksheet!X$305>=$J48,Staffing!$H48,0) -> 0 | ... AT48: =IF(Worksheet!AP$305>=$J48,Staffing!$H48,0) -> 4583.3333
A49: 25 | D49: Med-legal Clinical Coord | E49: Clinical Ops | F49: PI | G49: 55000 | H49: =G49/12 -> 4583.3333 | J49: 10 | Q49: =IF(Worksheet!M$305=10,Staffing!H$38,0) -> 0 | R49: =IF(Worksheet!N$305=10,Staffing!I$38,0) -> 0 | S49: =IF(Worksheet!O$305=10,Staffing!J$38,0) -> 0 | T49: =IF(Worksheet!P$305=10,Staffing!K$38,0) -> 0 | U49: =IF(Worksheet!Q$305>=$J49,Staffing!$H49,0) -> 0 | V49: =IF(Worksheet!R$305>=$J49,Staffing!$H49,0) -> 0 | W49: =IF(Worksheet!S$305>=$J49,Staffing!$H49,0) -> 0 | X49: =IF(Worksheet!T$305>=$J49,Staffing!$H49,0) -> 0 | Y49: =IF(Worksheet!U$305>=$J49,Staffing!$H49,0) -> 0 | Z49: =IF(Worksheet!V$305>=$J49,Staffing!$H49,0) -> 0 | AA49: =IF(Worksheet!W$305>=$J49,Staffing!$H49,0) -> 0 | AB49: =IF(Worksheet!X$305>=$J49,Staffing!$H49,0) -> 0 | ... AT49: =IF(Worksheet!AP$305>=$J49,Staffing!$H49,0) -> 0
A50: 1 | D50: IT Development | E50: Technolgy | F50: Technology | G50: 150000 | H50: =G50/12 -> 12500 | I50: 46023 | Q50: =IF(Q$2>=$I50,$H50,0) -> 0 | R50: =IF(R$2>=$I50,$H50,0) -> 0 | S50: =IF(S$2>=$I50,$H50,0) -> 0 | T50: =IF(T$2>=$I50,$H50,0) -> 0 | U50: =IF(U$2>=$I50,$H50,0) -> 0 | V50: =IF(V$2>=$I50,$H50,0) -> 0 | W50: =IF(W$2>=$I50,$H50,0) -> 12500 | X50: =IF(X$2>=$I50,$H50,0) -> 12500 | ... AT50: =IF(AT$2>=$I50,$H50,0) -> 12500
A51: 2 | D51: IT Development | E51: Technolgy | F51: Technology | G51: 150000 | H51: =G51/12 -> 12500 | I51: 46054 | Q51: =IF(Q$2>=$I51,$H51,0) -> 0 | R51: =IF(R$2>=$I51,$H51,0) -> 0 | S51: =IF(S$2>=$I51,$H51,0) -> 0 | T51: =IF(T$2>=$I51,$H51,0) -> 0 | U51: =IF(U$2>=$I51,$H51,0) -> 0 | V51: =IF(V$2>=$I51,$H51,0) -> 0 | W51: =IF(W$2>=$I51,$H51,0) -> 0 | X51: =IF(X$2>=$I51,$H51,0) -> 12500 | ... AT51: =IF(AT$2>=$I51,$H51,0) -> 12500
A52: 3 | D52: Infrastructure Mgmt | E52: Technolgy | F52: Technology | G52: 150000 | H52: =G52/12 -> 12500 | I52: 46082 | Q52: =IF(Q$2>=$I52,$H52,0) -> 0 | R52: =IF(R$2>=$I52,$H52,0) -> 0 | S52: =IF(S$2>=$I52,$H52,0) -> 0 | T52: =IF(T$2>=$I52,$H52,0) -> 0 | U52: =IF(U$2>=$I52,$H52,0) -> 0 | V52: =IF(V$2>=$I52,$H52,0) -> 0 | W52: =IF(W$2>=$I52,$H52,0) -> 0 | X52: =IF(X$2>=$I52,$H52,0) -> 0 | ... AT52: =IF(AT$2>=$I52,$H52,0) -> 12500
A53: 4 | D53: Data Analytics | E53: Technolgy | F53: Technology | G53: 115000 | H53: =G53/12 -> 9583.3333 | I53: 46235 | Q53: =IF(Q$2>=$I53,$H53,0) -> 0 | R53: =IF(R$2>=$I53,$H53,0) -> 0 | S53: =IF(S$2>=$I53,$H53,0) -> 0 | T53: =IF(T$2>=$I53,$H53,0) -> 0 | U53: =IF(U$2>=$I53,$H53,0) -> 0 | V53: =IF(V$2>=$I53,$H53,0) -> 0 | W53: =IF(W$2>=$I53,$H53,0) -> 0 | X53: =IF(X$2>=$I53,$H53,0) -> 0 | ... AT53: =IF(AT$2>=$I53,$H53,0) -> 9583.3333
A54: 5 | D54: Data Analytics | E54: Technolgy | F54: Technology | G54: 115000 | H54: =G54/12 -> 9583.3333 | I54: 46661 | Q54: =IF(Q$2>=$I54,$H54,0) -> 0 | R54: =IF(R$2>=$I54,$H54,0) -> 0 | S54: =IF(S$2>=$I54,$H54,0) -> 0 | T54: =IF(T$2>=$I54,$H54,0) -> 0 | U54: =IF(U$2>=$I54,$H54,0) -> 0 | V54: =IF(V$2>=$I54,$H54,0) -> 0 | W54: =IF(W$2>=$I54,$H54,0) -> 0 | X54: =IF(X$2>=$I54,$H54,0) -> 0 | ... AT54: =IF(AT$2>=$I54,$H54,0) -> 9583.3333
A55: 1 | D55: SaaS sales/Implement | E55: Business Dev | F55: SaaS | G55: 125000 | H55: =G55/12 -> 10416.667 | I55: =Worksheet!$C$13-151 -> 46023 | Q55: =IF(Q$2>=$I55,$H55,0) -> 0 | R55: =IF(R$2>=$I55,$H55,0) -> 0 | S55: =IF(S$2>=$I55,$H55,0) -> 0 | T55: =IF(T$2>=$I55,$H55,0) -> 0 | U55: =IF(U$2>=$I55,$H55,0) -> 0 | V55: =IF(V$2>=$I55,$H55,0) -> 0 | W55: =IF(W$2>=$I55,$H55,0) -> 10416.667 | X55: =IF(X$2>=$I55,$H55,0) -> 10416.667 | ... AT55: =IF(AT$2>=$I55,$H55,0) -> 10416.667
A56: 2 | D56: SaaS sales/Implement | E56: Business Dev | F56: SaaS | G56: 75000 | H56: =G56/12 -> 6250 | I56: =I55+91 -> 46114 | Q56: =IF(Q$2>=$I56,$H56,0) -> 0 | R56: =IF(R$2>=$I56,$H56,0) -> 0 | S56: =IF(S$2>=$I56,$H56,0) -> 0 | T56: =IF(T$2>=$I56,$H56,0) -> 0 | U56: =IF(U$2>=$I56,$H56,0) -> 0 | V56: =IF(V$2>=$I56,$H56,0) -> 0 | W56: =IF(W$2>=$I56,$H56,0) -> 0 | X56: =IF(X$2>=$I56,$H56,0) -> 0 | ... AT56: =IF(AT$2>=$I56,$H56,0) -> 6250
A57: 3 | D57: SaaS sales/Implement | E57: Business Dev | F57: SaaS | G57: 75000 | H57: =G57/12 -> 6250 | I57: =I56+91 -> 46205 | Q57: =IF(Q$2>=$I57,$H57,0) -> 0 | R57: =IF(R$2>=$I57,$H57,0) -> 0 | S57: =IF(S$2>=$I57,$H57,0) -> 0 | T57: =IF(T$2>=$I57,$H57,0) -> 0 | U57: =IF(U$2>=$I57,$H57,0) -> 0 | V57: =IF(V$2>=$I57,$H57,0) -> 0 | W57: =IF(W$2>=$I57,$H57,0) -> 0 | X57: =IF(X$2>=$I57,$H57,0) -> 0 | ... AT57: =IF(AT$2>=$I57,$H57,0) -> 6250
A58: 4 | D58: SaaS sales/Implement | E58: Business Dev | F58: SaaS | G58: 75000 | H58: =G58/12 -> 6250 | I58: =I57+183 -> 46388 | Q58: =IF(Q$2>=$I58,$H58,0) -> 0 | R58: =IF(R$2>=$I58,$H58,0) -> 0 | S58: =IF(S$2>=$I58,$H58,0) -> 0 | T58: =IF(T$2>=$I58,$H58,0) -> 0 | U58: =IF(U$2>=$I58,$H58,0) -> 0 | V58: =IF(V$2>=$I58,$H58,0) -> 0 | W58: =IF(W$2>=$I58,$H58,0) -> 0 | X58: =IF(X$2>=$I58,$H58,0) -> 0 | ... AT58: =IF(AT$2>=$I58,$H58,0) -> 6250
A59: 5 | D59: SaaS sales/Implement | E59: Business Dev | F59: SaaS | G59: 75000 | H59: =G59/12 -> 6250 | I59: =I58+181 -> 46569 | Q59: =IF(Q$2>=$I59,$H59,0) -> 0 | R59: =IF(R$2>=$I59,$H59,0) -> 0 | S59: =IF(S$2>=$I59,$H59,0) -> 0 | T59: =IF(T$2>=$I59,$H59,0) -> 0 | U59: =IF(U$2>=$I59,$H59,0) -> 0 | V59: =IF(V$2>=$I59,$H59,0) -> 0 | W59: =IF(W$2>=$I59,$H59,0) -> 0 | X59: =IF(X$2>=$I59,$H59,0) -> 0 | ... AT59: =IF(AT$2>=$I59,$H59,0) -> 6250
A60: 6 | D60: Marketing Ops Manager | E60: Business Dev | F60: Marketing | G60: 175000 | H60: =G60/12 -> 14583.333 | I60: 45992 | Q60: =IF(Q$2>=$I60,$H60,0) -> 0 | R60: =IF(R$2>=$I60,$H60,0) -> 0 | S60: =IF(S$2>=$I60,$H60,0) -> 0 | T60: =IF(T$2>=$I60,$H60,0) -> 0 | U60: =IF(U$2>=$I60,$H60,0) -> 0 | W60: =IF(W$2>=$I60,$H60,0) -> 14583.333 | X60: =IF(X$2>=$I60,$H60,0) -> 14583.333 | Y60: =IF(Y$2>=$I60,$H60,0) -> 14583.333 | Z60: =IF(Z$2>=$I60,$H60,0) -> 14583.333 | AA60: =IF(AA$2>=$I60,$H60,0) -> 14583.333 | AB60: =IF(AB$2>=$I60,$H60,0) -> 14583.333 | AC60: =IF(AC$2>=$I60,$H60,0) -> 14583.333 | AD60: =IF(AD$2>=$I60,$H60,0) -> 14583.333 | ... AT60: =IF(AT$2>=$I60,$H60,0) -> 14583.333
A61: 7 | D61: Campaign Manager | E61: Business Dev | F61: Marketing | G61: 125000 | H61: =G61/12 -> 10416.667 | I61: 46023 | Q61: =IF(Q$2>=$I61,$H61,0) -> 0 | R61: =IF(R$2>=$I61,$H61,0) -> 0 | S61: =IF(S$2>=$I61,$H61,0) -> 0 | T61: =IF(T$2>=$I61,$H61,0) -> 0 | U61: =IF(U$2>=$I61,$H61,0) -> 0 | W61: =IF(W$2>=$I61,$H61,0) -> 10416.667 | X61: =IF(X$2>=$I61,$H61,0) -> 10416.667 | Y61: =IF(Y$2>=$I61,$H61,0) -> 10416.667 | Z61: =IF(Z$2>=$I61,$H61,0) -> 10416.667 | AA61: =IF(AA$2>=$I61,$H61,0) -> 10416.667 | AB61: =IF(AB$2>=$I61,$H61,0) -> 10416.667 | AC61: =IF(AC$2>=$I61,$H61,0) -> 10416.667 | AD61: =IF(AD$2>=$I61,$H61,0) -> 10416.667 | ... AT61: =IF(AT$2>=$I61,$H61,0) -> 10416.667
A62: 8 | D62: Campaign Manager | E62: Business Dev | F62: Marketing | G62: 125000 | H62: =G62/12 -> 10416.667 | I62: 46113 | Q62: =IF(Q$2>=$I62,$H62,0) -> 0 | R62: =IF(R$2>=$I62,$H62,0) -> 0 | S62: =IF(S$2>=$I62,$H62,0) -> 0 | T62: =IF(T$2>=$I62,$H62,0) -> 0 | U62: =IF(U$2>=$I62,$H62,0) -> 0 | W62: =IF(W$2>=$I62,$H62,0) -> 0 | X62: =IF(X$2>=$I62,$H62,0) -> 0 | Y62: =IF(Y$2>=$I62,$H62,0) -> 0 | Z62: =IF(Z$2>=$I62,$H62,0) -> 10416.667 | AA62: =IF(AA$2>=$I62,$H62,0) -> 10416.667 | AB62: =IF(AB$2>=$I62,$H62,0) -> 10416.667 | AC62: =IF(AC$2>=$I62,$H62,0) -> 10416.667 | AD62: =IF(AD$2>=$I62,$H62,0) -> 10416.667 | ... AT62: =IF(AT$2>=$I62,$H62,0) -> 10416.667
A63: 9 | D63: Campaign Manager | E63: Business Dev | F63: Marketing | G63: 125000 | H63: =G63/12 -> 10416.667 | I63: 46204 | Q63: =IF(Q$2>=$I63,$H63,0) -> 0 | R63: =IF(R$2>=$I63,$H63,0) -> 0 | S63: =IF(S$2>=$I63,$H63,0) -> 0 | T63: =IF(T$2>=$I63,$H63,0) -> 0 | U63: =IF(U$2>=$I63,$H63,0) -> 0 | W63: =IF(W$2>=$I63,$H63,0) -> 0 | X63: =IF(X$2>=$I63,$H63,0) -> 0 | Y63: =IF(Y$2>=$I63,$H63,0) -> 0 | Z63: =IF(Z$2>=$I63,$H63,0) -> 0 | AA63: =IF(AA$2>=$I63,$H63,0) -> 0 | AB63: =IF(AB$2>=$I63,$H63,0) -> 0 | AC63: =IF(AC$2>=$I63,$H63,0) -> 10416.667 | AD63: =IF(AD$2>=$I63,$H63,0) -> 10416.667 | ... AT63: =IF(AT$2>=$I63,$H63,0) -> 10416.667
A64: 10 | D64: Campaign Manager | E64: Business Dev | F64: Marketing | G64: 125000 | H64: =G64/12 -> 10416.667 | I64: 46296 | Q64: =IF(Q$2>=$I64,$H64,0) -> 0 | R64: =IF(R$2>=$I64,$H64,0) -> 0 | S64: =IF(S$2>=$I64,$H64,0) -> 0 | T64: =IF(T$2>=$I64,$H64,0) -> 0 | U64: =IF(U$2>=$I64,$H64,0) -> 0 | W64: =IF(W$2>=$I64,$H64,0) -> 0 | X64: =IF(X$2>=$I64,$H64,0) -> 0 | Y64: =IF(Y$2>=$I64,$H64,0) -> 0 | Z64: =IF(Z$2>=$I64,$H64,0) -> 0 | AA64: =IF(AA$2>=$I64,$H64,0) -> 0 | AB64: =IF(AB$2>=$I64,$H64,0) -> 0 | AC64: =IF(AC$2>=$I64,$H64,0) -> 0 | AD64: =IF(AD$2>=$I64,$H64,0) -> 0 | ... AT64: =IF(AT$2>=$I64,$H64,0) -> 10416.667
A65: 11 | D65: CRM Administrator | E65: Business Dev | F65: Marketing | G65: 150000 | H65: =G65/12 -> 12500 | I65: 46023 | Q65: =IF(Q$2>=$I65,$H65,0) -> 0 | R65: =IF(R$2>=$I65,$H65,0) -> 0 | S65: =IF(S$2>=$I65,$H65,0) -> 0 | T65: =IF(T$2>=$I65,$H65,0) -> 0 | U65: =IF(U$2>=$I65,$H65,0) -> 0 | W65: =IF(W$2>=$I65,$H65,0) -> 12500 | X65: =IF(X$2>=$I65,$H65,0) -> 12500 | Y65: =IF(Y$2>=$I65,$H65,0) -> 12500 | Z65: =IF(Z$2>=$I65,$H65,0) -> 12500 | AA65: =IF(AA$2>=$I65,$H65,0) -> 12500 | AB65: =IF(AB$2>=$I65,$H65,0) -> 12500 | AC65: =IF(AC$2>=$I65,$H65,0) -> 12500 | AD65: =IF(AD$2>=$I65,$H65,0) -> 12500 | ... AT65: =IF(AT$2>=$I65,$H65,0) -> 12500
A66: 12 | D66: PR Relations Analyst | E66: Business Dev | F66: Marketing | G66: 100000 | H66: =G66/12 -> 8333.3333 | I66: 46023 | Q66: =IF(Q$2>=$I66,$H66,0) -> 0 | R66: =IF(R$2>=$I66,$H66,0) -> 0 | S66: =IF(S$2>=$I66,$H66,0) -> 0 | T66: =IF(T$2>=$I66,$H66,0) -> 0 | U66: =IF(U$2>=$I66,$H66,0) -> 0 | W66: =IF(W$2>=$I66,$H66,0) -> 8333.3333 | X66: =IF(X$2>=$I66,$H66,0) -> 8333.3333 | Y66: =IF(Y$2>=$I66,$H66,0) -> 8333.3333 | Z66: =IF(Z$2>=$I66,$H66,0) -> 8333.3333 | AA66: =IF(AA$2>=$I66,$H66,0) -> 8333.3333 | AB66: =IF(AB$2>=$I66,$H66,0) -> 8333.3333 | AC66: =IF(AC$2>=$I66,$H66,0) -> 8333.3333 | AD66: =IF(AD$2>=$I66,$H66,0) -> 8333.3333 | ... AT66: =IF(AT$2>=$I66,$H66,0) -> 8333.3333
A67: 13 | D67: Industry Dev, Manager | E67: Business Dev | F67: Business Dev | G67: 140000 | H67: =G67/12 -> 11666.667 | I67: 45992 | Q67: =IF(Q$2>=$I67,$H67,0) -> 0 | R67: =IF(R$2>=$I67,$H67,0) -> 0 | S67: =IF(S$2>=$I67,$H67,0) -> 0 | T67: =IF(T$2>=$I67,$H67,0) -> 0 | U67: =IF(U$2>=$I67,$H67,0) -> 0 | W67: =IF(W$2>=$I67,$H67,0) -> 11666.667 | X67: =IF(X$2>=$I67,$H67,0) -> 11666.667 | Y67: =IF(Y$2>=$I67,$H67,0) -> 11666.667 | Z67: =IF(Z$2>=$I67,$H67,0) -> 11666.667 | AA67: =IF(AA$2>=$I67,$H67,0) -> 11666.667 | AB67: =IF(AB$2>=$I67,$H67,0) -> 11666.667 | AC67: =IF(AC$2>=$I67,$H67,0) -> 11666.667 | AD67: =IF(AD$2>=$I67,$H67,0) -> 11666.667 | ... AT67: =IF(AT$2>=$I67,$H67,0) -> 11666.667
A68: 14 | D68: Industry Dev, Associate | E68: Business Dev | F68: Business Dev | G68: 120000 | H68: =G68/12 -> 10000 | I68: 46113 | Q68: =IF(Q$2>=$I68,$H68,0) -> 0 | R68: =IF(R$2>=$I68,$H68,0) -> 0 | S68: =IF(S$2>=$I68,$H68,0) -> 0 | T68: =IF(T$2>=$I68,$H68,0) -> 0 | U68: =IF(U$2>=$I68,$H68,0) -> 0 | W68: =IF(W$2>=$I68,$H68,0) -> 0 | X68: =IF(X$2>=$I68,$H68,0) -> 0 | Y68: =IF(Y$2>=$I68,$H68,0) -> 0 | Z68: =IF(Z$2>=$I68,$H68,0) -> 10000 | AA68: =IF(AA$2>=$I68,$H68,0) -> 10000 | AB68: =IF(AB$2>=$I68,$H68,0) -> 10000 | AC68: =IF(AC$2>=$I68,$H68,0) -> 10000 | AD68: =IF(AD$2>=$I68,$H68,0) -> 10000 | ... AT68: =IF(AT$2>=$I68,$H68,0) -> 10000
A69: 15 | D69: Industry Dev, Associate | E69: Business Dev | F69: Business Dev | G69: 100000 | H69: =G69/12 -> 8333.3333 | I69: 46204 | Q69: =IF(Q$2>=$I69,$H69,0) -> 0 | R69: =IF(R$2>=$I69,$H69,0) -> 0 | S69: =IF(S$2>=$I69,$H69,0) -> 0 | T69: =IF(T$2>=$I69,$H69,0) -> 0 | U69: =IF(U$2>=$I69,$H69,0) -> 0 | W69: =IF(W$2>=$I69,$H69,0) -> 0 | X69: =IF(X$2>=$I69,$H69,0) -> 0 | Y69: =IF(Y$2>=$I69,$H69,0) -> 0 | Z69: =IF(Z$2>=$I69,$H69,0) -> 0 | AA69: =IF(AA$2>=$I69,$H69,0) -> 0 | AB69: =IF(AB$2>=$I69,$H69,0) -> 0 | AC69: =IF(AC$2>=$I69,$H69,0) -> 8333.3333 | AD69: =IF(AD$2>=$I69,$H69,0) -> 8333.3333 | ... AT69: =IF(AT$2>=$I69,$H69,0) -> 8333.3333
A70: 16 | D70: Industry Dev, Associate | E70: Business Dev | F70: Business Dev | G70: 100000 | H70: =G70/12 -> 8333.3333 | I70: 46296 | Q70: =IF(Q$2>=$I70,$H70,0) -> 0 | R70: =IF(R$2>=$I70,$H70,0) -> 0 | S70: =IF(S$2>=$I70,$H70,0) -> 0 | T70: =IF(T$2>=$I70,$H70,0) -> 0 | U70: =IF(U$2>=$I70,$H70,0) -> 0 | V70: =IF(V$2>=$I70,$H70,0) -> 0 | W70: =IF(W$2>=$I70,$H70,0) -> 0 | X70: =IF(X$2>=$I70,$H70,0) -> 0 | ... AT70: =IF(AT$2>=$I70,$H70,0) -> 8333.3333
A71: 17 | D71: Industry Dev, Associate | E71: Business Dev | F71: Business Dev | G71: 100000 | H71: =G71/12 -> 8333.3333 | I71: 46388 | Q71: =IF(Q$2>=$I71,$H71,0) -> 0 | R71: =IF(R$2>=$I71,$H71,0) -> 0 | S71: =IF(S$2>=$I71,$H71,0) -> 0 | T71: =IF(T$2>=$I71,$H71,0) -> 0 | U71: =IF(U$2>=$I71,$H71,0) -> 0 | V71: =IF(V$2>=$I71,$H71,0) -> 0 | W71: =IF(W$2>=$I71,$H71,0) -> 0 | X71: =IF(X$2>=$I71,$H71,0) -> 0 | ... AT71: =IF(AT$2>=$I71,$H71,0) -> 8333.3333
A72: 18 | D72: Industry Dev, Associate | E72: Business Dev | F72: Business Dev | G72: 100000 | H72: =G72/12 -> 8333.3333 | I72: 46753 | Q72: =IF(Q$2>=$I72,$H72,0) -> 0 | R72: =IF(R$2>=$I72,$H72,0) -> 0 | S72: =IF(S$2>=$I72,$H72,0) -> 0 | T72: =IF(T$2>=$I72,$H72,0) -> 0 | U72: =IF(U$2>=$I72,$H72,0) -> 0 | V72: =IF(V$2>=$I72,$H72,0) -> 0 | W72: =IF(W$2>=$I72,$H72,0) -> 0 | X72: =IF(X$2>=$I72,$H72,0) -> 0 | ... AT72: =IF(AT$2>=$I72,$H72,0) -> 0
A73: 19 | D73: Industry Dev, Associate | E73: Business Dev | F73: Business Dev | G73: 100000 | H73: =G73/12 -> 8333.3333 | I73: 46753 | Q73: =IF(Q$2>=$I73,$H73,0) -> 0 | R73: =IF(R$2>=$I73,$H73,0) -> 0 | S73: =IF(S$2>=$I73,$H73,0) -> 0 | T73: =IF(T$2>=$I73,$H73,0) -> 0 | U73: =IF(U$2>=$I73,$H73,0) -> 0 | V73: =IF(V$2>=$I73,$H73,0) -> 0 | W73: =IF(W$2>=$I73,$H73,0) -> 0 | X73: =IF(X$2>=$I73,$H73,0) -> 0 | ... AT73: =IF(AT$2>=$I73,$H73,0) -> 0
A74: 20 | D74: Ops Director, Compliance | E74: Business Dev | F74: HC Compliance | G74: 200000 | H74: =G74/12 -> 16666.667 | I74: =Worksheet!$C$15-92 -> 46204 | Q74: =IF(Q$2>=$I74,$H74,0) -> 0 | R74: =IF(R$2>=$I74,$H74,0) -> 0 | S74: =IF(S$2>=$I74,$H74,0) -> 0 | T74: =IF(T$2>=$I74,$H74,0) -> 0 | U74: =IF(U$2>=$I74,$H74,0) -> 0 | V74: =IF(V$2>=$I74,$H74,0) -> 0 | W74: =IF(W$2>=$I74,$H74,0) -> 0 | X74: =IF(X$2>=$I74,$H74,0) -> 0 | ... AT74: =IF(AT$2>=$I74,$H74,0) -> 16666.667
A75: 21 | D75: Compliance Developer | E75: Business Dev | F75: HC Compliance | G75: 150000 | H75: =G75/12 -> 12500 | I75: =Worksheet!$C$15+61 -> 46357 | Q75: =IF(Q$2>=$I75,$H75,0) -> 0 | R75: =IF(R$2>=$I75,$H75,0) -> 0 | S75: =IF(S$2>=$I75,$H75,0) -> 0 | T75: =IF(T$2>=$I75,$H75,0) -> 0 | U75: =IF(U$2>=$I75,$H75,0) -> 0 | V75: =IF(V$2>=$I75,$H75,0) -> 0 | W75: =IF(W$2>=$I75,$H75,0) -> 0 | X75: =IF(X$2>=$I75,$H75,0) -> 0 | ... AT75: =IF(AT$2>=$I75,$H75,0) -> 12500
A76: 22 | D76: Compliance Developer | E76: Business Dev | F76: HC Compliance | G76: 150000 | H76: =G76/12 -> 12500 | I76: =I75+152 -> 46509 | Q76: =IF(Q$2>=$I76,$H76,0) -> 0 | R76: =IF(R$2>=$I76,$H76,0) -> 0 | S76: =IF(S$2>=$I76,$H76,0) -> 0 | T76: =IF(T$2>=$I76,$H76,0) -> 0 | U76: =IF(U$2>=$I76,$H76,0) -> 0 | V76: =IF(V$2>=$I76,$H76,0) -> 0 | W76: =IF(W$2>=$I76,$H76,0) -> 0 | X76: =IF(X$2>=$I76,$H76,0) -> 0 | ... AT76: =IF(AT$2>=$I76,$H76,0) -> 12500
A77: 23 | D77: Compliance Developer | E77: Business Dev | F77: HC Compliance | G77: 150000 | H77: =G77/12 -> 12500 | I77: =I76+121 -> 46630 | Q77: =IF(Q$2>=$I77,$H77,0) -> 0 | R77: =IF(R$2>=$I77,$H77,0) -> 0 | S77: =IF(S$2>=$I77,$H77,0) -> 0 | T77: =IF(T$2>=$I77,$H77,0) -> 0 | U77: =IF(U$2>=$I77,$H77,0) -> 0 | V77: =IF(V$2>=$I77,$H77,0) -> 0 | W77: =IF(W$2>=$I77,$H77,0) -> 0 | X77: =IF(X$2>=$I77,$H77,0) -> 0 | ... AT77: =IF(AT$2>=$I77,$H77,0) -> 12500
A78: 24 | D78: Compliance Developer | E78: Business Dev | F78: HC Compliance | G78: 150000 | H78: =G78/12 -> 12500 | I78: =I77+121 -> 46751 | Q78: =IF(Q$2>=$I78,$H78,0) -> 0 | R78: =IF(R$2>=$I78,$H78,0) -> 0 | S78: =IF(S$2>=$I78,$H78,0) -> 0 | T78: =IF(T$2>=$I78,$H78,0) -> 0 | U78: =IF(U$2>=$I78,$H78,0) -> 0 | V78: =IF(V$2>=$I78,$H78,0) -> 0 | W78: =IF(W$2>=$I78,$H78,0) -> 0 | X78: =IF(X$2>=$I78,$H78,0) -> 0 | ... AT78: =IF(AT$2>=$I78,$H78,0) -> 0
A79: 25 | D79: Compliance Developer | E79: Business Dev | F79: HC Compliance | G79: 150000 | H79: =G79/12 -> 12500 | I79: =I78+121 -> 46872 | Q79: =IF(Q$2>=$I79,$H79,0) -> 0 | R79: =IF(R$2>=$I79,$H79,0) -> 0 | S79: =IF(S$2>=$I79,$H79,0) -> 0 | T79: =IF(T$2>=$I79,$H79,0) -> 0 | U79: =IF(U$2>=$I79,$H79,0) -> 0 | V79: =IF(V$2>=$I79,$H79,0) -> 0 | W79: =IF(W$2>=$I79,$H79,0) -> 0 | X79: =IF(X$2>=$I79,$H79,0) -> 0 | ... AT79: =IF(AT$2>=$I79,$H79,0) -> 0
A80: 27 | D80: Compliance Ops, Manager | E80: Business Dev | F80: HC Compliance | G80: 150000 | H80: =G80/12 -> 12500 | I80: =Worksheet!$C$15-61 -> 46235 | Q80: =IF(Q$2>=$I80,$H80,0) -> 0 | R80: =IF(R$2>=$I80,$H80,0) -> 0 | S80: =IF(S$2>=$I80,$H80,0) -> 0 | T80: =IF(T$2>=$I80,$H80,0) -> 0 | U80: =IF(U$2>=$I80,$H80,0) -> 0 | V80: =IF(V$2>=$I80,$H80,0) -> 0 | W80: =IF(W$2>=$I80,$H80,0) -> 0 | X80: =IF(X$2>=$I80,$H80,0) -> 0 | ... AT80: =IF(AT$2>=$I80,$H80,0) -> 12500
A81: 28 | D81: Compliance Ops, Associate | E81: Business Dev | F81: HC Compliance | G81: 125000 | H81: =G81/12 -> 10416.667 | I81: =I75 -> 46357 | Q81: =IF(Q$2>=$I81,$H81,0) -> 0 | R81: =IF(R$2>=$I81,$H81,0) -> 0 | S81: =IF(S$2>=$I81,$H81,0) -> 0 | T81: =IF(T$2>=$I81,$H81,0) -> 0 | U81: =IF(U$2>=$I81,$H81,0) -> 0 | V81: =IF(V$2>=$I81,$H81,0) -> 0 | W81: =IF(W$2>=$I81,$H81,0) -> 0 | X81: =IF(X$2>=$I81,$H81,0) -> 0 | ... AT81: =IF(AT$2>=$I81,$H81,0) -> 10416.667
A82: 28 | D82: Compliance Ops, Associate | E82: Business Dev | F82: HC Compliance | G82: 125000 | H82: =G82/12 -> 10416.667 | I82: =I81+121 -> 46478 | Q82: =IF(Q$2>=$I82,$H82,0) -> 0 | R82: =IF(R$2>=$I82,$H82,0) -> 0 | S82: =IF(S$2>=$I82,$H82,0) -> 0 | T82: =IF(T$2>=$I82,$H82,0) -> 0 | U82: =IF(U$2>=$I82,$H82,0) -> 0 | V82: =IF(V$2>=$I82,$H82,0) -> 0 | W82: =IF(W$2>=$I82,$H82,0) -> 0 | X82: =IF(X$2>=$I82,$H82,0) -> 0 | ... AT82: =IF(AT$2>=$I82,$H82,0) -> 10416.667
A83: 29 | D83: Compliance Ops, Associate | E83: Business Dev | F83: HC Compliance | G83: 100000 | H83: =G83/12 -> 8333.3333 | I83: =I82+121 -> 46599 | Q83: =IF(Q$2>=$I83,$H83,0) -> 0 | R83: =IF(R$2>=$I83,$H83,0) -> 0 | S83: =IF(S$2>=$I83,$H83,0) -> 0 | T83: =IF(T$2>=$I83,$H83,0) -> 0 | W83: =IF(W$2>=$I83,$H83,0) -> 0 | X83: =IF(X$2>=$I83,$H83,0) -> 0 | Y83: =IF(Y$2>=$I83,$H83,0) -> 0 | Z83: =IF(Z$2>=$I83,$H83,0) -> 0 | AA83: =IF(AA$2>=$I83,$H83,0) -> 0 | AB83: =IF(AB$2>=$I83,$H83,0) -> 0 | AC83: =IF(AC$2>=$I83,$H83,0) -> 0 | AD83: =IF(AD$2>=$I83,$H83,0) -> 0 | ... AT83: =IF(AT$2>=$I83,$H83,0) -> 8333.3333
A84: 30 | D84: Compliance Ops, Associate | E84: Business Dev | F84: HC Compliance | G84: 100000 | H84: =G84/12 -> 8333.3333 | I84: =I83+61 -> 46660 | Q84: =IF(Q$2>=$I84,$H84,0) -> 0 | R84: =IF(R$2>=$I84,$H84,0) -> 0 | S84: =IF(S$2>=$I84,$H84,0) -> 0 | T84: =IF(T$2>=$I84,$H84,0) -> 0 | W84: =IF(W$2>=$I84,$H84,0) -> 0 | X84: =IF(X$2>=$I84,$H84,0) -> 0 | Y84: =IF(Y$2>=$I84,$H84,0) -> 0 | Z84: =IF(Z$2>=$I84,$H84,0) -> 0 | AA84: =IF(AA$2>=$I84,$H84,0) -> 0 | AB84: =IF(AB$2>=$I84,$H84,0) -> 0 | AC84: =IF(AC$2>=$I84,$H84,0) -> 0 | AD84: =IF(AD$2>=$I84,$H84,0) -> 0 | ... AT84: =IF(AT$2>=$I84,$H84,0) -> 8333.3333
A85: 31 | D85: Compliance Ops, Associate | E85: Business Dev | F85: HC Compliance | G85: 100000 | H85: =G85/12 -> 8333.3333 | I85: =I84+61 -> 46721 | Q85: =IF(Q$2>=$I85,$H85,0) -> 0 | R85: =IF(R$2>=$I85,$H85,0) -> 0 | S85: =IF(S$2>=$I85,$H85,0) -> 0 | T85: =IF(T$2>=$I85,$H85,0) -> 0 | W85: =IF(W$2>=$I85,$H85,0) -> 0 | X85: =IF(X$2>=$I85,$H85,0) -> 0 | Y85: =IF(Y$2>=$I85,$H85,0) -> 0 | Z85: =IF(Z$2>=$I85,$H85,0) -> 0 | AA85: =IF(AA$2>=$I85,$H85,0) -> 0 | AB85: =IF(AB$2>=$I85,$H85,0) -> 0 | AC85: =IF(AC$2>=$I85,$H85,0) -> 0 | AD85: =IF(AD$2>=$I85,$H85,0) -> 0 | ... AT85: =IF(AT$2>=$I85,$H85,0) -> 8333.3333
A86: 1 | D86: Staff Recruiting/Onboarding | E86: HR | F86: G&A | G86: 75000 | H86: =G86/12 -> 6250 | I86: 45962 | Q86: =IF(Q$2>=$I86,$H86,0) -> 0 | R86: =IF(R$2>=$I86,$H86,0) -> 0 | S86: =IF(S$2>=$I86,$H86,0) -> 0 | T86: =IF(T$2>=$I86,$H86,0) -> 0 | W86: =IF(W$2>=$I86,$H86,0) -> 6250 | X86: =IF(X$2>=$I86,$H86,0) -> 6250 | Y86: =IF(Y$2>=$I86,$H86,0) -> 6250 | Z86: =IF(Z$2>=$I86,$H86,0) -> 6250 | AA86: =IF(AA$2>=$I86,$H86,0) -> 6250 | AB86: =IF(AB$2>=$I86,$H86,0) -> 6250 | AC86: =IF(AC$2>=$I86,$H86,0) -> 6250 | AD86: =IF(AD$2>=$I86,$H86,0) -> 6250 | ... AT86: =IF(AT$2>=$I86,$H86,0) -> 6250
A87: 2 | D87: Staff Recruiting/Onboarding | E87: HR | F87: G&A | G87: 75000 | H87: =G87/12 -> 6250 | I87: 46054 | Q87: =IF(Q$2>=$I87,$H87,0) -> 0 | R87: =IF(R$2>=$I87,$H87,0) -> 0 | S87: =IF(S$2>=$I87,$H87,0) -> 0 | T87: =IF(T$2>=$I87,$H87,0) -> 0 | W87: =IF(W$2>=$I87,$H87,0) -> 0 | X87: =IF(X$2>=$I87,$H87,0) -> 6250 | Y87: =IF(Y$2>=$I87,$H87,0) -> 6250 | Z87: =IF(Z$2>=$I87,$H87,0) -> 6250 | AA87: =IF(AA$2>=$I87,$H87,0) -> 6250 | AB87: =IF(AB$2>=$I87,$H87,0) -> 6250 | AC87: =IF(AC$2>=$I87,$H87,0) -> 6250 | AD87: =IF(AD$2>=$I87,$H87,0) -> 6250 | ... AT87: =IF(AT$2>=$I87,$H87,0) -> 6250
A88: 3 | D88: HR Associate | E88: HR | F88: G&A | G88: 50000 | H88: =G88/12 -> 4166.6667 | I88: 46204 | Q88: =IF(Q$2>=$I88,$H88,0) -> 0 | R88: =IF(R$2>=$I88,$H88,0) -> 0 | S88: =IF(S$2>=$I88,$H88,0) -> 0 | T88: =IF(T$2>=$I88,$H88,0) -> 0 | U88: =IF(U$2>=$I88,$H88,0) -> 0 | V88: =IF(V$2>=$I88,$H88,0) -> 0 | W88: =IF(W$2>=$I88,$H88,0) -> 0 | X88: =IF(X$2>=$I88,$H88,0) -> 0 | ... AT88: =IF(AT$2>=$I88,$H88,0) -> 4166.6667
A89: 1 | D89: In-house Attorney | E89: Fin, Legal & Admin | F89: G&A | G89: 150000 | H89: =G89/12 -> 12500 | I89: 46388 | Q89: =IF(Q$2>=$I89,$H89,0) -> 0 | R89: =IF(R$2>=$I89,$H89,0) -> 0 | S89: =IF(S$2>=$I89,$H89,0) -> 0 | T89: =IF(T$2>=$I89,$H89,0) -> 0 | U89: =IF(U$2>=$I89,$H89,0) -> 0 | V89: =IF(V$2>=$I89,$H89,0) -> 0 | W89: =IF(W$2>=$I89,$H89,0) -> 0 | X89: =IF(X$2>=$I89,$H89,0) -> 0 | ... AT89: =IF(AT$2>=$I89,$H89,0) -> 12500
A90: 2 | D90: Accountant | E90: Fin, Legal & Admin | F90: G&A | G90: 150000 | H90: =G90/12 -> 12500 | I90: 46388 | Q90: =IF(Q$2>=$I90,$H90,0) -> 0 | R90: =IF(R$2>=$I90,$H90,0) -> 0 | S90: =IF(S$2>=$I90,$H90,0) -> 0 | T90: =IF(T$2>=$I90,$H90,0) -> 0 | U90: =IF(U$2>=$I90,$H90,0) -> 0 | V90: =IF(V$2>=$I90,$H90,0) -> 0 | W90: =IF(W$2>=$I90,$H90,0) -> 0 | X90: =IF(X$2>=$I90,$H90,0) -> 0 | ... AT90: =IF(AT$2>=$I90,$H90,0) -> 12500
A91: 3 | D91: AR/AP Associate | E91: Fin, Legal & Admin | F91: G&A | G91: 75000 | H91: =G91/12 -> 6250 | I91: 46082 | Q91: =IF(Q$2>=$I91,$H91,0) -> 0 | R91: =IF(R$2>=$I91,$H91,0) -> 0 | S91: =IF(S$2>=$I91,$H91,0) -> 0 | T91: =IF(T$2>=$I91,$H91,0) -> 0 | U91: =IF(U$2>=$I91,$H91,0) -> 0 | V91: =IF(V$2>=$I91,$H91,0) -> 0 | W91: =IF(W$2>=$I91,$H91,0) -> 0 | X91: =IF(X$2>=$I91,$H91,0) -> 0 | ... AT91: =IF(AT$2>=$I91,$H91,0) -> 6250
A92: 4 | D92: AR/AP Associate | E92: Fin, Legal & Admin | F92: G&A | G92: 75000 | H92: =G92/12 -> 6250 | I92: 46539 | Q92: =IF(Q$2>=$I92,$H92,0) -> 0 | R92: =IF(R$2>=$I92,$H92,0) -> 0 | S92: =IF(S$2>=$I92,$H92,0) -> 0 | T92: =IF(T$2>=$I92,$H92,0) -> 0 | U92: =IF(U$2>=$I92,$H92,0) -> 0 | V92: =IF(V$2>=$I92,$H92,0) -> 0 | W92: =IF(W$2>=$I92,$H92,0) -> 0 | X92: =IF(X$2>=$I92,$H92,0) -> 0 | ... AT92: =IF(AT$2>=$I92,$H92,0) -> 6250
A93: 5 | D93: Assoc: Finance/Insurance | E93: Fin, Legal & Admin | F93: G&A | G93: 50000 | H93: =G93/12 -> 4166.6667 | I93: 46539 | Q93: =IF(Q$2>=$I93,$H93,0) -> 0 | R93: =IF(R$2>=$I93,$H93,0) -> 0 | S93: =IF(S$2>=$I93,$H93,0) -> 0 | T93: =IF(T$2>=$I93,$H93,0) -> 0 | U93: =IF(U$2>=$I93,$H93,0) -> 0 | V93: =IF(V$2>=$I93,$H93,0) -> 0 | W93: =IF(W$2>=$I93,$H93,0) -> 0 | X93: =IF(X$2>=$I93,$H93,0) -> 0 | ... AT93: =IF(AT$2>=$I93,$H93,0) -> 4166.6667
Q94: =IF(Q$2>=$I94,$H94,0) -> 0 | R94: =IF(R$2>=$I94,$H94,0) -> 0 | S94: =IF(S$2>=$I94,$H94,0) -> 0 | T94: =IF(T$2>=$I94,$H94,0) -> 0 | U94: =IF(U$2>=$I94,$H94,0) -> 0 | V94: =IF(V$2>=$I94,$H94,0) -> 0 | W94: =IF(W$2>=$I94,$H94,0) -> 0 | X94: =IF(X$2>=$I94,$H94,0) -> 0 | ... AT94: =IF(AT$2>=$I94,$H94,0) -> 0
Q95: =IF(Q$2>=$I95,$H95,0) -> 0 | R95: =IF(R$2>=$I95,$H95,0) -> 0 | S95: =IF(S$2>=$I95,$H95,0) -> 0 | T95: =IF(T$2>=$I95,$H95,0) -> 0 | U95: =IF(U$2>=$I95,$H95,0) -> 0 | V95: =IF(V$2>=$I95,$H95,0) -> 0 | W95: =IF(W$2>=$I95,$H95,0) -> 0 | X95: =IF(X$2>=$I95,$H95,0) -> 0 | ... AT95: =IF(AT$2>=$I95,$H95,0) -> 0
A97: CONTRACTORS:
B98: Last | C98: First | D98: Title | E98: Department | H98: Monthly | I98: Start Date
A99: 1 | B99: Contract 01 | K99: =IF(K$2>=$I99,$H99,0) -> 0 | L99: =IF(L$2>=$I99,$H99,0) -> 0 | M99: =IF(M$2>=$I99,$H99,0) -> 0 | N99: =IF(N$2>=$I99,$H99,0) -> 0 | O99: =IF(O$2>=$I99,$H99,0) -> 0 | P99: =IF(P$2>=$I99,$H99,0) -> 0 | Q99: =IF(Q$2>=$I99,$H99,0) -> 0 | R99: =IF(R$2>=$I99,$H99,0) -> 0 | ... AT99: =IF(AT$2>=$I99,$H99,0) -> 0
A100: 2 | B100: Contract 02 | K100: =IF(K$2>=$I100,$H100,0) -> 0 | L100: =IF(L$2>=$I100,$H100,0) -> 0 | M100: =IF(M$2>=$I100,$H100,0) -> 0 | N100: =IF(N$2>=$I100,$H100,0) -> 0 | O100: =IF(O$2>=$I100,$H100,0) -> 0 | P100: =IF(P$2>=$I100,$H100,0) -> 0 | Q100: =IF(Q$2>=$I100,$H100,0) -> 0 | R100: =IF(R$2>=$I100,$H100,0) -> 0 | ... AT100: =IF(AT$2>=$I100,$H100,0) -> 0
A101: 3 | B101: Contract 03 | K101: =IF(K$2>=$I101,$H101,0) -> 0 | L101: =IF(L$2>=$I101,$H101,0) -> 0 | M101: =IF(M$2>=$I101,$H101,0) -> 0 | N101: =IF(N$2>=$I101,$H101,0) -> 0 | O101: =IF(O$2>=$I101,$H101,0) -> 0 | P101: =IF(P$2>=$I101,$H101,0) -> 0 | Q101: =IF(Q$2>=$I101,$H101,0) -> 0 | R101: =IF(R$2>=$I101,$H101,0) -> 0 | ... AT101: =IF(AT$2>=$I101,$H101,0) -> 0
A102: 4 | B102: Contract 04 | K102: =IF(K$2>=$I102,$H102,0) -> 0 | L102: =IF(L$2>=$I102,$H102,0) -> 0 | M102: =IF(M$2>=$I102,$H102,0) -> 0 | N102: =IF(N$2>=$I102,$H102,0) -> 0 | O102: =IF(O$2>=$I102,$H102,0) -> 0 | P102: =IF(P$2>=$I102,$H102,0) -> 0 | Q102: =IF(Q$2>=$I102,$H102,0) -> 0 | R102: =IF(R$2>=$I102,$H102,0) -> 0 | ... AT102: =IF(AT$2>=$I102,$H102,0) -> 0
A103: 5 | B103: Contract 05 | K103: =IF(K$2>=$I103,$H103,0) -> 0 | L103: =IF(L$2>=$I103,$H103,0) -> 0 | M103: =IF(M$2>=$I103,$H103,0) -> 0 | N103: =IF(N$2>=$I103,$H103,0) -> 0 | O103: =IF(O$2>=$I103,$H103,0) -> 0 | P103: =IF(P$2>=$I103,$H103,0) -> 0 | Q103: =IF(Q$2>=$I103,$H103,0) -> 0 | R103: =IF(R$2>=$I103,$H103,0) -> 0 | ... AT103: =IF(AT$2>=$I103,$H103,0) -> 0
A104: 6 | B104: Contract 06 | K104: =IF(K$2>=$I104,$H104,0) -> 0 | L104: =IF(L$2>=$I104,$H104,0) -> 0 | M104: =IF(M$2>=$I104,$H104,0) -> 0 | N104: =IF(N$2>=$I104,$H104,0) -> 0 | O104: =IF(O$2>=$I104,$H104,0) -> 0 | P104: =IF(P$2>=$I104,$H104,0) -> 0 | Q104: =IF(Q$2>=$I104,$H104,0) -> 0 | R104: =IF(R$2>=$I104,$H104,0) -> 0 | ... AT104: =IF(AT$2>=$I104,$H104,0) -> 0
...

Sheet Product Rollout

Sheet Charts
A1: Annual | Q1: Monthly
A2: Charts | Q2: Charts
B4: Annual | I4: Income Statemtent - Balance Sheet | S4: 45658 | T4: 45689 | U4: 45717 | V4: 45748 | W4: 45778 | X4: 45809 | Y4: 45839 | Z4: 45870 | AA4: 45901 | AB4: 45931 | AC4: 45962 | AD4: 45992 | AE4: 46023 | AF4: 46054 | AG4: 46082 | AH4: 46113 | AI4: 46143 | AJ4: 46174 | AK4: 46204 | AL4: 46235 | AM4: 46266 | AN4: 46296 | AO4: 46327 | AP4: 46357 | AQ4: 46388 | AR4: 46419 | AS4: 46447 | AT4: 46478 | AU4: 46508 | AV4: 46539 | AW4: 46569 | AX4: 46600 | AY4: 46631 | AZ4: 46661 | BA4: 46692 | BB4: 46722
A6: ='Monthly Financial Reports'!C3 -> 0 | C6: ='Monthly Financial Reports'!BB3 -> 2024 | D6: ='Monthly Financial Reports'!BC3 -> 2025 | E6: ='Monthly Financial Reports'!BD3 -> 2026 | F6: ='Monthly Financial Reports'!BE3 -> 2027
J7: 2024 | K7: 2025 | L7: 2026 | M7: 2027 | R7: Cash | S7: ='Monthly Financial Reports'!Q66 -> 1337303.1 | T7: ='Monthly Financial Reports'!R66 -> 1111183.4 | U7: ='Monthly Financial Reports'!S66 -> 1210604.1 | V7: ='Monthly Financial Reports'!T66 -> 615697.93 | W7: ='Monthly Financial Reports'!U66 -> 985758.14 | X7: ='Monthly Financial Reports'!V66 -> 994792.37 | Y7: ='Monthly Financial Reports'!W66 -> 907889.66 | Z7: ='Monthly Financial Reports'!X66 -> 1040575.4 | ... BB7: ='Monthly Financial Reports'!AZ66 -> 64205898
A8: ='Monthly Financial Reports'!C5 -> Revenue | C8: ='Monthly Financial Reports'!BB5 -> 7078783.1 | D8: ='Monthly Financial Reports'!BC5 -> 14671987 | E8: ='Monthly Financial Reports'!BD5 -> 66233629 | F8: ='Monthly Financial Reports'!BE5 -> 1.7811425e+08 | H8: =A8 -> Revenue | R8: Accounts Receivable | S8: ='Monthly Financial Reports'!Q67 -> 0 | T8: ='Monthly Financial Reports'!R67 -> 0 | U8: ='Monthly Financial Reports'!S67 -> 0 | V8: ='Monthly Financial Reports'!T67 -> 12010 | W8: ='Monthly Financial Reports'!U67 -> 70315 | X8: ='Monthly Financial Reports'!V67 -> 221000 | Y8: ='Monthly Financial Reports'!W67 -> 1675882.7 | Z8: ='Monthly Financial Reports'!X67 -> 2163693.6 | ... BB8: ='Monthly Financial Reports'!AZ67 -> 59583125
B9: ='Monthly Financial Reports'!D6 -> VA Mental Health | C9: ='Monthly Financial Reports'!BB6 -> 6970768.1 | D9: ='Monthly Financial Reports'!BC6 -> 10955547 | E9: ='Monthly Financial Reports'!BD6 -> 17132940 | F9: ='Monthly Financial Reports'!BE6 -> 21077100 | I9: =B9 -> VA Mental Health | J9: =C9 -> 6970768.1 | K9: =D9 -> 10955547 | L9: =E9 -> 17132940 | M9: =F9 -> 21077100 | R9: Revenue | S9: ='Monthly Financial Reports'!Q5 -> 697873 | T9: ='Monthly Financial Reports'!R5 -> 605304 | U9: ='Monthly Financial Reports'!S5 -> 937772 | V9: ='Monthly Financial Reports'!T5 -> 850512 | W9: ='Monthly Financial Reports'!U5 -> 991397 | X9: ='Monthly Financial Reports'!V5 -> 951240 | Y9: ='Monthly Financial Reports'!W5 -> 1034942.6 | Z9: ='Monthly Financial Reports'!X5 -> 1263146.6 | ... BB9: ='Monthly Financial Reports'!AZ5 -> 22051622
B10: ='Monthly Financial Reports'!D7 -> VA Medical Exams | C10: ='Monthly Financial Reports'!BB7 -> 108015 | D10: ='Monthly Financial Reports'!BC7 -> 1040988 | E10: ='Monthly Financial Reports'!BD7 -> 4956620 | F10: ='Monthly Financial Reports'!BE7 -> 9468620 | I10: =B10 -> VA Medical Exams | J10: =C10 -> 108015 | K10: =D10 -> 1040988 | L10: =E10 -> 4956620 | M10: =F10 -> 9468620 | R10: Gross Profit | S10: ='Monthly Financial Reports'!Q17 -> 273063.13 | T10: ='Monthly Financial Reports'!R17 -> 177084.75 | U10: ='Monthly Financial Reports'!S17 -> 295550.75 | V10: ='Monthly Financial Reports'!T17 -> 142036.14 | W10: ='Monthly Financial Reports'!U17 -> 487224.99 | X10: ='Monthly Financial Reports'!V17 -> 372751.07 | Y10: ='Monthly Financial Reports'!W17 -> 536262.6 | Z10: ='Monthly Financial Reports'!X17 -> 774186.6 | ... BB10: ='Monthly Financial Reports'!AZ17 -> 8094480.8
B11: ='Monthly Financial Reports'!D8 -> Personal Injury | C11: ='Monthly Financial Reports'!BB8 -> 0 | D11: ='Monthly Financial Reports'!BC8 -> 2547952 | E11: ='Monthly Financial Reports'!BD8 -> 27817425 | F11: ='Monthly Financial Reports'!BE8 -> 50932946 | I11: =B11 -> Personal Injury | J11: =C11 -> 0 | K11: =D11 -> 2547952 | L11: =E11 -> 27817425 | M11: =F11 -> 50932946 | R11: EBITDA | S11: ='Monthly Financial Reports'!Q26 -> 98401.12 | T11: ='Monthly Financial Reports'!R26 -> -237693.74 | U11: ='Monthly Financial Reports'!S26 -> 96525.34 | V11: ='Monthly Financial Reports'!T26 -> -65535.8 | W11: ='Monthly Financial Reports'!U26 -> 454588.16 | X11: ='Monthly Financial Reports'!V26 -> 167633.18 | Y11: ='Monthly Financial Reports'!W26 -> 360965.43 | Z11: ='Monthly Financial Reports'!X26 -> 592199.1 | ... BB11: ='Monthly Financial Reports'!AZ26 -> 7096226.7
B12: ='Monthly Financial Reports'!D9 -> Workers Comp | C12: ='Monthly Financial Reports'!BB9 -> 0 | D12: ='Monthly Financial Reports'!BC9 -> 127500 | E12: ='Monthly Financial Reports'!BD9 -> 7650000 | F12: ='Monthly Financial Reports'!BE9 -> 19890000 | I12: =B12 -> Workers Comp | J12: =C12 -> 0 | K12: =D12 -> 127500 | L12: =E12 -> 7650000 | M12: =F12 -> 19890000 | R12: Accounts Payable | S12: ='Monthly Financial Reports'!Q73 -> 0 | T12: ='Monthly Financial Reports'!R73 -> 0 | U12: ='Monthly Financial Reports'!S73 -> 0 | V12: ='Monthly Financial Reports'!T73 -> 0 | W12: ='Monthly Financial Reports'!U73 -> 0 | X12: ='Monthly Financial Reports'!V73 -> 0 | Y12: ='Monthly Financial Reports'!W73 -> 512450.74 | Z12: ='Monthly Financial Reports'!X73 -> 642295 | ... BB12: ='Monthly Financial Reports'!AZ73 -> 13913755
B13: ='Monthly Financial Reports'!D10 -> SaaS | C13: ='Monthly Financial Reports'!BB10 -> 0 | D13: ='Monthly Financial Reports'!BC10 -> 0 | E13: ='Monthly Financial Reports'!BD10 -> 1125419.1 | F13: ='Monthly Financial Reports'!BE10 -> 9514199.7 | I13: =B13 -> SaaS | J13: =C13 -> 0 | K13: =D13 -> 0 | L13: =E13 -> 1125419.1 | M13: =F13 -> 9514199.7 | R13: Net Receivables | S13: =S8-S12 -> 0 | T13: =T8-T12 -> 0 | U13: =U8-U12 -> 0 | V13: =V8-V12 -> 12010 | W13: =W8-W12 -> 70315 | X13: =X8-X12 -> 221000 | Y13: =Y8-Y12 -> 1163432 | Z13: =Z8-Z12 -> 1521398.6 | ... BB13: =BB8-BB12 -> 45669370
B14: ='Monthly Financial Reports'!D11 -> Corrections | C14: ='Monthly Financial Reports'!BB11 -> 0 | D14: ='Monthly Financial Reports'!BC11 -> 0 | E14: ='Monthly Financial Reports'!BD11 -> 7514100 | F14: ='Monthly Financial Reports'!BE11 -> 65531400 | I14: =B14 -> Corrections | J14: =C14 -> 0 | K14: =D14 -> 0 | L14: =E14 -> 7514100 | M14: =F14 -> 65531400
B15: ='Monthly Financial Reports'!D12 -> Healthcare Compliance | C15: ='Monthly Financial Reports'!BB12 -> 0 | D15: ='Monthly Financial Reports'!BC12 -> 0 | E15: ='Monthly Financial Reports'!BD12 -> 37125 | F15: ='Monthly Financial Reports'!BE12 -> 1699987.5 | I15: =B15 -> Healthcare Compliance | J15: =C15 -> 0 | K15: =D15 -> 0 | L15: =E15 -> 37125 | M15: =F15 -> 1699987.5
B16: ='Monthly Financial Reports'!D13 -> Employee Wellness | C16: ='Monthly Financial Reports'!BB13 -> 0 | D16: ='Monthly Financial Reports'!BC13 -> 0 | E16: ='Monthly Financial Reports'!BD13 -> 0 | F16: ='Monthly Financial Reports'!BE13 -> 0 | I16: Total Revenue | J16: =C8 -> 7078783.1 | K16: =D8 -> 14671987 | L16: =E8 -> 66233629 | M16: =F8 -> 1.7811425e+08
C17: ='Monthly Financial Reports'!BB14 -> 0 | D17: ='Monthly Financial Reports'!BC14 -> 0 | E17: ='Monthly Financial Reports'!BD14 -> 0 | F17: ='Monthly Financial Reports'!BE14 -> 0 | H17: =A18 -> COGS | J17: =C18 -> 4503867 | K17: =D18 -> 6758123.6 | L17: =E18 -> 22489378 | M17: =F18 -> 91956882
A18: ='Monthly Financial Reports'!C15 -> COGS | C18: ='Monthly Financial Reports'!BB15 -> 4503867 | D18: ='Monthly Financial Reports'!BC15 -> 6758123.6 | E18: ='Monthly Financial Reports'!BD15 -> 22489378 | F18: ='Monthly Financial Reports'!BE15 -> 91956882 | H18: =A20 -> Gross Profit | J18: =C20 -> 2574916.1 | K18: =D20 -> 7913863.4 | L18: =E20 -> 43744250 | M18: =F20 -> 86157371
C19: ='Monthly Financial Reports'!BB16 -> 0 | D19: ='Monthly Financial Reports'!BC16 -> 0 | E19: ='Monthly Financial Reports'!BD16 -> 0 | F19: ='Monthly Financial Reports'!BE16 -> 0 | I19: =B21 -> Gross Margin | J19: =C21 -> 0.36375123 | K19: =D21 -> 0.53938593 | L19: =E21 -> 0.66045378 | M19: =F21 -> 0.48371969 | S19: =S4 -> 45658 | T19: =T4 -> 45689 | U19: =U4 -> 45717 | V19: =V4 -> 45748 | W19: =W4 -> 45778 | X19: =X4 -> 45809 | Y19: =Y4 -> 45839 | Z19: =Z4 -> 45870 | ... BB19: =BB4 -> 46722
A20: ='Monthly Financial Reports'!C17 -> Gross Profit | C20: ='Monthly Financial Reports'!BB17 -> 2574916.1 | D20: ='Monthly Financial Reports'!BC17 -> 7913863.4 | E20: ='Monthly Financial Reports'!BD17 -> 43744250 | F20: ='Monthly Financial Reports'!BE17 -> 86157371 | H20: =A23 -> Expenses | R20: =R7 -> Cash | S20: =S7 -> 1337303.1 | T20: =T7 -> 1111183.4 | U20: =U7 -> 1210604.1 | V20: =V7 -> 615697.93 | W20: =W7 -> 985758.14 | X20: =X7 -> 994792.37 | Y20: =Y7 -> 907889.66 | ... BB20: =BB7 -> 64205898
B21: ='Monthly Financial Reports'!D18 -> Gross Margin | C21: ='Monthly Financial Reports'!BB18 -> 0.36375123 | D21: ='Monthly Financial Reports'!BC18 -> 0.53938593 | E21: ='Monthly Financial Reports'!BD18 -> 0.66045378 | F21: ='Monthly Financial Reports'!BE18 -> 0.48371969 | I21: =B24 -> Technology | J21: =C24 -> 171650 | K21: =D24 -> 182487.04 | L21: =E24 -> 882042.71 | M21: =F24 -> 1066909.4 | R21: =R13 -> Net Receivables | S21: =S13 -> 0 | T21: =T13 -> 0 | U21: =U13 -> 0 | V21: =V13 -> 12010 | W21: =W13 -> 70315 | X21: =X13 -> 221000 | Y21: =Y13 -> 1163432 | ... BB21: =BB13 -> 45669370
C22: ='Monthly Financial Reports'!BB19 -> 0 | D22: ='Monthly Financial Reports'!BC19 -> 0 | E22: ='Monthly Financial Reports'!BD19 -> 0 | F22: ='Monthly Financial Reports'!BE19 -> 0 | I22: =B25 -> Marketing & Development | J22: =C25 -> 534189 | K22: =D25 -> 346185.62 | L22: =E25 -> 3995196.5 | M22: =F25 -> 4223961.5
A23: ='Monthly Financial Reports'!C20 -> Expenses | C23: ='Monthly Financial Reports'!BB20 -> 1630675 | D23: ='Monthly Financial Reports'!BC20 -> 2394328.7 | E23: ='Monthly Financial Reports'!BD20 -> 10536978 | F23: ='Monthly Financial Reports'!BE20 -> 11217840 | I23: =B26 -> Clinical Operations | J23: =C26 -> 229668 | K23: =D26 -> 349120.43 | L23: =E26 -> 2264444.5 | M23: =F26 -> 1886865.7
B24: ='Monthly Financial Reports'!D21 -> Technology | C24: ='Monthly Financial Reports'!BB21 -> 171650 | D24: ='Monthly Financial Reports'!BC21 -> 182487.04 | E24: ='Monthly Financial Reports'!BD21 -> 882042.71 | F24: ='Monthly Financial Reports'!BE21 -> 1066909.4 | I24: =B27 -> General Administrative | J24: =C27 -> 695168 | K24: =D27 -> 1516535.7 | L24: =E27 -> 3395294.6 | M24: =F27 -> 4040103
B25: ='Monthly Financial Reports'!D22 -> Marketing & Development | C25: ='Monthly Financial Reports'!BB22 -> 534189 | D25: ='Monthly Financial Reports'!BC22 -> 346185.62 | E25: ='Monthly Financial Reports'!BD22 -> 3995196.5 | F25: ='Monthly Financial Reports'!BE22 -> 4223961.5 | I25: Total Expenses | J25: =C23 -> 1630675 | K25: =D23 -> 2394328.7 | L25: =E23 -> 10536978 | M25: =F23 -> 11217840
B26: ='Monthly Financial Reports'!D23 -> Clinical Operations | C26: ='Monthly Financial Reports'!BB23 -> 229668 | D26: ='Monthly Financial Reports'!BC23 -> 349120.43 | E26: ='Monthly Financial Reports'!BD23 -> 2264444.5 | F26: ='Monthly Financial Reports'!BE23 -> 1886865.7 | H26: =A29 -> EBITDA | J26: =C29 -> 944241.07 | K26: =D29 -> 5519534.7 | L26: =E29 -> 33207272 | M26: =F29 -> 74939531
B27: ='Monthly Financial Reports'!D24 -> General Administrative | C27: ='Monthly Financial Reports'!BB24 -> 695168 | D27: ='Monthly Financial Reports'!BC24 -> 1516535.7 | E27: ='Monthly Financial Reports'!BD24 -> 3395294.6 | F27: ='Monthly Financial Reports'!BE24 -> 4040103 | I27: EBITDA Margin | J27: =C30 -> 0.13339031 | K27: =D30 -> 0.37619544 | L27: =E30 -> 0.50136574 | M27: =F30 -> 0.42073854
C28: ='Monthly Financial Reports'!BB25 -> 0 | D28: ='Monthly Financial Reports'!BC25 -> 0 | E28: ='Monthly Financial Reports'!BD25 -> 0 | F28: ='Monthly Financial Reports'!BE25 -> 0
A29: ='Monthly Financial Reports'!C26 -> EBITDA | C29: ='Monthly Financial Reports'!BB26 -> 944241.07 | D29: ='Monthly Financial Reports'!BC26 -> 5519534.7 | E29: ='Monthly Financial Reports'!BD26 -> 33207272 | F29: ='Monthly Financial Reports'!BE26 -> 74939531
B30: ='Monthly Financial Reports'!D27 -> EBIT Margin | C30: ='Monthly Financial Reports'!BB27 -> 0.13339031 | D30: ='Monthly Financial Reports'!BC27 -> 0.37619544 | E30: ='Monthly Financial Reports'!BD27 -> 0.50136574 | F30: ='Monthly Financial Reports'!BE27 -> 0.42073854 | J30: 2024 | K30: 2025 | L30: 2026 | M30: 2027
C31: ='Monthly Financial Reports'!BB28 -> 0 | D31: ='Monthly Financial Reports'!BC28 -> 0 | E31: ='Monthly Financial Reports'!BD28 -> 0 | F31: ='Monthly Financial Reports'!BE28 -> 0
B32: ='Monthly Financial Reports'!D29 -> Interest Expense | C32: ='Monthly Financial Reports'!BB29 -> 11108 | D32: ='Monthly Financial Reports'!BC29 -> 8970 | E32: ='Monthly Financial Reports'!BD29 -> 8724 | F32: ='Monthly Financial Reports'!BE29 -> 8436 | H32: =A67 -> ASSETS | J32: =C67 -> 1258371 | K32: =D67 -> 7514289.2 | L32: =E67 -> 42780908 | M32: =F67 -> 1.237906e+08
B33: ='Monthly Financial Reports'!D30 -> Income Tax | C33: ='Monthly Financial Reports'!BB30 -> 0 | D33: ='Monthly Financial Reports'!BC30 -> 1296454.6 | E33: ='Monthly Financial Reports'!BD30 -> 8600683.4 | F33: ='Monthly Financial Reports'!BE30 -> 19409339 | I33: Cash | J33: =C69 -> 1257232 | K33: =D69 -> 2602593.6 | L33: =E69 -> 11389945 | M33: =F69 -> 64205898
B34: ='Monthly Financial Reports'!D31 -> Depreciation | C34: ='Monthly Financial Reports'!BB31 -> 1200 | D34: ='Monthly Financial Reports'!BC31 -> 1200 | E34: ='Monthly Financial Reports'!BD31 -> 1200 | F34: ='Monthly Financial Reports'!BE31 -> 1200 | I34: =B70 -> Accounts Receivable | J34: =C70 -> 0 | K34: =D70 -> 4907723.6 | L34: =E70 -> 31388191 | M34: =F70 -> 59583125
B35: ='Monthly Financial Reports'!D32 -> Amortization | C35: ='Monthly Financial Reports'!BB32 -> 9000 | D35: ='Monthly Financial Reports'!BC32 -> 9030 | E35: ='Monthly Financial Reports'!BD32 -> 9276 | F35: ='Monthly Financial Reports'!BE32 -> 9564 | I35: =A71 -> Fixed Assets | J35: =C71 -> 1139 | K35: =D71 -> 3972 | L35: =E71 -> 2772 | M35: =F71 -> 1572
C36: ='Monthly Financial Reports'!BB33 -> 0 | D36: ='Monthly Financial Reports'!BC33 -> 0 | E36: ='Monthly Financial Reports'!BD33 -> 0 | F36: ='Monthly Financial Reports'!BE33 -> 0 | H36: =A73 -> LIABILITIES | J36: =C73 -> 198133 | K36: =D73 -> 2492984.6 | L36: =E73 -> 13345037 | M36: =F73 -> 33412669
A37: ='Monthly Financial Reports'!C34 -> Net Income | C37: ='Monthly Financial Reports'!BB34 -> 922933.07 | D37: ='Monthly Financial Reports'!BC34 -> 4203880 | E37: ='Monthly Financial Reports'!BD34 -> 24587389 | F37: ='Monthly Financial Reports'!BE34 -> 55510993 | I37: =A74 -> Current Liabilities | J37: =C74 -> 82446 | K37: =D74 -> 2446827.6 | L37: =E74 -> 13308156 | M37: =F74 -> 33385352
B38: ='Monthly Financial Reports'!D35 -> Net Margin | C38: ='Monthly Financial Reports'!BB35 -> 0.13038019 | D38: ='Monthly Financial Reports'!BC35 -> 0.28652425 | E38: ='Monthly Financial Reports'!BD35 -> 0.37122213 | F38: ='Monthly Financial Reports'!BE35 -> 0.31165946 | I38: =A78 -> Long-Term Liabilities | J38: =C78 -> 115687 | K38: =D78 -> 46157 | L38: =E78 -> 36881 | M38: =F78 -> 27317
C39: ='Monthly Financial Reports'!BB36 -> 0 | D39: ='Monthly Financial Reports'!BC36 -> 0 | E39: ='Monthly Financial Reports'!BD36 -> 0 | F39: ='Monthly Financial Reports'!BE36 -> 0 | H39: =A80 -> EQUITY | J39: =C80 -> 1060238 | K39: =D80 -> 5021304.5 | L39: =E80 -> 29435871 | M39: =F80 -> 90377926
C40: ='Monthly Financial Reports'!BB37 -> 0 | D40: ='Monthly Financial Reports'!BC37 -> 0 | E40: ='Monthly Financial Reports'!BD37 -> 0 | F40: ='Monthly Financial Reports'!BE37 -> 0
C41: ='Monthly Financial Reports'!BB38 -> 0 | D41: ='Monthly Financial Reports'!BC38 -> 0 | E41: ='Monthly Financial Reports'!BD38 -> 0 | F41: ='Monthly Financial Reports'!BE38 -> 0 | H41: =A88 -> LIABILITIES AND EQUITY | J41: =C88 -> 1258371 | K41: =D88 -> 7514289.2 | L41: =E88 -> 42780908 | M41: =F88 -> 1.237906e+08 | S41: =S19 -> 45658 | T41: =T19 -> 45689 | U41: =U19 -> 45717 | V41: =V19 -> 45748 | W41: =W19 -> 45778 | X41: =X19 -> 45809 | Y41: =Y19 -> 45839 | Z41: =Z19 -> 45870 | ... BB41: =BB19 -> 46722
C42: ='Monthly Financial Reports'!BB39 -> 2024 | D42: ='Monthly Financial Reports'!BC39 -> 2025 | E42: ='Monthly Financial Reports'!BD39 -> 2026 | F42: ='Monthly Financial Reports'!BE39 -> 2027 | R42: =R20 -> Cash | S42: =S20 -> 1337303.1 | T42: =T20 -> 1111183.4 | U42: =U20 -> 1210604.1 | V42: =V20 -> 615697.93 | W42: =W20 -> 985758.14 | X42: =X20 -> 994792.37 | Y42: =Y20 -> 907889.66 | ... BB42: =BB20 -> 64205898
C43: ='Monthly Financial Reports'!BB40 -> 0 | D43: ='Monthly Financial Reports'!BC40 -> 0 | E43: ='Monthly Financial Reports'!BD40 -> 0 | F43: ='Monthly Financial Reports'!BE40 -> 0 | R43: =R11 -> EBITDA | S43: =S11 -> 98401.12 | T43: =T11 -> -237693.74 | U43: =U11 -> 96525.34 | V43: =V11 -> -65535.8 | W43: =W11 -> 454588.16 | X43: =X11 -> 167633.18 | Y43: =Y11 -> 360965.43 | ... BB43: =BB11 -> 7096226.7
A44: ='Monthly Financial Reports'!C41 -> Starting Cash | C44: ='Monthly Financial Reports'!BB41 -> 299151 | D44: ='Monthly Financial Reports'!BC41 -> 1257232.1 | E44: ='Monthly Financial Reports'!BD41 -> 2602593.6 | F44: ='Monthly Financial Reports'!BE41 -> 11389945 | I44: Revenue vs EBITDA | R44: =R13 -> Net Receivables | S44: =S13 -> 0 | T44: =T13 -> 0 | U44: =U13 -> 0 | V44: =V13 -> 12010 | W44: =W13 -> 70315 | X44: =X13 -> 221000 | Y44: =Y13 -> 1163432 | ... BB44: =BB13 -> 45669370
C45: ='Monthly Financial Reports'!BB42 -> 0 | D45: ='Monthly Financial Reports'!BC42 -> 0 | E45: ='Monthly Financial Reports'!BD42 -> 0 | F45: ='Monthly Financial Reports'!BE42 -> 0 | J45: 2024 | K45: 2025-F | L45: 2026-F | M45: 2027-F
B46: ='Monthly Financial Reports'!D43 -> Net Income | C46: ='Monthly Financial Reports'!BB43 -> 922933.07 | D46: ='Monthly Financial Reports'!BC43 -> 4203880 | E46: ='Monthly Financial Reports'!BD43 -> 24587389 | F46: ='Monthly Financial Reports'!BE43 -> 55510993 | I46: =H8 -> Revenue | J46: =J16 -> 7078783.1 | K46: =K16 -> 14671987 | L46: =L16 -> 66233629 | M46: =M16 -> 1.7811425e+08
B47: ='Monthly Financial Reports'!D44 -> Recievables | C47: ='Monthly Financial Reports'!BB44 -> 0 | D47: ='Monthly Financial Reports'!BC44 -> -9836481.7 | E47: ='Monthly Financial Reports'!BD44 -> -65108210 | F47: ='Monthly Financial Reports'!BE44 -> -1.6860005e+08 | I47: =H26 -> EBITDA | J47: =J26 -> 944241.07 | K47: =K26 -> 5519534.7 | L47: =L26 -> 33207272 | M47: =M26 -> 74939531
B48: ='Monthly Financial Reports'!D45 -> Payables - COGS | C48: ='Monthly Financial Reports'!BB45 -> 24948 | D48: ='Monthly Financial Reports'!BC45 -> 4785505.7 | E48: ='Monthly Financial Reports'!BD45 -> 33945930 | F48: ='Monthly Financial Reports'!BE45 -> 105563495
B49: ='Monthly Financial Reports'!D46 -> Net Contribution Cash | C49: ='Monthly Financial Reports'!BB46 -> 0 | D49: ='Monthly Financial Reports'!BC46 -> 1369219.4 | E49: ='Monthly Financial Reports'!BD46 -> 8083934 | F49: ='Monthly Financial Reports'!BE46 -> 49657860 | R49: Product Rollout:
B50: ='Monthly Financial Reports'!D47 -> Net Expense Cash | C50: ='Monthly Financial Reports'!BB47 -> 0 | D50: ='Monthly Financial Reports'!BC47 -> 52085.406 | E50: ='Monthly Financial Reports'!BD47 -> 152328 | F50: ='Monthly Financial Reports'!BE47 -> 52675.208 | R50: =Worksheet!B9 -> VA - Mental Health | S50: =Worksheet!C9 -> 45292
B51: ='Monthly Financial Reports'!D48 -> Income Tax | C51: ='Monthly Financial Reports'!BB48 -> 0 | D51: ='Monthly Financial Reports'!BC48 -> 1296454.6 | E51: ='Monthly Financial Reports'!BD48 -> 8600683.4 | F51: ='Monthly Financial Reports'!BE48 -> 19409339 | R51: =Worksheet!B10 -> VA - Medical Evaluations | S51: =Worksheet!C10 -> 45658
B52: ='Monthly Financial Reports'!D49 -> Taxes Paid | C52: ='Monthly Financial Reports'!BB49 -> 0 | D52: ='Monthly Financial Reports'!BC49 -> 0 | E52: ='Monthly Financial Reports'!BD49 -> -1296454.6 | F52: ='Monthly Financial Reports'!BE49 -> -8600683.4 | R52: =Worksheet!B11 -> Personal Injury | S52: =Worksheet!C11 -> 45778
B53: ='Monthly Financial Reports'!D50 -> Interest Expense | C53: ='Monthly Financial Reports'!BB50 -> 0 | D53: ='Monthly Financial Reports'!BC50 -> -8970 | E53: ='Monthly Financial Reports'!BD50 -> -8724 | F53: ='Monthly Financial Reports'!BE50 -> -8436 | R53: =Worksheet!B12 -> Workers Comp | S53: =Worksheet!C12 -> 45931
B54: ='Monthly Financial Reports'!D51 -> Depreciation | C54: ='Monthly Financial Reports'!BB51 -> 1200 | D54: ='Monthly Financial Reports'!BC51 -> 1200 | E54: ='Monthly Financial Reports'!BD51 -> 1200 | F54: ='Monthly Financial Reports'!BE51 -> 1200 | R54: =Worksheet!B13 -> SaaS | S54: =Worksheet!C13 -> 46174
B55: ='Monthly Financial Reports'!D52 -> Amortization | C55: ='Monthly Financial Reports'!BB52 -> 9000 | D55: ='Monthly Financial Reports'!BC52 -> 9030 | E55: ='Monthly Financial Reports'!BD52 -> 9276 | F55: ='Monthly Financial Reports'!BE52 -> 9564 | R55: =Worksheet!B14 -> Corrections | S55: =Worksheet!C14 -> 46204
B56: ='Monthly Financial Reports'!D53 -> Net Credit Card | C56: ='Monthly Financial Reports'!BB53 -> 0 | D56: ='Monthly Financial Reports'!BC53 -> -3337 | E56: ='Monthly Financial Reports'!BD53 -> 0 | F56: ='Monthly Financial Reports'!BE53 -> 0 | R56: =Worksheet!B15 -> Healthcare Compliance | S56: =Worksheet!C15 -> 46296
B57: ='Monthly Financial Reports'!D54 -> Owner's Draw | C57: ='Monthly Financial Reports'!BB54 -> 0 | D57: ='Monthly Financial Reports'!BC54 -> -493225 | E57: ='Monthly Financial Reports'!BD54 -> -180000 | F57: ='Monthly Financial Reports'!BE54 -> -180000 | R57: =Worksheet!B16 -> Employee Wellness | S57: =Worksheet!C16 -> 46753
B58: ='Monthly Financial Reports'!D55 -> Capital Raise | C58: ='Monthly Financial Reports'!BB55 -> 0 | D58: ='Monthly Financial Reports'!BC55 -> 0 | E58: ='Monthly Financial Reports'!BD55 -> 0 | F58: ='Monthly Financial Reports'!BE55 -> 0 | R58: =Worksheet!B17 -> Data Analytics | S58: =Worksheet!C17 -> 46753
B59: ='Monthly Financial Reports'!D56 -> Loan Principal | C59: ='Monthly Financial Reports'!BB56 -> 0 | D59: ='Monthly Financial Reports'!BC56 -> -30000 | E59: ='Monthly Financial Reports'!BD56 -> 0 | F59: ='Monthly Financial Reports'!BE56 -> 0
C60: ='Monthly Financial Reports'!BB57 -> 0 | D60: ='Monthly Financial Reports'!BC57 -> 0 | E60: ='Monthly Financial Reports'!BD57 -> 0 | F60: ='Monthly Financial Reports'!BE57 -> 0
A61: ='Monthly Financial Reports'!C58 -> Ending Cash | C61: ='Monthly Financial Reports'!BB58 -> 1257232.1 | D61: ='Monthly Financial Reports'!BC58 -> 2602593.6 | E61: ='Monthly Financial Reports'!BD58 -> 11389945 | F61: ='Monthly Financial Reports'!BE58 -> 64205898
C65: ='Monthly Financial Reports'!BB62 -> 2024 | D65: ='Monthly Financial Reports'!BC62 -> 2025 | E65: ='Monthly Financial Reports'!BD62 -> 2026 | F65: ='Monthly Financial Reports'!BE62 -> 2027 | I65: Column 1 | J65: Column 2 | K65: Column 3 | L65: Column 4 | M65: Column 5 | Y65: =Y50 -> 0 | Z65: =Z50 -> 0 | AA65: =AA50 -> 0 | AB65: =AB50 -> 0 | AC65: =AC50 -> 0 | AD65: =AD50 -> 0 | AE65: =AE50 -> 0 | AF65: =AF50 -> 0 | ... BB65: =BB50 -> 0
C66: ='Monthly Financial Reports'!BB63 -> 0 | D66: ='Monthly Financial Reports'!BC63 -> 0 | E66: ='Monthly Financial Reports'!BD63 -> 0 | F66: ='Monthly Financial Reports'!BE63 -> 0 | S66: =Y19 -> 45839 | T66: =Z19 -> 45870 | U66: =AA19 -> 45901 | V66: =AB19 -> 45931 | W66: =AC19 -> 45962 | X66: =AD19 -> 45992 | Y66: =AE19 -> 46023 | Z66: =AF19 -> 46054 | ... AX66: =BD19 -> 0
A67: ='Monthly Financial Reports'!C64 -> ASSETS | C67: ='Monthly Financial Reports'!BB64 -> 1258371 | D67: ='Monthly Financial Reports'!BC64 -> 7514289.2 | E67: ='Monthly Financial Reports'!BD64 -> 42780908 | F67: ='Monthly Financial Reports'!BE64 -> 1.237906e+08 | R67: Net Cash | S67: =Worksheet!M293 -> -121108.29 | T67: =Worksheet!N293 -> -141108.29 | U67: =Worksheet!O293 -> -118108.29 | V67: =Worksheet!P293 -> -171508.29 | W67: =Worksheet!Q293 -> -221908.29 | X67: =Worksheet!R293 -> -299708.29 | Y67: =Worksheet!S293 -> -338565.58 | Z67: =Worksheet!T293 -> -421737.88 | ... AV67: =Worksheet!AP293 -> 1746860.3
A68: ='Monthly Financial Reports'!C65 -> Current Assets | C68: ='Monthly Financial Reports'!BB65 -> 1257232 | D68: ='Monthly Financial Reports'!BC65 -> 7510317.2 | E68: ='Monthly Financial Reports'!BD65 -> 42778136 | F68: ='Monthly Financial Reports'!BE65 -> 1.2378902e+08 | R68: Gross Profit | S68: =Worksheet!M288 -> 73887.308 | T68: =Worksheet!N288 -> 43888.308 | U68: =Worksheet!O288 -> 113485.91 | V68: =Worksheet!P288 -> 179083.51 | W68: =Worksheet!Q288 -> 280279.71 | X68: =Worksheet!R288 -> 339077.51 | Y68: =Worksheet!S288 -> 494604.42 | Z68: =Worksheet!T288 -> 646131.33 | ... AV68: =Worksheet!AP288 -> 2589242.1
B69: ='Monthly Financial Reports'!D66 -> Cash | C69: ='Monthly Financial Reports'!BB66 -> 1257232 | D69: ='Monthly Financial Reports'!BC66 -> 2602593.6 | E69: ='Monthly Financial Reports'!BD66 -> 11389945 | F69: ='Monthly Financial Reports'!BE66 -> 64205898 | R69: Gross Margin | S69: =Worksheet!M289 -> 0.34366893 | T69: =Worksheet!N289 -> 0.27092117 | U69: =Worksheet!O289 -> 0.39820427 | V69: =Worksheet!P289 -> 0.44660142 | W69: =Worksheet!Q289 -> 0.48325087 | X69: =Worksheet!R289 -> 0.49573764 | Y69: =Worksheet!S289 -> 0.51043821 | Z69: =Worksheet!T289 -> 0.51815934 | ... AV69: =Worksheet!AP289 -> 0.54442717
B70: ='Monthly Financial Reports'!D67 -> Accounts Receivable | C70: ='Monthly Financial Reports'!BB67 -> 0 | D70: ='Monthly Financial Reports'!BC67 -> 4907723.6 | E70: ='Monthly Financial Reports'!BD67 -> 31388191 | F70: ='Monthly Financial Reports'!BE67 -> 59583125
A71: ='Monthly Financial Reports'!C68 -> Fixed Assets | C71: ='Monthly Financial Reports'!BB68 -> 1139 | D71: ='Monthly Financial Reports'!BC68 -> 3972 | E71: ='Monthly Financial Reports'!BD68 -> 2772 | F71: ='Monthly Financial Reports'!BE68 -> 1572
C72: ='Monthly Financial Reports'!BB69 -> 0 | D72: ='Monthly Financial Reports'!BC69 -> 0 | E72: ='Monthly Financial Reports'!BD69 -> 0 | F72: ='Monthly Financial Reports'!BE69 -> 0
A73: ='Monthly Financial Reports'!C70 -> LIABILITIES | C73: ='Monthly Financial Reports'!BB70 -> 198133 | D73: ='Monthly Financial Reports'!BC70 -> 2492984.6 | E73: ='Monthly Financial Reports'!BD70 -> 13345037 | F73: ='Monthly Financial Reports'!BE70 -> 33412669
A74: ='Monthly Financial Reports'!C71 -> Current Liabilities | C74: ='Monthly Financial Reports'!BB71 -> 82446 | D74: ='Monthly Financial Reports'!BC71 -> 2446827.6 | E74: ='Monthly Financial Reports'!BD71 -> 13308156 | F74: ='Monthly Financial Reports'!BE71 -> 33385352
B75: ='Monthly Financial Reports'!D72 -> Total Credit Cards | C75: ='Monthly Financial Reports'!BB72 -> 82446 | D75: ='Monthly Financial Reports'!BC72 -> 62258 | E75: ='Monthly Financial Reports'!BD72 -> 62258 | F75: ='Monthly Financial Reports'!BE72 -> 62258
B76: ='Monthly Financial Reports'!D73 -> Accounts Payable | C76: ='Monthly Financial Reports'!BB73 -> 0 | D76: ='Monthly Financial Reports'!BC73 -> 1088115 | E76: ='Monthly Financial Reports'!BD73 -> 4645215 | F76: ='Monthly Financial Reports'!BE73 -> 13913755
B77: ='Monthly Financial Reports'!D74 -> Taxes Payable | C77: ='Monthly Financial Reports'!BB74 -> 0 | D77: ='Monthly Financial Reports'!BC74 -> 1296454.6 | E77: ='Monthly Financial Reports'!BD74 -> 8600683.4 | F77: ='Monthly Financial Reports'!BE74 -> 19409339
A78: ='Monthly Financial Reports'!C75 -> Long-Term Liabilities | C78: ='Monthly Financial Reports'!BB75 -> 115687 | D78: ='Monthly Financial Reports'!BC75 -> 46157 | E78: ='Monthly Financial Reports'!BD75 -> 36881 | F78: ='Monthly Financial Reports'!BE75 -> 27317
C79: ='Monthly Financial Reports'!BB76 -> 0 | D79: ='Monthly Financial Reports'!BC76 -> 0 | E79: ='Monthly Financial Reports'!BD76 -> 0 | F79: ='Monthly Financial Reports'!BE76 -> 0
A80: ='Monthly Financial Reports'!C77 -> EQUITY | C80: ='Monthly Financial Reports'!BB77 -> 1060238 | D80: ='Monthly Financial Reports'!BC77 -> 5021304.5 | E80: ='Monthly Financial Reports'!BD77 -> 29435871 | F80: ='Monthly Financial Reports'!BE77 -> 90377926
B81: ='Monthly Financial Reports'!D78 -> Opening Balance Equity | C81: ='Monthly Financial Reports'!BB78 -> 82500 | D81: ='Monthly Financial Reports'!BC78 -> 82500 | E81: ='Monthly Financial Reports'!BD78 -> 82500 | F81: ='Monthly Financial Reports'!BE78 -> 82500
B82: ='Monthly Financial Reports'!D79 -> Investment By Others | C82: ='Monthly Financial Reports'!BB79 -> 0 | D82: ='Monthly Financial Reports'!BC79 -> 0 | E82: ='Monthly Financial Reports'!BD79 -> 0 | F82: ='Monthly Financial Reports'!BE79 -> 0
B83: ='Monthly Financial Reports'!D80 -> Cumulative Owners Draw | C83: ='Monthly Financial Reports'!BB80 -> 219741 | D83: ='Monthly Financial Reports'!BC80 -> 540881 | E83: ='Monthly Financial Reports'!BD80 -> 720881 | F83: ='Monthly Financial Reports'!BE80 -> 900881
B84: ='Monthly Financial Reports'!D81 -> Balancing | C84: ='Monthly Financial Reports'!BB81 -> -336158 | D84: ='Monthly Financial Reports'!BC81 -> 0 | E84: ='Monthly Financial Reports'!BD81 -> -955399.68 | F84: ='Monthly Financial Reports'!BE81 -> 4295663.2
B85: ='Monthly Financial Reports'!D82 -> Retained Earnings | C85: ='Monthly Financial Reports'!BB82 -> 171158 | D85: ='Monthly Financial Reports'!BC82 -> 796620.92 | E85: ='Monthly Financial Reports'!BD82 -> 25986075 | F85: ='Monthly Financial Reports'!BE82 -> 79842178
B86: ='Monthly Financial Reports'!D83 -> Net Income | C86: ='Monthly Financial Reports'!BB83 -> 922997 | D86: ='Monthly Financial Reports'!BC83 -> 4203880 | E86: ='Monthly Financial Reports'!BD83 -> 3601814.3 | F86: ='Monthly Financial Reports'!BE83 -> 5256704
C87: ='Monthly Financial Reports'!BB84 -> 0 | D87: ='Monthly Financial Reports'!BC84 -> 0 | E87: ='Monthly Financial Reports'!BD84 -> 0 | F87: ='Monthly Financial Reports'!BE84 -> 0
A88: ='Monthly Financial Reports'!C85 -> LIABILITIES AND EQUITY | C88: ='Monthly Financial Reports'!BB85 -> 1258371 | D88: ='Monthly Financial Reports'!BC85 -> 7514289.2 | E88: ='Monthly Financial Reports'!BD85 -> 42780908 | F88: ='Monthly Financial Reports'!BE85 -> 1.237906e+08

Sheet P&L Yearly
B1: Empower Psychological Services LLC
B2: Profit and Loss
C3: Jan - Dec 2023 | D3: Jan - Dec 2024 | E3: Jan - Jun, 2025
B4: Income
B6: Service Income
B7: VA Psychology | C7: 1628431 | D7: 7078847.6 | E7: =3795502.900844+1674943 -> 5470445.9
B8: VA Gen Med | E8: 356918.11
B9: PI | E9: =92010+640000 -> 732010
B10: Total Income | C10: 1628431 | D10: 7078847.6 | E10: 6559374.3
B11: Cost of Goods Sold
B12: Subcontractor Expense
B13: VA Psychology | C13: 1015327.8 | D13: 4160381.3 | E13: 2556020.3
B14: VA Gen Med | E14: 209038.44
B15: PI | E15: 221000
B16: VA Subcontractors Payable | D16: 355892 | E16: 530000
B17: Total Cost of Goods Sold | C17: 1015327.8 | D17: 4516273.3 | E17: 3516058.8
B18: Gross Profit | C18: 613103.21 | D18: 2562574.2 | E18: 3043315.6
B19: Expenses
A20: Mkt | B20: Advertising and Promotion | C20: 10191.54 | D20: 17749.25 | E20: 10202.73
A21: G&A | B21: Automobile Expense | C21: 28127.76 | D21: 26115.07 | E21: 10720.11
A22: G&A | B22: Total Bank Charges | C22: 3981.94 | D22: 6358.04 | E22: 2675.25
A23: Development | B23: Business Development | C23: 198788.63 | D23: 342668.65 | E23: 54988.26
A24: G&A | B24: Computer and Software Expense | C24: 21539.95 | D24: 57555.69 | E24: 43658.29
A25: G&A | B25: Dues and Subscriptions | C25: 53.15 | D25: 1294.15 | E25: 4140.6
A26: Payroll | B26: Freelancers | D26: 8786.54 | E26: 10648.95
A27: G&A | B27: Insurance Expense | C27: 8142.93 | D27: 27466.39 | E27: 24984.22
B28: Legal & Professional Fees | C28: =40861.79+2260 -> 43121.79 | D28: =40819.99+3235 -> 44054.99 | E28: =44768.99+369 -> 45137.99
B29: Meals and Entertainment | C29: 24657.45 | D29: 28976.73 | E29: 22643.86
B30: Office Supplies | C30: 20215.54 | D30: 77828.27 | E30: 32045.78
A31: Payroll | B31: Wages | C31: 28545.04 | D31: 564082.08 | E31: 542190.13 | F31: =E31/4 -> 135547.53
B32: Payroll Processing Fees | D32: 26641.64 | E32: 18868.59
A33: Development | B33: Recruitment expense | C33: 21838 | D33: 17667.5 | E33: 1931.18
B34: Rent Expense | C34: 84448.28 | D34: 214658.98 | E34: 95810
B35: License | C35: 10741.71 | D35: 36851.29 | E35: 27372
B36: Travel Expense | C36: 27218.79 | D36: 70652.63 | E36: 23914.79
B37: Office Expenses | C37: =10668.52+4302+1637 -> 16607.52 | D37: =13071.42+3141+2897 -> 19109.42 | E37: =35939.86+485+1540 -> 37964.86
B38: Total Expenses | C38: 548220.95 | D38: 1588517.2 | E38: 1009897.8
B39: EBITDA | C39: 64882.26 | D39: 974057.01 | E39: 2033417.8
B40: Interest Expense | C40: 9349.68 | D40: 11108.16 | E40: 4500 | F40: =E40/6 -> 750
B41: Depreciation Expense | C41: 5971
B42: Net Income | C42: 49561.58 | D42: 962948.85 | E42: 2028917.8

Sheet Balance Sheet Yearly
A1: Empower Psychological Services LLC
A2: Balance Sheet
B3: 45291 | C3: 45657 | D3: 6/31/24
A4: ASSETS
A5: Current Assets
A6: Total Bank Accounts | B6: 299151.5 | C6: 1257232 | D6: 994791.98
A7: Accounts Receivable | D7: 2314943.3
A8: Total Current Assets | B8: 299151.5 | C8: 1257232 | D8: 3309735.3
A9: Fixed Assets | B9: 1138.62 | C9: 1138.62 | D9: 4572.4
A10: TOTAL ASSETS | B10: 300290.12 | C10: 1258370.6 | D10: 3314307.7
A12: LIABILITIES AND EQUITY
A13: LIABILITIES
A14: Current Liabilities
A15: Total Credit Cards | B15: 66315.64 | C15: 82446.36 | D15: 65257.78
A16: Accounts Payable | C16: 355892 | D16: 530000
A17: Total Current Liabilities | B17: 66315.64 | C17: 438338.36 | D17: 595257.78
A18: Long-Term Liabilities
A19: Chase LoC - 9001 | B19: 39432.74 | C19: 33186.83 | D19: -1813.17
A20: EIDL Loan | B20: 82500 | C20: 82500 | D20: 82500
A21: Total Long-Term Liabilities | B21: 121932.74 | C21: 115686.83 | D21: 80686.83
A22: Total Liabilities | B22: 188248.38 | C22: 554025.19 | D22: 675944.61
A23: EQUITY
A24: Opening Balance Equity | B24: -82500
A25: Total Owners Draw | B25: 23384.11 | C25: 429760.94 | D25: 524660.88
A26: Retained Earnings | B26: 121596.05 | C26: 171157.63 | D26: 1134106.5
A27: Net Income | B27: 49561.58 | C27: 962948.85 | D27: 2028917.8 | Z27: ='P&L Yearly'!F42 -> 0
A28: Total Equity | B28: 112041.74 | C28: 704345.54 | D28: 2638363.4
A29: TOTAL LIABILITIES AND EQUITY | B29: 300290.12 | C29: 1258370.7 | D29: 3314308

Sheet Profit and Loss
A1: Empower Psychological Services LLC
A2: Profit and Loss
A3: January 1, 2024 - August 20, 2025
B5: Jan 2024 | C5: Feb 2024 | D5: Mar 2024 | E5: Apr 2024 | F5: May 2024 | G5: Jun 2024 | H5: Jul 2024 | I5: Aug 2024 | J5: Sep 2024 | K5: Oct 2024 | L5: Nov 2024 | M5: Dec 2024 | N5: Jan 2025 | O5: Feb 2025 | P5: Mar 2025 | Q5: Apr 2025 | R5: May 2025 | S5: Jun 2025 | T5: Jul 2025 | U5: Aug 1-20, 2025 | V5: Total
A6: Income
A7: Service Income | B7: =399264.35 -> 399264.35 | C7: =416954.21 -> 416954.21 | D7: =533761.66 -> 533761.66 | E7: =540967.64 -> 540967.64 | F7: =633262.09 -> 633262.09 | G7: =604119.44 -> 604119.44 | H7: =557899.1 -> 557899.1 | I7: =693490.47 -> 693490.47 | J7: =612333.91 -> 612333.91 | K7: =645118.38 -> 645118.38 | L7: =817669.25 -> 817669.25 | M7: =623942.57 -> 623942.57 | N7: =697873.62 -> 697873.62 | O7: =605304.9 -> 605304.9 | P7: =937772.07 -> 937772.07 | Q7: =838502.33 -> 838502.33 | R7: =933092.75 -> 933092.75 | S7: =800555.18 -> 800555.18 | T7: =819947.42 -> 819947.42 | U7: =543496.29 -> 543496.29 | V7: =(((((((((((((((((((B7)+(C7))+(D7))+(E7))+(F7))+(G7))+(H7))+(I7))+(J7))+(K7))+(L7))+(M7))+(N7))+(O7))+(P7))+(Q7))+(R7))+(S7))+(T7))+(U7) -> 13255328
A9: Cost of Goods Sold | B9: =252079.03 -> 252079.03 | C9: =272000.62 -> 272000.62 | D9: =326650.13 -> 326650.13 | E9: =321109.97 -> 321109.97 | F9: =353010.65 -> 353010.65 | G9: =367526.55 -> 367526.55 | H9: =376307.64 -> 376307.64 | I9: =431023.4 -> 431023.4 | J9: =427727.45 -> 427727.45 | K9: =446273.02 -> 446273.02 | L9: =440971.27 -> 440971.27 | M9: =485168.6 -> 485168.6 | N9: =424642.96 -> 424642.96 | O9: =428219.25 -> 428219.25 | P9: =631814.04 -> 631814.04 | Q9: =698068.65 -> 698068.65 | R9: =480884.59 -> 480884.59 | S9: =542321.3 -> 542321.3 | T9: =263158.8 -> 263158.8 | U9: =9765.15 -> 9765.15 | V9: =(((((((((((((((((((B9)+(C9))+(D9))+(E9))+(F9))+(G9))+(H9))+(I9))+(J9))+(K9))+(L9))+(M9))+(N9))+(O9))+(P9))+(Q9))+(R9))+(S9))+(T9))+(U9) -> 7978723.1
A10: Gross Profit | B10: =B7-B9 -> 147185.32 | C10: =C7-C9 -> 144953.59 | D10: =D7-D9 -> 207111.53 | E10: =E7-E9 -> 219857.67 | F10: =F7-F9 -> 280251.44 | G10: =G7-G9 -> 236592.89 | H10: =H7-H9 -> 181591.46 | I10: =I7-I9 -> 262467.07 | ... V10: =V7-V9 -> 5276604.6
B11: =B10/B7 -> 0.36864128 | C11: =C10/C7 -> 0.3476487 | D11: =D10/D7 -> 0.38802249 | E11: =E10/E7 -> 0.40641557 | F11: =F10/F7 -> 0.44255206 | G11: =G10/G7 -> 0.39163264 | H11: =H10/H7 -> 0.32549158 | I11: =I10/I7 -> 0.3784725 | ... V11: =V10/V7 -> 0.39807425
A13: Expenses
A14: Advertising and Promotion | B14: =13370.77 -> 13370.77 | C14: =29.95 -> 29.95 | D14: =2529.95 -> 2529.95 | E14: =29.95 -> 29.95 | F14: =464.95 -> 464.95 | G14: =29.95 -> 29.95 | H14: =131 -> 131 | I14: =29.95 -> 29.95 | J14: =522.72 -> 522.72 | K14: =29.95 -> 29.95 | L14: =367.6 -> 367.6 | M14: =212.51 -> 212.51 | N14: =153.52 -> 153.52 | O14: =373.95 -> 373.95 | P14: =9081.26 -> 9081.26 | Q14: =229.95 -> 229.95 | R14: =134.1 -> 134.1 | S14: =229.95 -> 229.95 | T14: =119.3 -> 119.3 | U14: =155.97 -> 155.97 | V14: =(((((((((((((((((((B14)+(C14))+(D14))+(E14))+(F14))+(G14))+(H14))+(I14))+(J14))+(K14))+(L14))+(M14))+(N14))+(O14))+(P14))+(Q14))+(R14))+(S14))+(T14))+(U14) -> 28227.25
A15: Automobile Expense | V15: =(((((((((((((((((((B15)+(C15))+(D15))+(E15))+(F15))+(G15))+(H15))+(I15))+(J15))+(K15))+(L15))+(M15))+(N15))+(O15))+(P15))+(Q15))+(R15))+(S15))+(T15))+(U15) -> 0
A16: Fuel / Gas | B16: =363.12 -> 363.12 | C16: =207.2 -> 207.2 | D16: =298.66 -> 298.66 | E16: =350.53 -> 350.53 | F16: =404.61 -> 404.61 | G16: =204.18 -> 204.18 | H16: =213.67 -> 213.67 | I16: =236.67 -> 236.67 | J16: =329.55 -> 329.55 | K16: =329.98 -> 329.98 | L16: =272.61 -> 272.61 | M16: =289.01 -> 289.01 | N16: =179.27 -> 179.27 | O16: =234.29 -> 234.29 | P16: =280.42 -> 280.42 | Q16: =62.73 -> 62.73 | R16: =137.81 -> 137.81 | S16: =161.3 -> 161.3 | T16: =11.85 -> 11.85 | V16: =(((((((((((((((((((B16)+(C16))+(D16))+(E16))+(F16))+(G16))+(H16))+(I16))+(J16))+(K16))+(L16))+(M16))+(N16))+(O16))+(P16))+(Q16))+(R16))+(S16))+(T16))+(U16) -> 4567.46
A17: Insurance | G17: =1346 -> 1346 | I17: =80.71 -> 80.71 | K17: =62.88 -> 62.88 | M17: =1955 -> 1955 | V17: =(((((((((((((((((((B17)+(C17))+(D17))+(E17))+(F17))+(G17))+(H17))+(I17))+(J17))+(K17))+(L17))+(M17))+(N17))+(O17))+(P17))+(Q17))+(R17))+(S17))+(T17))+(U17) -> 3444.59
A18: Lease | B18: =789.47 -> 789.47 | C18: =789.47 -> 789.47 | D18: =1578.94 -> 1578.94 | F18: =789.47 -> 789.47 | G18: =4831.65 -> 4831.65 | H18: =1562.64 -> 1562.64 | I18: =2360.26 -> 2360.26 | J18: =781.32 -> 781.32 | K18: =1570.79 -> 1570.79 | L18: =2360.26 -> 2360.26 | M18: =781.32 -> 781.32 | N18: =1570.79 -> 1570.79 | O18: =1570.79 -> 1570.79 | P18: =1570.79 -> 1570.79 | Q18: =1570.79 -> 1570.79 | R18: =2360.26 -> 2360.26 | S18: =781.32 -> 781.32 | T18: =1574.39 -> 1574.39 | U18: =1574.39 -> 1574.39 | V18: =(((((((((((((((((((B18)+(C18))+(D18))+(E18))+(F18))+(G18))+(H18))+(I18))+(J18))+(K18))+(L18))+(M18))+(N18))+(O18))+(P18))+(Q18))+(R18))+(S18))+(T18))+(U18) -> 30769.11
A19: Parking / Toll | D19: =25.75 -> 25.75 | G19: =67.75 -> 67.75 | H19: =36.62 -> 36.62 | I19: =57.22 -> 57.22 | M19: =31 -> 31 | N19: =3.35 -> 3.35 | O19: =3 -> 3 | P19: =53.5 -> 53.5 | V19: =(((((((((((((((((((B19)+(C19))+(D19))+(E19))+(F19))+(G19))+(H19))+(I19))+(J19))+(K19))+(L19))+(M19))+(N19))+(O19))+(P19))+(Q19))+(R19))+(S19))+(T19))+(U19) -> 278.19
A20: Repair | B20: =257.72 -> 257.72 | C20: =22 -> 22 | D20: =42.5 -> 42.5 | E20: =29.95 -> 29.95 | F20: =104.94 -> 104.94 | G20: =29.95 -> 29.95 | H20: =29.95 -> 29.95 | I20: =29.95 -> 29.95 | J20: =29.95 -> 29.95 | K20: =29.95 -> 29.95 | L20: =29.95 -> 29.95 | M20: =119.95 -> 119.95 | N20: =49.95 -> 49.95 | O20: =29.95 -> 29.95 | P20: =24.95 -> 24.95 | Q20: =24.95 -> 24.95 | R20: =24.95 -> 24.95 | S20: =24.95 -> 24.95 | T20: =24.95 -> 24.95 | U20: =567.33 -> 567.33 | V20: =(((((((((((((((((((B20)+(C20))+(D20))+(E20))+(F20))+(G20))+(H20))+(I20))+(J20))+(K20))+(L20))+(M20))+(N20))+(O20))+(P20))+(Q20))+(R20))+(S20))+(T20))+(U20) -> 1528.74
A21: Total Automobile Expense | B21: =(((((B15)+(B16))+(B17))+(B18))+(B19))+(B20) -> 1410.31 | C21: =(((((C15)+(C16))+(C17))+(C18))+(C19))+(C20) -> 1018.67 | D21: =(((((D15)+(D16))+(D17))+(D18))+(D19))+(D20) -> 1945.85 | E21: =(((((E15)+(E16))+(E17))+(E18))+(E19))+(E20) -> 380.48 | F21: =(((((F15)+(F16))+(F17))+(F18))+(F19))+(F20) -> 1299.02 | G21: =(((((G15)+(G16))+(G17))+(G18))+(G19))+(G20) -> 6479.53 | H21: =(((((H15)+(H16))+(H17))+(H18))+(H19))+(H20) -> 1842.88 | I21: =(((((I15)+(I16))+(I17))+(I18))+(I19))+(I20) -> 2764.81 | ... U21: =(((((U15)+(U16))+(U17))+(U18))+(U19))+(U20) -> 2141.72 | V21: =(((((((((((((((((((B21)+(C21))+(D21))+(E21))+(F21))+(G21))+(H21))+(I21))+(J21))+(K21))+(L21))+(M21))+(N21))+(O21))+(P21))+(Q21))+(R21))+(S21))+(T21))+(U21) -> 40588.09
A22: Bank Charges | V22: =(((((((((((((((((((B22)+(C22))+(D22))+(E22))+(F22))+(G22))+(H22))+(I22))+(J22))+(K22))+(L22))+(M22))+(N22))+(O22))+(P22))+(Q22))+(R22))+(S22))+(T22))+(U22) -> 0
A23: Bank Service Charges | B23: =854.99 -> 854.99 | C23: =838.2 -> 838.2 | D23: =128.55 -> 128.55 | E23: =55.02 -> 55.02 | F23: =161.06 -> 161.06 | G23: =114.99 -> 114.99 | H23: =809.94 -> 809.94 | I23: =357.42 -> 357.42 | J23: =114.99 -> 114.99 | K23: =114.99 -> 114.99 | L23: =114.99 -> 114.99 | M23: =243.99 -> 243.99 | N23: =854.99 -> 854.99 | O23: =644.99 -> 644.99 | P23: =149.37 -> 149.37 | Q23: =114.99 -> 114.99 | R23: =207.99 -> 207.99 | S23: =125.29 -> 125.29 | T23: =577.44 -> 577.44 | U23: =199.99 -> 199.99 | V23: =(((((((((((((((((((B23)+(C23))+(D23))+(E23))+(F23))+(G23))+(H23))+(I23))+(J23))+(K23))+(L23))+(M23))+(N23))+(O23))+(P23))+(Q23))+(R23))+(S23))+(T23))+(U23) -> 6784.18
A24: Merchant Processing Fee | B24: =323.78 -> 323.78 | C24: =204.44 -> 204.44 | D24: =176.96 -> 176.96 | E24: =162.27 -> 162.27 | F24: =193.07 -> 193.07 | G24: =169.17 -> 169.17 | H24: =216.33 -> 216.33 | I24: =203.18 -> 203.18 | J24: =230.64 -> 230.64 | K24: =129.62 -> 129.62 | L24: =166.73 -> 166.73 | M24: =272.72 -> 272.72 | N24: =15 -> 15 | O24: =139.27 -> 139.27 | P24: =14.62 -> 14.62 | Q24: =115.14 -> 115.14 | R24: =117.39 -> 117.39 | S24: =176.21 -> 176.21 | T24: =44.25 -> 44.25 | U24: =120.45 -> 120.45 | V24: =(((((((((((((((((((B24)+(C24))+(D24))+(E24))+(F24))+(G24))+(H24))+(I24))+(J24))+(K24))+(L24))+(M24))+(N24))+(O24))+(P24))+(Q24))+(R24))+(S24))+(T24))+(U24) -> 3191.24
A25: Total Bank Charges | B25: =((B22)+(B23))+(B24) -> 1178.77 | C25: =((C22)+(C23))+(C24) -> 1042.64 | D25: =((D22)+(D23))+(D24) -> 305.51 | E25: =((E22)+(E23))+(E24) -> 217.29 | F25: =((F22)+(F23))+(F24) -> 354.13 | G25: =((G22)+(G23))+(G24) -> 284.16 | H25: =((H22)+(H23))+(H24) -> 1026.27 | I25: =((I22)+(I23))+(I24) -> 560.6 | ... U25: =((U22)+(U23))+(U24) -> 320.44 | V25: =(((((((((((((((((((B25)+(C25))+(D25))+(E25))+(F25))+(G25))+(H25))+(I25))+(J25))+(K25))+(L25))+(M25))+(N25))+(O25))+(P25))+(Q25))+(R25))+(S25))+(T25))+(U25) -> 9975.42
A26: Business Development | B26: =31809.79 -> 31809.79 | C26: =31887.11 -> 31887.11 | D26: =81045.18 -> 81045.18 | E26: =35985.37 -> 35985.37 | F26: =20466.93 -> 20466.93 | G26: =25487.75 -> 25487.75 | H26: =17059.97 -> 17059.97 | I26: =2488.03 -> 2488.03 | J26: =32706.16 -> 32706.16 | K26: =35944.4 -> 35944.4 | L26: =31077.62 -> 31077.62 | M26: =17583.91 -> 17583.91 | N26: =10652.66 -> 10652.66 | O26: =11518.39 -> 11518.39 | P26: =19118.97 -> 19118.97 | Q26: =10867.2 -> 10867.2 | R26: =875.07 -> 875.07 | S26: =1955.97 -> 1955.97 | T26: =1618.76 -> 1618.76 | V26: =(((((((((((((((((((B26)+(C26))+(D26))+(E26))+(F26))+(G26))+(H26))+(I26))+(J26))+(K26))+(L26))+(M26))+(N26))+(O26))+(P26))+(Q26))+(R26))+(S26))+(T26))+(U26) -> 420149.24
A27: Business Gift | G27: =502.5 -> 502.5 | H27: =92 -> 92 | I27: =2079.24 -> 2079.24 | M27: =223.46 -> 223.46 | U27: =95.25 -> 95.25 | V27: =(((((((((((((((((((B27)+(C27))+(D27))+(E27))+(F27))+(G27))+(H27))+(I27))+(J27))+(K27))+(L27))+(M27))+(N27))+(O27))+(P27))+(Q27))+(R27))+(S27))+(T27))+(U27) -> 2992.45
A28: Charitable Contributions | B28: =1826.73 -> 1826.73 | C28: =706.33 -> 706.33 | D28: =1018.54 -> 1018.54 | E28: =18805.33 -> 18805.33 | F28: =2181.44 -> 2181.44 | G28: =1328.33 -> 1328.33 | H28: =708.33 -> 708.33 | I28: =17345.31 -> 17345.31 | J28: =6036.17 -> 6036.17 | K28: =1114.33 -> 1114.33 | L28: =3101.27 -> 3101.27 | M28: =2204.72 -> 2204.72 | N28: =6679.33 -> 6679.33 | O28: =2678.65 -> 2678.65 | P28: =3699.33 -> 3699.33 | Q28: =1699.33 -> 1699.33 | R28: =1699.33 -> 1699.33 | S28: =1828.08 -> 1828.08 | T28: =14224.33 -> 14224.33 | U28: =200.98 -> 200.98 | V28: =(((((((((((((((((((B28)+(C28))+(D28))+(E28))+(F28))+(G28))+(H28))+(I28))+(J28))+(K28))+(L28))+(M28))+(N28))+(O28))+(P28))+(Q28))+(R28))+(S28))+(T28))+(U28) -> 89086.19
A29: Computer and Software Expense | B29: =4346.45 -> 4346.45 | C29: =2571.18 -> 2571.18 | D29: =1500.56 -> 1500.56 | E29: =5459.11 -> 5459.11 | F29: =3528 -> 3528 | G29: =5188.11 -> 5188.11 | H29: =5272 -> 5272 | I29: =5815.84 -> 5815.84 | J29: =6152.6 -> 6152.6 | K29: =5605.58 -> 5605.58 | L29: =5526.51 -> 5526.51 | M29: =6439.75 -> 6439.75 | N29: =6734.81 -> 6734.81 | O29: =5997.56 -> 5997.56 | P29: =8885.28 -> 8885.28 | Q29: =6488.24 -> 6488.24 | R29: =8638.83 -> 8638.83 | S29: =6913.57 -> 6913.57 | T29: =7328.75 -> 7328.75 | U29: =6069.67 -> 6069.67 | V29: =(((((((((((((((((((B29)+(C29))+(D29))+(E29))+(F29))+(G29))+(H29))+(I29))+(J29))+(K29))+(L29))+(M29))+(N29))+(O29))+(P29))+(Q29))+(R29))+(S29))+(T29))+(U29) -> 114462.4
A30: Consulting | B30: =2010 -> 2010 | C30: =1310 -> 1310 | D30: =1660 -> 1660 | E30: =1660 -> 1660 | F30: =1660 -> 1660 | G30: =1310 -> 1310 | H30: =1985 -> 1985 | I30: =960 -> 960 | J30: =8960 -> 8960 | K30: =14685 -> 14685 | L30: =1860 -> 1860 | M30: =1185 -> 1185 | N30: =1735 -> 1735 | O30: =1510 -> 1510 | P30: =13785 -> 13785 | Q30: =14135 -> 14135 | R30: =2285 -> 2285 | S30: =1510 -> 1510 | T30: =2085 -> 2085 | U30: =225 -> 225 | V30: =(((((((((((((((((((B30)+(C30))+(D30))+(E30))+(F30))+(G30))+(H30))+(I30))+(J30))+(K30))+(L30))+(M30))+(N30))+(O30))+(P30))+(Q30))+(R30))+(S30))+(T30))+(U30) -> 76515
A31: Dues and Subscriptions | B31: =37.74 -> 37.74 | C31: =30.14 -> 30.14 | D31: =51.84 -> 51.84 | E31: =247.25 -> 247.25 | F31: =82.23 -> 82.23 | G31: =60.53 -> 60.53 | H31: =140.33 -> 140.33 | I31: =63.79 -> 63.79 | J31: =222.79 -> 222.79 | K31: =92.59 -> 92.59 | L31: =119.17 -> 119.17 | M31: =145.75 -> 145.75 | N31: =119.17 -> 119.17 | O31: =139.17 -> 139.17 | P31: =91.45 -> 91.45 | Q31: =1423.56 -> 1423.56 | R31: =1189.66 -> 1189.66 | S31: =1177.59 -> 1177.59 | T31: =1254.33 -> 1254.33 | U31: =1147.27 -> 1147.27 | V31: =(((((((((((((((((((B31)+(C31))+(D31))+(E31))+(F31))+(G31))+(H31))+(I31))+(J31))+(K31))+(L31))+(M31))+(N31))+(O31))+(P31))+(Q31))+(R31))+(S31))+(T31))+(U31) -> 7836.35
A32: Education & Training | D32: =40.73 -> 40.73 | E32: =314.94 -> 314.94 | F32: =1393.09 -> 1393.09 | G32: =61.38 -> 61.38 | H32: =1312.95 -> 1312.95 | I32: =10.85 -> 10.85 | J32: =101.17 -> 101.17 | R32: =325.8 -> 325.8 | S32: =43.43 -> 43.43 | T32: =2402.17 -> 2402.17 | U32: =2354.93 -> 2354.93 | V32: =(((((((((((((((((((B32)+(C32))+(D32))+(E32))+(F32))+(G32))+(H32))+(I32))+(J32))+(K32))+(L32))+(M32))+(N32))+(O32))+(P32))+(Q32))+(R32))+(S32))+(T32))+(U32) -> 8361.44
A33: Freelancers | D33: =29.99 -> 29.99 | G33: =3278.55 -> 3278.55 | H33: =5103 -> 5103 | L33: =100 -> 100 | M33: =275 -> 275 | N33: =305 -> 305 | O33: =200 -> 200 | P33: =2273.71 -> 2273.71 | Q33: =2273.33 -> 2273.33 | R33: =2958.33 -> 2958.33 | S33: =2638.58 -> 2638.58 | T33: =2279.45 -> 2279.45 | U33: =1621 -> 1621 | V33: =(((((((((((((((((((B33)+(C33))+(D33))+(E33))+(F33))+(G33))+(H33))+(I33))+(J33))+(K33))+(L33))+(M33))+(N33))+(O33))+(P33))+(Q33))+(R33))+(S33))+(T33))+(U33) -> 23335.94
A34: Insurance Expense | B34: =-328.04 -> -328.04 | C34: =1492.58 -> 1492.58 | J34: =232.64 -> 232.64 | M34: =1984.37 -> 1984.37 | N34: =-118.27 -> -118.27 | O34: =-360 -> -360 | P34: =-240 -> -240 | Q34: =-1775.78 -> -1775.78 | R34: =-120 -> -120 | S34: =1712.19 -> 1712.19 | T34: =-64 -> -64 | V34: =(((((((((((((((((((B34)+(C34))+(D34))+(E34))+(F34))+(G34))+(H34))+(I34))+(J34))+(K34))+(L34))+(M34))+(N34))+(O34))+(P34))+(Q34))+(R34))+(S34))+(T34))+(U34) -> 2415.69
A35: Health Insurance | B35: =3243.04 -> 3243.04 | C35: =1621.52 -> 1621.52 | D35: =1621.52 -> 1621.52 | E35: =1621.52 -> 1621.52 | F35: =1621.52 -> 1621.52 | G35: =1621.52 -> 1621.52 | H35: =1621.52 -> 1621.52 | I35: =1621.52 -> 1621.52 | J35: =1621.52 -> 1621.52 | K35: =2204.84 -> 2204.84 | L35: =2832.4 -> 2832.4 | M35: =2832.4 -> 2832.4 | N35: =4924.56 -> 4924.56 | O35: =3878.48 -> 3878.48 | P35: =3878.48 -> 3878.48 | Q35: =4401.52 -> 4401.52 | R35: =4401.52 -> 4401.52 | S35: =4401.52 -> 4401.52 | T35: =4401.52 -> 4401.52 | U35: =583.32 -> 583.32 | V35: =(((((((((((((((((((B35)+(C35))+(D35))+(E35))+(F35))+(G35))+(H35))+(I35))+(J35))+(K35))+(L35))+(M35))+(N35))+(O35))+(P35))+(Q35))+(R35))+(S35))+(T35))+(U35) -> 54955.76
A36: Total Insurance Expense | B36: =(B34)+(B35) -> 2915 | C36: =(C34)+(C35) -> 3114.1 | D36: =(D34)+(D35) -> 1621.52 | E36: =(E34)+(E35) -> 1621.52 | F36: =(F34)+(F35) -> 1621.52 | G36: =(G34)+(G35) -> 1621.52 | H36: =(H34)+(H35) -> 1621.52 | I36: =(I34)+(I35) -> 1621.52 | ... U36: =(U34)+(U35) -> 583.32 | V36: =(((((((((((((((((((B36)+(C36))+(D36))+(E36))+(F36))+(G36))+(H36))+(I36))+(J36))+(K36))+(L36))+(M36))+(N36))+(O36))+(P36))+(Q36))+(R36))+(S36))+(T36))+(U36) -> 57371.45
A37: Interest Expense | B37: =1272.53 -> 1272.53 | C37: =805.39 -> 805.39 | D37: =567 -> 567 | E37: =1070.06 -> 1070.06 | F37: =483.56 -> 483.56 | G37: =820.05 -> 820.05 | H37: =797.06 -> 797.06 | I37: =804.06 -> 804.06 | J37: =1145.47 -> 1145.47 | K37: =1126.52 -> 1126.52 | L37: =1119.16 -> 1119.16 | M37: =1097.3 -> 1097.3 | N37: =750 -> 750 | O37: =750 -> 750 | P37: =750 -> 750 | Q37: =750 -> 750 | R37: =750 -> 750 | S37: =750 -> 750 | T37: =750 -> 750 | U37: =750 -> 750 | V37: =(((((((((((((((((((B37)+(C37))+(D37))+(E37))+(F37))+(G37))+(H37))+(I37))+(J37))+(K37))+(L37))+(M37))+(N37))+(O37))+(P37))+(Q37))+(R37))+(S37))+(T37))+(U37) -> 17108.16
A38: Legal & Professional Fees | C38: =1500 -> 1500 | G38: =74.99 -> 74.99 | O38: =1810 -> 1810 | P38: =4924 -> 4924 | Q38: =1000 -> 1000 | R38: =1000 -> 1000 | S38: =1074.99 -> 1074.99 | T38: =1000 -> 1000 | U38: =1000 -> 1000 | V38: =(((((((((((((((((((B38)+(C38))+(D38))+(E38))+(F38))+(G38))+(H38))+(I38))+(J38))+(K38))+(L38))+(M38))+(N38))+(O38))+(P38))+(Q38))+(R38))+(S38))+(T38))+(U38) -> 13383.98
A39: Meals and Entertainment | B39: =3155.97 -> 3155.97 | C39: =2625.66 -> 2625.66 | D39: =726.32 -> 726.32 | E39: =3997.92 -> 3997.92 | F39: =1550.52 -> 1550.52 | G39: =1426.69 -> 1426.69 | H39: =3065.59 -> 3065.59 | I39: =4097.86 -> 4097.86 | J39: =1723.98 -> 1723.98 | K39: =2669.97 -> 2669.97 | L39: =1184.55 -> 1184.55 | M39: =2751.7 -> 2751.7 | N39: =3355.46 -> 3355.46 | O39: =10215.58 -> 10215.58 | P39: =2522.17 -> 2522.17 | Q39: =1795.35 -> 1795.35 | R39: =1548.47 -> 1548.47 | S39: =3206.83 -> 3206.83 | T39: =3495.41 -> 3495.41 | U39: =1068.65 -> 1068.65 | V39: =(((((((((((((((((((B39)+(C39))+(D39))+(E39))+(F39))+(G39))+(H39))+(I39))+(J39))+(K39))+(L39))+(M39))+(N39))+(O39))+(P39))+(Q39))+(R39))+(S39))+(T39))+(U39) -> 56184.65
A40: Office Supplies | B40: =3612.13 -> 3612.13 | C40: =6040.46 -> 6040.46 | D40: =3807.54 -> 3807.54 | E40: =3338.99 -> 3338.99 | F40: =5484.94 -> 5484.94 | G40: =6860.42 -> 6860.42 | H40: =3911.67 -> 3911.67 | I40: =21658.03 -> 21658.03 | J40: =4745.86 -> 4745.86 | K40: =3220.7 -> 3220.7 | L40: =8879.35 -> 8879.35 | M40: =2249.76 -> 2249.76 | N40: =3621.71 -> 3621.71 | O40: =5781.43 -> 5781.43 | P40: =7703.14 -> 7703.14 | Q40: =4594.84 -> 4594.84 | R40: =5942.62 -> 5942.62 | S40: =4235.13 -> 4235.13 | T40: =3009.45 -> 3009.45 | U40: =8664.39 -> 8664.39 | V40: =(((((((((((((((((((B40)+(C40))+(D40))+(E40))+(F40))+(G40))+(H40))+(I40))+(J40))+(K40))+(L40))+(M40))+(N40))+(O40))+(P40))+(Q40))+(R40))+(S40))+(T40))+(U40) -> 117362.56
A41: Payroll Expenses | V41: =(((((((((((((((((((B41)+(C41))+(D41))+(E41))+(F41))+(G41))+(H41))+(I41))+(J41))+(K41))+(L41))+(M41))+(N41))+(O41))+(P41))+(Q41))+(R41))+(S41))+(T41))+(U41) -> 0
A42: Tax | B42: =5268.78 -> 5268.78 | C42: =5245.14 -> 5245.14 | D42: =8821.21 -> 8821.21 | E42: =5701.58 -> 5701.58 | F42: =8546.22 -> 8546.22 | G42: =10618.83 -> 10618.83 | H42: =12303.78 -> 12303.78 | I42: =12230.63 -> 12230.63 | J42: =12675.69 -> 12675.69 | K42: =14092.79 -> 14092.79 | L42: =14726.53 -> 14726.53 | M42: =28717.74 -> 28717.74 | N42: =18865.63 -> 18865.63 | O42: =18344.5 -> 18344.5 | P42: =21620.93 -> 21620.93 | Q42: =23622.08 -> 23622.08 | R42: =23376.66 -> 23376.66 | S42: =26812.21 -> 26812.21 | T42: =36670.01 -> 36670.01 | U42: =18040.58 -> 18040.58 | V42: =(((((((((((((((((((B42)+(C42))+(D42))+(E42))+(F42))+(G42))+(H42))+(I42))+(J42))+(K42))+(L42))+(M42))+(N42))+(O42))+(P42))+(Q42))+(R42))+(S42))+(T42))+(U42) -> 326301.52
A43: Wages | B43: =15650.38 -> 15650.38 | C43: =17449.18 -> 17449.18 | D43: =28633.5 -> 28633.5 | E43: =18773.71 -> 18773.71 | F43: =28160.25 -> 28160.25 | G43: =34666.05 -> 34666.05 | H43: =36587.35 -> 36587.35 | I43: =44037.11 -> 44037.11 | J43: =39206.51 -> 39206.51 | K43: =43647.15 -> 43647.15 | L43: =45269.91 -> 45269.91 | M43: =73052.06 -> 73052.06 | N43: =58123.54 -> 58123.54 | O43: =55038.01 -> 55038.01 | P43: =72051.76 -> 72051.76 | Q43: =104331.2 -> 104331.2 | R43: =71353.64 -> 71353.64 | S43: =78649.97 -> 78649.97 | T43: =320062.99 -> 320062.99 | U43: =251481.6 -> 251481.6 | V43: =(((((((((((((((((((B43)+(C43))+(D43))+(E43))+(F43))+(G43))+(H43))+(I43))+(J43))+(K43))+(L43))+(M43))+(N43))+(O43))+(P43))+(Q43))+(R43))+(S43))+(T43))+(U43) -> 1436225.9
A44: Total Payroll Expenses | B44: =((B41)+(B42))+(B43) -> 20919.16 | C44: =((C41)+(C42))+(C43) -> 22694.32 | D44: =((D41)+(D42))+(D43) -> 37454.71 | E44: =((E41)+(E42))+(E43) -> 24475.29 | F44: =((F41)+(F42))+(F43) -> 36706.47 | G44: =((G41)+(G42))+(G43) -> 45284.88 | H44: =((H41)+(H42))+(H43) -> 48891.13 | I44: =((I41)+(I42))+(I43) -> 56267.74 | ... U44: =((U41)+(U42))+(U43) -> 269522.18 | V44: =(((((((((((((((((((B44)+(C44))+(D44))+(E44))+(F44))+(G44))+(H44))+(I44))+(J44))+(K44))+(L44))+(M44))+(N44))+(O44))+(P44))+(Q44))+(R44))+(S44))+(T44))+(U44) -> 1762527.4
A45: Payroll Processing Fees | B45: =850.25 -> 850.25 | C45: =981.46 -> 981.46 | D45: =850.25 -> 850.25 | E45: =4826.17 -> 4826.17 | F45: =2471.68 -> 2471.68 | G45: =2374.9 -> 2374.9 | H45: =3519.41 -> 3519.41 | I45: =722.48 -> 722.48 | J45: =2502.14 -> 2502.14 | K45: =2471.81 -> 2471.81 | L45: =2434.69 -> 2434.69 | M45: =2636.4 -> 2636.4 | N45: =2534.09 -> 2534.09 | O45: =2260.46 -> 2260.46 | P45: =3590.85 -> 3590.85 | Q45: =3128.06 -> 3128.06 | R45: =3584.07 -> 3584.07 | S45: =3771.06 -> 3771.06 | T45: =4111.72 -> 4111.72 | U45: =1975.8 -> 1975.8 | V45: =(((((((((((((((((((B45)+(C45))+(D45))+(E45))+(F45))+(G45))+(H45))+(I45))+(J45))+(K45))+(L45))+(M45))+(N45))+(O45))+(P45))+(Q45))+(R45))+(S45))+(T45))+(U45) -> 51597.75
A46: Recruitment expense | B46: =3066.26 -> 3066.26 | C46: =449.6 -> 449.6 | D46: =757.34 -> 757.34 | E46: =7342.44 -> 7342.44 | F46: =4491.35 -> 4491.35 | G46: =136.84 -> 136.84 | H46: =130.32 -> 130.32 | I46: =149.62 -> 149.62 | J46: =390.96 -> 390.96 | K46: =201.54 -> 201.54 | L46: =290.59 -> 290.59 | M46: =260.64 -> 260.64 | N46: =170.64 -> 170.64 | O46: =260.64 -> 260.64 | P46: =260.64 -> 260.64 | Q46: =300.96 -> 300.96 | R46: =547.34 -> 547.34 | S46: =390.96 -> 390.96 | T46: =302.76 -> 302.76 | U46: =392.76 -> 392.76 | V46: =(((((((((((((((((((B46)+(C46))+(D46))+(E46))+(F46))+(G46))+(H46))+(I46))+(J46))+(K46))+(L46))+(M46))+(N46))+(O46))+(P46))+(Q46))+(R46))+(S46))+(T46))+(U46) -> 20294.2
A47: Rent Expense | B47: =10358.35 -> 10358.35 | C47: =10400.66 -> 10400.66 | D47: =10361.13 -> 10361.13 | E47: =12671.32 -> 12671.32 | F47: =10817.1 -> 10817.1 | G47: =11420.34 -> 11420.34 | H47: =12388.04 -> 12388.04 | I47: =11103.06 -> 11103.06 | J47: =11113.61 -> 11113.61 | K47: =11371.55 -> 11371.55 | L47: =8337.16 -> 8337.16 | M47: =18359.26 -> 18359.26 | N47: =11309.79 -> 11309.79 | O47: =11498.27 -> 11498.27 | P47: =4067.48 -> 4067.48 | Q47: =12903 -> 12903 | R47: =20203.35 -> 20203.35 | S47: =11447.91 -> 11447.91 | T47: =13157.96 -> 13157.96 | U47: =8614.09 -> 8614.09 | V47: =(((((((((((((((((((B47)+(C47))+(D47))+(E47))+(F47))+(G47))+(H47))+(I47))+(J47))+(K47))+(L47))+(M47))+(N47))+(O47))+(P47))+(Q47))+(R47))+(S47))+(T47))+(U47) -> 231903.43
A48: Rent Expense Israel | B48: =728 -> 728 | C48: =7278 -> 7278 | D48: =10671.4 -> 10671.4 | E48: =3626 -> 3626 | F48: =15922 -> 15922 | G48: =4230 -> 4230 | H48: =10361 -> 10361 | I48: =3909 -> 3909 | J48: =3997 -> 3997 | K48: =8022 -> 8022 | L48: =224 -> 224 | M48: =6989 -> 6989 | N48: =8105.2 -> 8105.2 | P48: =8172 -> 8172 | R48: =3815 -> 3815 | S48: =4288 -> 4288 | U48: =3989 -> 3989 | V48: =(((((((((((((((((((B48)+(C48))+(D48))+(E48))+(F48))+(G48))+(H48))+(I48))+(J48))+(K48))+(L48))+(M48))+(N48))+(O48))+(P48))+(Q48))+(R48))+(S48))+(T48))+(U48) -> 104326.6
A49: Repairs and Maintenance | P49: =484.95 -> 484.95 | V49: =(((((((((((((((((((B49)+(C49))+(D49))+(E49))+(F49))+(G49))+(H49))+(I49))+(J49))+(K49))+(L49))+(M49))+(N49))+(O49))+(P49))+(Q49))+(R49))+(S49))+(T49))+(U49) -> 484.95
A50: Security Expense | J50: =2.5 -> 2.5 | L50: =2.5 -> 2.5 | O50: =5 -> 5 | V50: =(((((((((((((((((((B50)+(C50))+(D50))+(E50))+(F50))+(G50))+(H50))+(I50))+(J50))+(K50))+(L50))+(M50))+(N50))+(O50))+(P50))+(Q50))+(R50))+(S50))+(T50))+(U50) -> 10
A51: Shipping & Postage | I51: =153.61 -> 153.61 | V51: =(((((((((((((((((((B51)+(C51))+(D51))+(E51))+(F51))+(G51))+(H51))+(I51))+(J51))+(K51))+(L51))+(M51))+(N51))+(O51))+(P51))+(Q51))+(R51))+(S51))+(T51))+(U51) -> 153.61
A52: Small Medical Equipment | R52: =45 -> 45 | V52: =(((((((((((((((((((B52)+(C52))+(D52))+(E52))+(F52))+(G52))+(H52))+(I52))+(J52))+(K52))+(L52))+(M52))+(N52))+(O52))+(P52))+(Q52))+(R52))+(S52))+(T52))+(U52) -> 45
A53: Taxes & License | B53: =-121.9 -> -121.9 | D53: =9339.13 -> 9339.13 | E53: =25088.7 -> 25088.7 | G53: =850 -> 850 | H53: =425 -> 425 | K53: =474 -> 474 | L53: =594 -> 594 | M53: =202.36 -> 202.36 | P53: =26990 -> 26990 | Q53: =450000 -> 450000 | R53: =75 -> 75 | S53: =307 -> 307 | T53: =225 -> 225 | V53: =(((((((((((((((((((B53)+(C53))+(D53))+(E53))+(F53))+(G53))+(H53))+(I53))+(J53))+(K53))+(L53))+(M53))+(N53))+(O53))+(P53))+(Q53))+(R53))+(S53))+(T53))+(U53) -> 514448.29
A54: Team Morale | E54: =1250 -> 1250 | F54: =6500 -> 6500 | K54: =1053.36 -> 1053.36 | L54: =4109.45 -> 4109.45 | V54: =(((((((((((((((((((B54)+(C54))+(D54))+(E54))+(F54))+(G54))+(H54))+(I54))+(J54))+(K54))+(L54))+(M54))+(N54))+(O54))+(P54))+(Q54))+(R54))+(S54))+(T54))+(U54) -> 12912.81
A55: Travel Expense | B55: =17.35 -> 17.35 | C55: =516.62 -> 516.62 | D55: =61.99 -> 61.99 | E55: =1172.11 -> 1172.11 | F55: =174.51 -> 174.51 | G55: =11421.2 -> 11421.2 | H55: =8693.91 -> 8693.91 | I55: =7707.99 -> 7707.99 | J55: =2855.46 -> 2855.46 | L55: =107.51 -> 107.51 | M55: =2369.38 -> 2369.38 | N55: =428.72 -> 428.72 | O55: =2392.2 -> 2392.2 | P55: =2418.1 -> 2418.1 | R55: =4000 -> 4000 | T55: =10925.97 -> 10925.97 | V55: =(((((((((((((((((((B55)+(C55))+(D55))+(E55))+(F55))+(G55))+(H55))+(I55))+(J55))+(K55))+(L55))+(M55))+(N55))+(O55))+(P55))+(Q55))+(R55))+(S55))+(T55))+(U55) -> 55263.02
A56: Airfare | B56: =3211.24 -> 3211.24 | C56: =2604.44 -> 2604.44 | D56: =254 -> 254 | E56: =219.45 -> 219.45 | F56: =4473.48 -> 4473.48 | G56: =2083.8 -> 2083.8 | H56: =1206.93 -> 1206.93 | I56: =2157.68 -> 2157.68 | J56: =2227.87 -> 2227.87 | K56: =1965.48 -> 1965.48 | L56: =505.09 -> 505.09 | M56: =3851.11 -> 3851.11 | N56: =4099.7 -> 4099.7 | O56: =4842.57 -> 4842.57 | P56: =188.94 -> 188.94 | Q56: =218.36 -> 218.36 | R56: =471.46 -> 471.46 | S56: =438.54 -> 438.54 | T56: =6690.9 -> 6690.9 | U56: =35 -> 35 | V56: =(((((((((((((((((((B56)+(C56))+(D56))+(E56))+(F56))+(G56))+(H56))+(I56))+(J56))+(K56))+(L56))+(M56))+(N56))+(O56))+(P56))+(Q56))+(R56))+(S56))+(T56))+(U56) -> 41746.04
A57: Hotel & Lodging | B57: =703.18 -> 703.18 | C57: =-431.06 -> -431.06 | F57: =390.82 -> 390.82 | G57: =2386.78 -> 2386.78 | H57: =878.37 -> 878.37 | I57: =361.3 -> 361.3 | J57: =129.2 -> 129.2 | K57: =691.99 -> 691.99 | L57: =1790.28 -> 1790.28 | M57: =676.42 -> 676.42 | N57: =526.78 -> 526.78 | O57: =487.49 -> 487.49 | P57: =1397.45 -> 1397.45 | Q57: =468.3 -> 468.3 | R57: =191.48 -> 191.48 | S57: =24.99 -> 24.99 | T57: =367.34 -> 367.34 | U57: =24.99 -> 24.99 | V57: =(((((((((((((((((((B57)+(C57))+(D57))+(E57))+(F57))+(G57))+(H57))+(I57))+(J57))+(K57))+(L57))+(M57))+(N57))+(O57))+(P57))+(Q57))+(R57))+(S57))+(T57))+(U57) -> 11066.1
A58: Other | O58: =15.05 -> 15.05 | V58: =(((((((((((((((((((B58)+(C58))+(D58))+(E58))+(F58))+(G58))+(H58))+(I58))+(J58))+(K58))+(L58))+(M58))+(N58))+(O58))+(P58))+(Q58))+(R58))+(S58))+(T58))+(U58) -> 15.05
A59: Taxi / Car Rental | C59: =354.8 -> 354.8 | E59: =143.49 -> 143.49 | G59: =443.71 -> 443.71 | H59: =325.4 -> 325.4 | I59: =1067.13 -> 1067.13 | K59: =610.38 -> 610.38 | M59: =271.84 -> 271.84 | N59: =20.43 -> 20.43 | O59: =1108.78 -> 1108.78 | Q59: =85 -> 85 | S59: =90.45 -> 90.45 | T59: =13.93 -> 13.93 | U59: =56.54 -> 56.54 | V59: =(((((((((((((((((((B59)+(C59))+(D59))+(E59))+(F59))+(G59))+(H59))+(I59))+(J59))+(K59))+(L59))+(M59))+(N59))+(O59))+(P59))+(Q59))+(R59))+(S59))+(T59))+(U59) -> 4591.88
A60: Total Travel Expense | B60: =((((B55)+(B56))+(B57))+(B58))+(B59) -> 3931.77 | C60: =((((C55)+(C56))+(C57))+(C58))+(C59) -> 3044.8 | D60: =((((D55)+(D56))+(D57))+(D58))+(D59) -> 315.99 | E60: =((((E55)+(E56))+(E57))+(E58))+(E59) -> 1535.05 | F60: =((((F55)+(F56))+(F57))+(F58))+(F59) -> 5038.81 | G60: =((((G55)+(G56))+(G57))+(G58))+(G59) -> 16335.49 | H60: =((((H55)+(H56))+(H57))+(H58))+(H59) -> 11104.61 | I60: =((((I55)+(I56))+(I57))+(I58))+(I59) -> 11294.1 | ... U60: =((((U55)+(U56))+(U57))+(U58))+(U59) -> 116.53 | V60: =(((((((((((((((((((B60)+(C60))+(D60))+(E60))+(F60))+(G60))+(H60))+(I60))+(J60))+(K60))+(L60))+(M60))+(N60))+(O60))+(P60))+(Q60))+(R60))+(S60))+(T60))+(U60) -> 112682.09
A61: Uncategorized Expense | B61: =652.87 -> 652.87 | C61: =295.41 -> 295.41 | D61: =-22939 -> -22939 | E61: =3574.39 -> 3574.39 | J61: =-2499.14 -> -2499.14 | M61: =41.9 -> 41.9 | N61: =28634.56 -> 28634.56 | O61: =271153.34 -> 271153.34 | P61: =-10633.6 -> -10633.6 | Q61: =16034.95 -> 16034.95 | R61: =-111060.24 -> -111060.24 | S61: =81760.85 -> 81760.85 | T61: =147296.55 -> 147296.55 | U61: =3925.71 -> 3925.71 | V61: =(((((((((((((((((((B61)+(C61))+(D61))+(E61))+(F61))+(G61))+(H61))+(I61))+(J61))+(K61))+(L61))+(M61))+(N61))+(O61))+(P61))+(Q61))+(R61))+(S61))+(T61))+(U61) -> 406238.55
A62: Utilities | V62: =(((((((((((((((((((B62)+(C62))+(D62))+(E62))+(F62))+(G62))+(H62))+(I62))+(J62))+(K62))+(L62))+(M62))+(N62))+(O62))+(P62))+(Q62))+(R62))+(S62))+(T62))+(U62) -> 0
A63: Phone/Internet | C63: =529.54 -> 529.54 | E63: =503.67 -> 503.67 | F63: =472.6 -> 472.6 | I63: =790.8 -> 790.8 | K63: =330.76 -> 330.76 | L63: =256.62 -> 256.62 | M63: =256.63 -> 256.63 | N63: =256.63 -> 256.63 | O63: =256.68 -> 256.68 | P63: =256.68 -> 256.68 | Q63: =256.68 -> 256.68 | R63: =256.68 -> 256.68 | S63: =256.68 -> 256.68 | T63: =256.68 -> 256.68 | U63: =293.7 -> 293.7 | V63: =(((((((((((((((((((B63)+(C63))+(D63))+(E63))+(F63))+(G63))+(H63))+(I63))+(J63))+(K63))+(L63))+(M63))+(N63))+(O63))+(P63))+(Q63))+(R63))+(S63))+(T63))+(U63) -> 5231.03
A64: Total Utilities | B64: =(B62)+(B63) -> 0 | C64: =(C62)+(C63) -> 529.54 | D64: =(D62)+(D63) -> 0 | E64: =(E62)+(E63) -> 503.67 | F64: =(F62)+(F63) -> 472.6 | G64: =(G62)+(G63) -> 0 | H64: =(H62)+(H63) -> 0 | I64: =(I62)+(I63) -> 790.8 | ... U64: =(U62)+(U63) -> 293.7 | V64: =(((((((((((((((((((B64)+(C64))+(D64))+(E64))+(F64))+(G64))+(H64))+(I64))+(J64))+(K64))+(L64))+(M64))+(N64))+(O64))+(P64))+(Q64))+(R64))+(S64))+(T64))+(U64) -> 5231.03
A65: Website Expense | D65: =150 -> 150 | V65: =(((((((((((((((((((B65)+(C65))+(D65))+(E65))+(F65))+(G65))+(H65))+(I65))+(J65))+(K65))+(L65))+(M65))+(N65))+(O65))+(P65))+(Q65))+(R65))+(S65))+(T65))+(U65) -> 150
A66: Total Expenses | B66: =((((((((((((((((((((((((((((((B14)+(B21))+(B25))+(B26))+(B27))+(B28))+(B29))+(B30))+(B31))+(B32))+(B33))+(B36))+(B37))+(B38))+(B39))+(B40))+(B44))+(B45))+(B46))+(B47))+(B48))+(B49))+(B50))+(B51))+(B52))+(B53))+(B54))+(B60))+(B61))+(B64))+(B65) -> 107330.95 | C66: =((((((((((((((((((((((((((((((C14)+(C21))+(C25))+(C26))+(C27))+(C28))+(C29))+(C30))+(C31))+(C32))+(C33))+(C36))+(C37))+(C38))+(C39))+(C40))+(C44))+(C45))+(C46))+(C47))+(C48))+(C49))+(C50))+(C51))+(C52))+(C53))+(C54))+(C60))+(C61))+(C64))+(C65) -> 98355.42 | D66: =((((((((((((((((((((((((((((((D14)+(D21))+(D25))+(D26))+(D27))+(D28))+(D29))+(D30))+(D31))+(D32))+(D33))+(D36))+(D37))+(D38))+(D39))+(D40))+(D44))+(D45))+(D46))+(D47))+(D48))+(D49))+(D50))+(D51))+(D52))+(D53))+(D54))+(D60))+(D61))+(D64))+(D65) -> 143811.48 | E66: =((((((((((((((((((((((((((((((E14)+(E21))+(E25))+(E26))+(E27))+(E28))+(E29))+(E30))+(E31))+(E32))+(E33))+(E36))+(E37))+(E38))+(E39))+(E40))+(E44))+(E45))+(E46))+(E47))+(E48))+(E49))+(E50))+(E51))+(E52))+(E53))+(E54))+(E60))+(E61))+(E64))+(E65) -> 158021.24 | F66: =((((((((((((((((((((((((((((((F14)+(F21))+(F25))+(F26))+(F27))+(F28))+(F29))+(F30))+(F31))+(F32))+(F33))+(F36))+(F37))+(F38))+(F39))+(F40))+(F44))+(F45))+(F46))+(F47))+(F48))+(F49))+(F50))+(F51))+(F52))+(F53))+(F54))+(F60))+(F61))+(F64))+(F65) -> 122990.34 | G66: =((((((((((((((((((((((((((((((G14)+(G21))+(G25))+(G26))+(G27))+(G28))+(G29))+(G30))+(G31))+(G32))+(G33))+(G36))+(G37))+(G38))+(G39))+(G40))+(G44))+(G45))+(G46))+(G47))+(G48))+(G49))+(G50))+(G51))+(G52))+(G53))+(G54))+(G60))+(G61))+(G64))+(G65) -> 135446.91 | H66: =((((((((((((((((((((((((((((((H14)+(H21))+(H25))+(H26))+(H27))+(H28))+(H29))+(H30))+(H31))+(H32))+(H33))+(H36))+(H37))+(H38))+(H39))+(H40))+(H44))+(H45))+(H46))+(H47))+(H48))+(H49))+(H50))+(H51))+(H52))+(H53))+(H54))+(H60))+(H61))+(H64))+(H65) -> 130889.08 | I66: =((((((((((((((((((((((((((((((I14)+(I21))+(I25))+(I26))+(I27))+(I28))+(I29))+(I30))+(I31))+(I32))+(I33))+(I36))+(I37))+(I38))+(I39))+(I40))+(I44))+(I45))+(I46))+(I47))+(I48))+(I49))+(I50))+(I51))+(I52))+(I53))+(I54))+(I60))+(I61))+(I64))+(I65) -> 144690.3 | ... U66: =((((((((((((((((((((((((((((((U14)+(U21))+(U25))+(U26))+(U27))+(U28))+(U29))+(U30))+(U31))+(U32))+(U33))+(U36))+(U37))+(U38))+(U39))+(U40))+(U44))+(U45))+(U46))+(U47))+(U48))+(U49))+(U50))+(U51))+(U52))+(U53))+(U54))+(U60))+(U61))+(U64))+(U65) -> 315228.36 | V66: =(((((((((((((((((((B66)+(C66))+(D66))+(E66))+(F66))+(G66))+(H66))+(I66))+(J66))+(K66))+(L66))+(M66))+(N66))+(O66))+(P66))+(Q66))+(R66))+(S66))+(T66))+(U66) -> 4305946.3
A67: Net Operating Income | B67: =(B10)-(B66) -> 39854.37 | C67: =(C10)-(C66) -> 46598.17 | D67: =(D10)-(D66) -> 63300.05 | E67: =(E10)-(E66) -> 61836.43 | F67: =(F10)-(F66) -> 157261.1 | G67: =(G10)-(G66) -> 101145.98 | H67: =(H10)-(H66) -> 50702.38 | I67: =(I10)-(I66) -> 117776.77 | ... U67: =(U10)-(U66) -> 218502.78 | V67: =(((((((((((((((((((B67)+(C67))+(D67))+(E67))+(F67))+(G67))+(H67))+(I67))+(J67))+(K67))+(L67))+(M67))+(N67))+(O67))+(P67))+(Q67))+(R67))+(S67))+(T67))+(U67) -> 970658.29
A68: Other Expenses
A69: charity | T69: =100 -> 100 | V69: =(((((((((((((((((((B69)+(C69))+(D69))+(E69))+(F69))+(G69))+(H69))+(I69))+(J69))+(K69))+(L69))+(M69))+(N69))+(O69))+(P69))+(Q69))+(R69))+(S69))+(T69))+(U69) -> 100
A70: Total Other Expenses | B70: =B69 -> 0 | C70: =C69 -> 0 | D70: =D69 -> 0 | E70: =E69 -> 0 | F70: =F69 -> 0 | G70: =G69 -> 0 | H70: =H69 -> 0 | I70: =I69 -> 0 | ... U70: =U69 -> 0 | V70: =(((((((((((((((((((B70)+(C70))+(D70))+(E70))+(F70))+(G70))+(H70))+(I70))+(J70))+(K70))+(L70))+(M70))+(N70))+(O70))+(P70))+(Q70))+(R70))+(S70))+(T70))+(U70) -> 100
A71: Net Other Income | B71: =(0)-(B70) -> 0 | C71: =(0)-(C70) -> 0 | D71: =(0)-(D70) -> 0 | E71: =(0)-(E70) -> 0 | F71: =(0)-(F70) -> 0 | G71: =(0)-(G70) -> 0 | H71: =(0)-(H70) -> 0 | I71: =(0)-(I70) -> 0 | ... U71: =(0)-(U70) -> 0 | V71: =(((((((((((((((((((B71)+(C71))+(D71))+(E71))+(F71))+(G71))+(H71))+(I71))+(J71))+(K71))+(L71))+(M71))+(N71))+(O71))+(P71))+(Q71))+(R71))+(S71))+(T71))+(U71) -> -100
A72: Net Income | B72: =(B67)+(B71) -> 39854.37 | C72: =(C67)+(C71) -> 46598.17 | D72: =(D67)+(D71) -> 63300.05 | E72: =(E67)+(E71) -> 61836.43 | F72: =(F67)+(F71) -> 157261.1 | G72: =(G67)+(G71) -> 101145.98 | H72: =(H67)+(H71) -> 50702.38 | I72: =(I67)+(I71) -> 117776.77 | ... V72: =(V67)+(V71) -> 970558.29
B73: =B72/B7 -> 0.099819506 | C73: =C72/C7 -> 0.11175848 | D73: =D72/D7 -> 0.11859235 | E73: =E72/E7 -> 0.11430708 | F73: =F72/F7 -> 0.24833494 | G73: =G72/G7 -> 0.16742712 | H73: =H72/H7 -> 0.090880914 | I73: =I72/I7 -> 0.16983185 | ... V73: =V72/V7 -> 0.073220241
A76: Wednesday, Aug 20, 2025 05:06:27 PM GMT-7 - Accrual Basis

Sheet HR Comp
A1: Gusto Employee Information
A2: Empower Psychological Services, PLLC
A3: Printed on | B3: 45889
A5: Last | B5: First | C5: Start Date | D5: Termination Date | E5: Job Title | F5: Compensation Amount | G5: Compensation Unit
A6: Blech | B6: Benzion | C6: 45717 | E6: Chief Technology Officer | F6: 120000 | G6: year
A7: Chapman | B7: Chelsea | C7: 45708 | E7: Clinical CoordinatorÊ | F7: 53000 | G7: year
A8: Cohen | B8: Shmuel | C8: 45139 | E8: Director of Business Development | F8: 200000 | G8: year
A9: Craft | B9: Sherry | C9: 45658 | E9: Chief Clinical Officer | F9: 150000 | G9: year
A10: David | B10: Aviva | C10: 45335 | E10: Strategic Growth ManagerÊ | F10: 82500 | G10: year
A11: Dodson | B11: Josie | C11: 45628 | E11: HR Director | F11: 95000 | G11: year
A12: Gallegos | B12: Martha | C12: 45826 | E12: PI Case Manager | F12: 57000 | G12: year
A13: Kanter | B13: Jesse | C13: 45599 | E13: IT Solutions Engineer | F13: 75000 | G13: year
A14: Kawasaki | B14: Bailey | C14: 45552 | E14: Office Manager | F14: 44000 | G14: year
A15: Kessler | B15: Yaakov | C15: 45152 | E15: Director of Operations | F15: 102000 | G15: year
A16: Kluger | B16: Kasiah | C16: 45444 | E16: Strategic Growth Manager | F16: 70000 | G16: year
A17: Kulfan | B17: Jaclyn | C17: 45741 | E17: Director of Operations PI Division | F17: 135000 | G17: year
... A22: Tutrone | B22: Taylor | C22: 45866 | E22: Site Acquisition Specialist | F22: 56000 | G22: year
A23: Zuckerberg | B23: Beth | C23: 45754 | F23: 125000 | G23: year
A24: Reinstein | B24: Sam | C24: 45597 | E24: CFO | F24: 0

Sheet 12 month
A1: Item | C1: Plan | D1: Current | E1: Additional | F1: Non-Staff | G1: Cost | I1: Section | J1: Non Staff | L1: 1 | M1: 2 | N1: 3 | O1: 4 | P1: 5 | Q1: 6 | R1: 7 | S1: 8 | T1: 9 | U1: 10 | V1: 11
A3: COO | C3: 1 | D3: 1 | E3: =C3-D3 -> 0 | G3: 350000 | I3: Executive Leadership and Strategic Roles | K3: =SUM(L3:S3) -> 350000 | L3: =G3 -> 350000
A4: CFO | C4: 1 | D4: 1 | E4: =C4-D4 -> 0 | G4: 250000 | I4: Executive Leadership and Strategic Roles | K4: =SUM(L4:S4) -> 250000 | L4: =G4 -> 250000
A5: CTO | C5: 1 | D5: 1 | E5: =C5-D5 -> 0 | G5: 300000 | I5: Executive Leadership and Strategic Roles | K5: =SUM(L5:S5) -> 300000 | L5: =G5 -> 300000
A6: CMO | C6: 1 | D6: 0 | E6: =C6-D6 -> 1 | G6: 300000 | I6: Executive Leadership and Strategic Roles | K6: 250000 | L6: =G6 -> 300000
A7: CCO | C7: 1 | D7: 1 | E7: =C7-D7 -> 0 | G7: 250000 | I7: Executive Leadership and Strategic Roles | K7: =SUM(L7:S7) -> 250000 | L7: =G7 -> 250000
C8: =SUM(C3:C7) -> 5 | D8: =SUM(D3:D7) -> 4 | E8: =SUM(E3:E7) -> 1 | G8: =SUM(G3:G7) -> 1450000 | K8: =SUM(K3:K7) -> 1400000
A10: Mktin Operations Manager- 1 | C10: 1 | E10: =C10-D10 -> 1 | G10: 175000 | I10: Business Development & Growth | K10: =SUM(L10:S10) -> 175000 | L10: 175000
A11: Campaign Managers -4 | C11: 4 | E11: =C11-D11 -> 4 | G11: 500000 | I11: Business Development & Growth | K11: =SUM(L11:S11) -> 500000 | L11: 125000 | M11: 125000 | N11: 125000 | O11: 125000
A12: Marketing Ops & CRM Admin | C12: 1 | E12: =C12-D12 -> 1 | G12: 150000 | I12: Business Development & Growth | K12: =SUM(L12:S12) -> 150000 | L12: 150000
A13: PR relations analyst - 1 | C13: 1 | E13: =C13-D13 -> 1 | G13: 100000 | I13: Business Development & Growth | K13: =SUM(L13:S13) -> 100000 | L13: 100000
